Workbook

Sheet README
A1: Rent-vs-buy engine: manual test scenarios
A2: Each scenario sheet re-computes the CLAUDE.md formulas with Excel formulas, year by year, and compares the result with the hand calculation and the Python engine.
A4: Colour legend
A5: Blue text: hardcoded inputs, hand-calculated values and pasted Python engine values.
A6: Black text: Excel formulas. Green text: links to another sheet.
A7: Yellow fill: the key result, Delta(H) = C_R(H) - C_B(H) (positive = buying is cheaper).
A9: Formulas
A10: L = (1-d)P ; i = r/12 ; n = 12T ; M = L i (1+i)^n / ((1+i)^n - 1) (M = L/n if r = 0, 0 if d = 1)
A11: V_t = P(1+g)^t ; B_t = L(1+i)^(12t) - M((1+i)^(12t) - 1)/i, and B_t = 0 once t >= T
A12: O_t = 12M [t <= T] + (tau+m+h) V_(t-1) ; Rent_t = 12R(1+q)^(t-1)
A13: C_B(H) = (d+cb)P + sum O_t/(1+k)^t - (V_H(1-cs) - B_H)/(1+k)^H ; C_R(H) = sum Rent_t/(1+k)^t
A14: Break-even = smallest H in 1..30 with Delta(H) >= 0 ; User cost UC = (k+tau+m+h-g)P vs 12R
... A20: Indicative decision support only – not financial or valuation advice

Sheet Summary
A1: ID | B1: Scenario | C1: Price P | D1: Rent R | E1: H | F1: Payment M | G1: C_B(H) | H1: C_R(H) | I1: Delta(H) | J1: Recommendation | K1: Break-even year | L1: User cost | M1: Checks
A2: S01 | B2: Cash purchase, zero growth, no costs | C2: ='S01'!B4 -> 100000 | D2: ='S01'!B5 -> 500 | E2: ='S01'!B9 -> 1 | F2: ='S01'!E7 -> 0 | G2: ='S01'!E9 -> 0 | H2: ='S01'!E10 -> 6000 | I2: ='S01'!E11 -> 6000 | J2: ='S01'!E12 -> buy | K2: ='S01'!E13 -> 1 | L2: ='S01'!E14 -> 0 | M2: =IF(COUNTIF('S01'!I7:J16,"FAIL")=0,"PASS","FAIL") -> PASS
A3: S02 | B3: Zero growth with running and transaction costs (100% down) | C3: ='S02'!B4 -> 200000 | D3: ='S02'!B5 -> 1000 | E3: ='S02'!B9 -> 5 | F3: ='S02'!E7 -> 0 | G3: ='S02'!E9 -> 38000 | H3: ='S02'!E10 -> 60000 | I3: ='S02'!E11 -> 22000 | J3: ='S02'!E12 -> buy | K3: ='S02'!E13 -> 3 | L3: ='S02'!E14 -> 4000 | M3: =IF(COUNTIF('S02'!I7:J16,"FAIL")=0,"PASS","FAIL") -> PASS
A4: S03 | B4: Interest-free mortgage, holding period shorter than term | C4: ='S03'!B4 -> 120000 | D4: ='S03'!B5 -> 700 | E4: ='S03'!B9 -> 5 | F4: ='S03'!E7 -> 500 | G4: ='S03'!E9 -> 0 | H4: ='S03'!E10 -> 42000 | I4: ='S03'!E11 -> 42000 | J4: ='S03'!E12 -> buy | K4: ='S03'!E13 -> 1 | L4: ='S03'!E14 -> 0 | M4: =IF(COUNTIF('S03'!I7:J16,"FAIL")=0,"PASS","FAIL") -> PASS
A5: S04 | B5: Holding period longer than mortgage term (H > T) | C5: ='S04'!B4 -> 120000 | D5: ='S04'!B5 -> 700 | E5: ='S04'!B9 -> 7 | F5: ='S04'!E7 -> 1500 | G5: ='S04'!E9 -> 0 | H5: ='S04'!E10 -> 58800 | I5: ='S04'!E11 -> 58800 | J5: ='S04'!E12 -> buy | K5: ='S04'!E13 -> 1 | L5: ='S04'!E14 -> 0 | M5: =IF(COUNTIF('S04'!I7:J16,"FAIL")=0,"PASS","FAIL") -> PASS
A6: S05 | B6: 100% down payment with appreciation and discounting | C6: ='S05'!B4 -> 100000 | D6: ='S05'!B5 -> 1000 | E6: ='S05'!B9 -> 2 | F6: ='S05'!E7 -> 0 | G6: ='S05'!E9 -> 0 | H6: ='S05'!E10 -> 20826.446 | I6: ='S05'!E11 -> 20826.446 | J6: ='S05'!E12 -> buy | K6: ='S05'!E13 -> 1 | L6: ='S05'!E14 -> 0 | M6: =IF(COUNTIF('S05'!I7:J16,"FAIL")=0,"PASS","FAIL") -> PASS
A7: S06 | B7: Rent growth compounding | C7: ='S06'!B4 -> 500000 | D7: ='S06'!B5 -> 1000 | E7: ='S06'!B9 -> 3 | F7: ='S06'!E7 -> 0 | G7: ='S06'!E9 -> 0 | H7: ='S06'!E10 -> 37830 | I7: ='S06'!E11 -> 37830 | J7: ='S06'!E12 -> buy | K7: ='S06'!E13 -> 1 | L7: ='S06'!E14 -> 0 | M7: =IF(COUNTIF('S06'!I7:J16,"FAIL")=0,"PASS","FAIL") -> PASS
A8: S07 | B8: Standard 30-year mortgage (published payment check) | C8: ='S07'!B4 -> 300000 | D8: ='S07'!B5 -> 1500 | E8: ='S07'!B9 -> 7 | F8: ='S07'!E7 -> 1438.9213 | G8: ='S07'!E9 -> 119722.01 | H8: ='S07'!E10 -> 113356.44 | I8: ='S07'!E11 -> -6365.5684 | J8: ='S07'!E12 -> rent | K8: ='S07'!E13 -> 10 | L8: ='S07'!E14 -> 13050 | M8: =IF(COUNTIF('S07'!I7:J16,"FAIL")=0,"PASS","FAIL") -> PASS
A9: S08 | B9: Buying never breaks even (price very high relative to rent) | C9: ='S08'!B4 -> 1000000 | D9: ='S08'!B5 -> 1000 | E9: ='S08'!B9 -> 7 | F9: ='S08'!E7 -> 4796.4042 | G9: ='S08'!E9 -> 540625.06 | H9: ='S08'!E10 -> 69436.481 | I9: ='S08'!E11 -> -471188.58 | J9: ='S08'!E12 -> rent | K9: ='S08'!E13 -> never | L9: ='S08'!E14 -> 73500 | M9: =IF(COUNTIF('S08'!I7:J16,"FAIL")=0,"PASS","FAIL") -> PASS
A10: S09 | B10: User cost check with default assumptions | C10: ='S09'!B4 -> 300000 | D10: ='S09'!B5 -> 1200 | E10: ='S09'!B9 -> 7 | F10: ='S09'!E7 -> 1438.9213 | G10: ='S09'!E9 -> 119722.01 | H10: ='S09'!E10 -> 90685.156 | I10: ='S09'!E11 -> -29036.857 | J10: ='S09'!E12 -> rent | K10: ='S09'!E13 -> never | L10: ='S09'!E14 -> 13050 | M10: =IF(COUNTIF('S09'!I7:J16,"FAIL")=0,"PASS","FAIL") -> PASS
A11: S10 | B11: Negative appreciation | C11: ='S10'!B4 -> 200000 | D11: ='S10'!B5 -> 1000 | E11: ='S10'!B9 -> 2 | F11: ='S10'!E7 -> 0 | G11: ='S10'!E9 -> 19500 | H11: ='S10'!E10 -> 24000 | I11: ='S10'!E11 -> 4500 | J11: ='S10'!E12 -> buy | K11: ='S10'!E13 -> 1 | L11: ='S10'!E14 -> 10000 | M11: =IF(COUNTIF('S10'!I7:J16,"FAIL")=0,"PASS","FAIL") -> PASS
A12: S11 | B12: Typical case: defaults, latest mortgage rate and forecasts | C12: ='S11'!B4 -> 400000 | D12: ='S11'!B5 -> 2000 | E12: ='S11'!B9 -> 7 | F12: ='S11'!E7 -> 1991.6769 | G12: ='S11'!E9 -> 149467.46 | H12: ='S11'!E10 -> 153609.24 | I12: ='S11'!E11 -> 4141.7716 | J12: ='S11'!E12 -> buy | K12: ='S11'!E13 -> 7 | L12: ='S11'!E14 -> 14280 | M12: =IF(COUNTIF('S11'!I7:J16,"FAIL")=0,"PASS","FAIL") -> PASS
B14: All scenarios | M14: =IF(COUNTIF(M2:M12,"FAIL")=0,"ALL PASS","SOME FAIL") -> ALL PASS

Sheet S01
A1: S01: Cash purchase, zero growth, no costs
A2: Hand calculation: C_B = (1+0)100,000 + 0 - (100,000 x 1 - 0) = 0. C_R = 12 x 500 = 6,000. Delta = 6,000 >= 0 in year 1.
A3: Inputs (blue: edit to explore) | D3: Results (Excel formulas)
A4: Price P ($) | B4: 100000 | D4: Loan L = (1-d)P | E4: =(1-$B$6)*$B$4 -> 0
A5: Monthly rent R ($) | B5: 500 | D5: Monthly rate i = r/12 | E5: =$B$7/12 -> 0
A6: Down payment d | B6: 1 | D6: Number of payments n = 12T | E6: =12*$B$8 -> 360
A7: Mortgage rate r | B7: 0 | D7: Monthly payment M | E7: =IF($E$4=0,0,IF($E$5=0,$E$4/$E$6,$E$4*$E$5*(1+$E$5)^$E$6/((1+$E$5)^$E$6-1))) -> 0 | G7: 0 | H7: 0 | I7: =IF(ABS(E7-H7)<0.01,"PASS","FAIL") -> PASS | J7: =IF(ABS(E7-G7)<0.01,"PASS","FAIL") -> PASS
A8: Mortgage term T (years) | B8: 30 | G8: Hand calculation | H8: Python engine | I8: Excel vs engine | J8: Excel vs hand
A9: Holding period H (years) | B9: 1 | D9: C_B(H) cost of buying (PV) | E9: =INDEX(J21:J50,$B$9) -> 0 | G9: 0 | H9: 0 | I9: =IF(ABS(E9-H9)<0.01,"PASS","FAIL") -> PASS | J9: =IF(ABS(E9-G9)<0.01,"PASS","FAIL") -> PASS
A10: Property tax tau | B10: 0 | D10: C_R(H) cost of renting (PV) | E10: =INDEX(I21:I50,$B$9) -> 6000 | G10: 6000 | H10: 6000 | I10: =IF(ABS(E10-H10)<0.01,"PASS","FAIL") -> PASS | J10: =IF(ABS(E10-G10)<0.01,"PASS","FAIL") -> PASS
A11: Maintenance m | B11: 0 | D11: Delta(H) = C_R - C_B | E11: =INDEX(K21:K50,$B$9) -> 6000 | G11: 6000 | H11: 6000 | I11: =IF(ABS(E11-H11)<0.01,"PASS","FAIL") -> PASS | J11: =IF(ABS(E11-G11)<0.01,"PASS","FAIL") -> PASS
A12: Insurance h | B12: 0 | D12: Recommendation at H | E12: =IF(E11>=0,"buy","rent") -> buy | G12: buy | H12: buy | I12: =IF(E12=H12,"PASS","FAIL") -> PASS | J12: =IF(E12=G12,"PASS","FAIL") -> PASS
A13: Buying costs cb | B13: 0 | D13: Break-even year (search 1-30) | E13: =IF(COUNT(L21:L50)=0,"never",MIN(L21:L50)) -> 1 | G13: 1 | H13: 1 | I13: =IF(ABS(E13-H13)<0.01,"PASS","FAIL") -> PASS | J13: =IF(ABS(E13-G13)<0.01,"PASS","FAIL") -> PASS
A14: Selling costs cs | B14: 0 | D14: User cost UC = (k+tau+m+h-g)P | E14: =($B$15+$B$10+$B$11+$B$12-$B$16)*$B$4 -> 0 | G14: 0 | H14: 0 | I14: =IF(ABS(E14-H14)<0.01,"PASS","FAIL") -> PASS | J14: =IF(ABS(E14-G14)<0.01,"PASS","FAIL") -> PASS
A15: Discount rate k | B15: 0 | D15: Annual rent 12R | E15: =12*$B$5 -> 6000 | H15: 6000 | I15: =IF(ABS(E15-H15)<0.01,"PASS","FAIL") -> PASS
A16: Appreciation g | B16: 0 | D16: Loan balance B_H | E16: =INDEX(C21:C50,$B$9) -> 0 | H16: 0 | I16: =IF(ABS(E16-H16)<0.01,"PASS","FAIL") -> PASS
A17: Rent growth q | B17: 0 | G17: Hand and Python values are pasted for the inputs above; if you edit an input, only the Excel column updates.
A19: Year-by-year (selling at the end of year t)
A20: Year t | B20: Home value V_t | C20: Loan balance B_t | D20: Owner cost O_t | E20: PV of O_t | F20: Sum PV O (1..t) | G20: Rent_t | H20: PV of Rent_t | I20: C_R(t) | J20: C_B(t) | K20: Delta(t) = C_R - C_B | L20: Break-even helper
A21: 1 | B21: =$B$4*(1+$B$16)^A21 -> 100000 | C21: =IF(OR($E$4=0,A21>=$B$8),0,IF($E$5=0,$E$4-12*A21*$E$7,$E$4*(1+$E$5)^(12*A21)-$E$7*((1+$E$5)^(12*A21)-1)/$E$5)) -> 0 | D21: =IF(A21<=$B$8,12*$E$7,0)+($B$10+$B$11+$B$12)*$B$4*(1+$B$16)^(A21-1) -> 0 | E21: =D21/(1+$B$15)^A21 -> 0 | F21: =SUM($E$21:E21) -> 0 | G21: =12*$B$5*(1+$B$17)^(A21-1) -> 6000 | H21: =G21/(1+$B$15)^A21 -> 6000 | I21: =SUM($H$21:H21) -> 6000 | J21: =($B$6+$B$13)*$B$4+F21-(B21*(1-$B$14)-C21)/(1+$B$15)^A21 -> 0 | K21: =I21-J21 -> 6000 | L21: =IF(K21>=0,A21,"") -> 1
A22: 2 | B22: =$B$4*(1+$B$16)^A22 -> 100000 | C22: =IF(OR($E$4=0,A22>=$B$8),0,IF($E$5=0,$E$4-12*A22*$E$7,$E$4*(1+$E$5)^(12*A22)-$E$7*((1+$E$5)^(12*A22)-1)/$E$5)) -> 0 | D22: =IF(A22<=$B$8,12*$E$7,0)+($B$10+$B$11+$B$12)*$B$4*(1+$B$16)^(A22-1) -> 0 | E22: =D22/(1+$B$15)^A22 -> 0 | F22: =SUM($E$21:E22) -> 0 | G22: =12*$B$5*(1+$B$17)^(A22-1) -> 6000 | H22: =G22/(1+$B$15)^A22 -> 6000 | I22: =SUM($H$21:H22) -> 12000 | J22: =($B$6+$B$13)*$B$4+F22-(B22*(1-$B$14)-C22)/(1+$B$15)^A22 -> 0 | K22: =I22-J22 -> 12000 | L22: =IF(K22>=0,A22,"") -> 2
A23: 3 | B23: =$B$4*(1+$B$16)^A23 -> 100000 | C23: =IF(OR($E$4=0,A23>=$B$8),0,IF($E$5=0,$E$4-12*A23*$E$7,$E$4*(1+$E$5)^(12*A23)-$E$7*((1+$E$5)^(12*A23)-1)/$E$5)) -> 0 | D23: =IF(A23<=$B$8,12*$E$7,0)+($B$10+$B$11+$B$12)*$B$4*(1+$B$16)^(A23-1) -> 0 | E23: =D23/(1+$B$15)^A23 -> 0 | F23: =SUM($E$21:E23) -> 0 | G23: =12*$B$5*(1+$B$17)^(A23-1) -> 6000 | H23: =G23/(1+$B$15)^A23 -> 6000 | I23: =SUM($H$21:H23) -> 18000 | J23: =($B$6+$B$13)*$B$4+F23-(B23*(1-$B$14)-C23)/(1+$B$15)^A23 -> 0 | K23: =I23-J23 -> 18000 | L23: =IF(K23>=0,A23,"") -> 3
A24: 4 | B24: =$B$4*(1+$B$16)^A24 -> 100000 | C24: =IF(OR($E$4=0,A24>=$B$8),0,IF($E$5=0,$E$4-12*A24*$E$7,$E$4*(1+$E$5)^(12*A24)-$E$7*((1+$E$5)^(12*A24)-1)/$E$5)) -> 0 | D24: =IF(A24<=$B$8,12*$E$7,0)+($B$10+$B$11+$B$12)*$B$4*(1+$B$16)^(A24-1) -> 0 | E24: =D24/(1+$B$15)^A24 -> 0 | F24: =SUM($E$21:E24) -> 0 | G24: =12*$B$5*(1+$B$17)^(A24-1) -> 6000 | H24: =G24/(1+$B$15)^A24 -> 6000 | I24: =SUM($H$21:H24) -> 24000 | J24: =($B$6+$B$13)*$B$4+F24-(B24*(1-$B$14)-C24)/(1+$B$15)^A24 -> 0 | K24: =I24-J24 -> 24000 | L24: =IF(K24>=0,A24,"") -> 4
A25: 5 | B25: =$B$4*(1+$B$16)^A25 -> 100000 | C25: =IF(OR($E$4=0,A25>=$B$8),0,IF($E$5=0,$E$4-12*A25*$E$7,$E$4*(1+$E$5)^(12*A25)-$E$7*((1+$E$5)^(12*A25)-1)/$E$5)) -> 0 | D25: =IF(A25<=$B$8,12*$E$7,0)+($B$10+$B$11+$B$12)*$B$4*(1+$B$16)^(A25-1) -> 0 | E25: =D25/(1+$B$15)^A25 -> 0 | F25: =SUM($E$21:E25) -> 0 | G25: =12*$B$5*(1+$B$17)^(A25-1) -> 6000 | H25: =G25/(1+$B$15)^A25 -> 6000 | I25: =SUM($H$21:H25) -> 30000 | J25: =($B$6+$B$13)*$B$4+F25-(B25*(1-$B$14)-C25)/(1+$B$15)^A25 -> 0 | K25: =I25-J25 -> 30000 | L25: =IF(K25>=0,A25,"") -> 5
A26: 6 | B26: =$B$4*(1+$B$16)^A26 -> 100000 | C26: =IF(OR($E$4=0,A26>=$B$8),0,IF($E$5=0,$E$4-12*A26*$E$7,$E$4*(1+$E$5)^(12*A26)-$E$7*((1+$E$5)^(12*A26)-1)/$E$5)) -> 0 | D26: =IF(A26<=$B$8,12*$E$7,0)+($B$10+$B$11+$B$12)*$B$4*(1+$B$16)^(A26-1) -> 0 | E26: =D26/(1+$B$15)^A26 -> 0 | F26: =SUM($E$21:E26) -> 0 | G26: =12*$B$5*(1+$B$17)^(A26-1) -> 6000 | H26: =G26/(1+$B$15)^A26 -> 6000 | I26: =SUM($H$21:H26) -> 36000 | J26: =($B$6+$B$13)*$B$4+F26-(B26*(1-$B$14)-C26)/(1+$B$15)^A26 -> 0 | K26: =I26-J26 -> 36000 | L26: =IF(K26>=0,A26,"") -> 6
A27: 7 | B27: =$B$4*(1+$B$16)^A27 -> 100000 | C27: =IF(OR($E$4=0,A27>=$B$8),0,IF($E$5=0,$E$4-12*A27*$E$7,$E$4*(1+$E$5)^(12*A27)-$E$7*((1+$E$5)^(12*A27)-1)/$E$5)) -> 0 | D27: =IF(A27<=$B$8,12*$E$7,0)+($B$10+$B$11+$B$12)*$B$4*(1+$B$16)^(A27-1) -> 0 | E27: =D27/(1+$B$15)^A27 -> 0 | F27: =SUM($E$21:E27) -> 0 | G27: =12*$B$5*(1+$B$17)^(A27-1) -> 6000 | H27: =G27/(1+$B$15)^A27 -> 6000 | I27: =SUM($H$21:H27) -> 42000 | J27: =($B$6+$B$13)*$B$4+F27-(B27*(1-$B$14)-C27)/(1+$B$15)^A27 -> 0 | K27: =I27-J27 -> 42000 | L27: =IF(K27>=0,A27,"") -> 7
A28: 8 | B28: =$B$4*(1+$B$16)^A28 -> 100000 | C28: =IF(OR($E$4=0,A28>=$B$8),0,IF($E$5=0,$E$4-12*A28*$E$7,$E$4*(1+$E$5)^(12*A28)-$E$7*((1+$E$5)^(12*A28)-1)/$E$5)) -> 0 | D28: =IF(A28<=$B$8,12*$E$7,0)+($B$10+$B$11+$B$12)*$B$4*(1+$B$16)^(A28-1) -> 0 | E28: =D28/(1+$B$15)^A28 -> 0 | F28: =SUM($E$21:E28) -> 0 | G28: =12*$B$5*(1+$B$17)^(A28-1) -> 6000 | H28: =G28/(1+$B$15)^A28 -> 6000 | I28: =SUM($H$21:H28) -> 48000 | J28: =($B$6+$B$13)*$B$4+F28-(B28*(1-$B$14)-C28)/(1+$B$15)^A28 -> 0 | K28: =I28-J28 -> 48000 | L28: =IF(K28>=0,A28,"") -> 8
A29: 9 | B29: =$B$4*(1+$B$16)^A29 -> 100000 | C29: =IF(OR($E$4=0,A29>=$B$8),0,IF($E$5=0,$E$4-12*A29*$E$7,$E$4*(1+$E$5)^(12*A29)-$E$7*((1+$E$5)^(12*A29)-1)/$E$5)) -> 0 | D29: =IF(A29<=$B$8,12*$E$7,0)+($B$10+$B$11+$B$12)*$B$4*(1+$B$16)^(A29-1) -> 0 | E29: =D29/(1+$B$15)^A29 -> 0 | F29: =SUM($E$21:E29) -> 0 | G29: =12*$B$5*(1+$B$17)^(A29-1) -> 6000 | H29: =G29/(1+$B$15)^A29 -> 6000 | I29: =SUM($H$21:H29) -> 54000 | J29: =($B$6+$B$13)*$B$4+F29-(B29*(1-$B$14)-C29)/(1+$B$15)^A29 -> 0 | K29: =I29-J29 -> 54000 | L29: =IF(K29>=0,A29,"") -> 9
A30: 10 | B30: =$B$4*(1+$B$16)^A30 -> 100000 | C30: =IF(OR($E$4=0,A30>=$B$8),0,IF($E$5=0,$E$4-12*A30*$E$7,$E$4*(1+$E$5)^(12*A30)-$E$7*((1+$E$5)^(12*A30)-1)/$E$5)) -> 0 | D30: =IF(A30<=$B$8,12*$E$7,0)+($B$10+$B$11+$B$12)*$B$4*(1+$B$16)^(A30-1) -> 0 | E30: =D30/(1+$B$15)^A30 -> 0 | F30: =SUM($E$21:E30) -> 0 | G30: =12*$B$5*(1+$B$17)^(A30-1) -> 6000 | H30: =G30/(1+$B$15)^A30 -> 6000 | I30: =SUM($H$21:H30) -> 60000 | J30: =($B$6+$B$13)*$B$4+F30-(B30*(1-$B$14)-C30)/(1+$B$15)^A30 -> 0 | K30: =I30-J30 -> 60000 | L30: =IF(K30>=0,A30,"") -> 10
A31: 11 | B31: =$B$4*(1+$B$16)^A31 -> 100000 | C31: =IF(OR($E$4=0,A31>=$B$8),0,IF($E$5=0,$E$4-12*A31*$E$7,$E$4*(1+$E$5)^(12*A31)-$E$7*((1+$E$5)^(12*A31)-1)/$E$5)) -> 0 | D31: =IF(A31<=$B$8,12*$E$7,0)+($B$10+$B$11+$B$12)*$B$4*(1+$B$16)^(A31-1) -> 0 | E31: =D31/(1+$B$15)^A31 -> 0 | F31: =SUM($E$21:E31) -> 0 | G31: =12*$B$5*(1+$B$17)^(A31-1) -> 6000 | H31: =G31/(1+$B$15)^A31 -> 6000 | I31: =SUM($H$21:H31) -> 66000 | J31: =($B$6+$B$13)*$B$4+F31-(B31*(1-$B$14)-C31)/(1+$B$15)^A31 -> 0 | K31: =I31-J31 -> 66000 | L31: =IF(K31>=0,A31,"") -> 11
A32: 12 | B32: =$B$4*(1+$B$16)^A32 -> 100000 | C32: =IF(OR($E$4=0,A32>=$B$8),0,IF($E$5=0,$E$4-12*A32*$E$7,$E$4*(1+$E$5)^(12*A32)-$E$7*((1+$E$5)^(12*A32)-1)/$E$5)) -> 0 | D32: =IF(A32<=$B$8,12*$E$7,0)+($B$10+$B$11+$B$12)*$B$4*(1+$B$16)^(A32-1) -> 0 | E32: =D32/(1+$B$15)^A32 -> 0 | F32: =SUM($E$21:E32) -> 0 | G32: =12*$B$5*(1+$B$17)^(A32-1) -> 6000 | H32: =G32/(1+$B$15)^A32 -> 6000 | I32: =SUM($H$21:H32) -> 72000 | J32: =($B$6+$B$13)*$B$4+F32-(B32*(1-$B$14)-C32)/(1+$B$15)^A32 -> 0 | K32: =I32-J32 -> 72000 | L32: =IF(K32>=0,A32,"") -> 12
... A50: 30 | B50: =$B$4*(1+$B$16)^A50 -> 100000 | C50: =IF(OR($E$4=0,A50>=$B$8),0,IF($E$5=0,$E$4-12*A50*$E$7,$E$4*(1+$E$5)^(12*A50)-$E$7*((1+$E$5)^(12*A50)-1)/$E$5)) -> 0 | D50: =IF(A50<=$B$8,12*$E$7,0)+($B$10+$B$11+$B$12)*$B$4*(1+$B$16)^(A50-1) -> 0 | E50: =D50/(1+$B$15)^A50 -> 0 | F50: =SUM($E$21:E50) -> 0 | G50: =12*$B$5*(1+$B$17)^(A50-1) -> 6000 | H50: =G50/(1+$B$15)^A50 -> 6000 | I50: =SUM($H$21:H50) -> 180000 | J50: =($B$6+$B$13)*$B$4+F50-(B50*(1-$B$14)-C50)/(1+$B$15)^A50 -> 0 | K50: =I50-J50 -> 180000 | L50: =IF(K50>=0,A50,"") -> 30

Sheet S02
A1: S02: Zero growth with running and transaction costs (100% down)
A2: Hand calculation: Upfront (1+0.03)200,000 = 206,000. Running 0.02 x 200,000 = 4,000 a year. Sale 200,000 x 0.94 = 188,000. C_B(5) = 206,000 + 20,000 - 188,000 = 38,000. C_R(5) = 60,000. In general Delta(H) = 12,000H - (18,000 + 4,000H) = 8,000H - 18,000: H=2 gives -2,000, H=3 gives +6,000, so break-even = 3. The mortgage rate is irrelevant because nothing is borrowed.
A3: Inputs (blue: edit to explore) | D3: Results (Excel formulas)
A4: Price P ($) | B4: 200000 | D4: Loan L = (1-d)P | E4: =(1-$B$6)*$B$4 -> 0
A5: Monthly rent R ($) | B5: 1000 | D5: Monthly rate i = r/12 | E5: =$B$7/12 -> 0.005
A6: Down payment d | B6: 1 | D6: Number of payments n = 12T | E6: =12*$B$8 -> 360
A7: Mortgage rate r | B7: 0.06 | D7: Monthly payment M | E7: =IF($E$4=0,0,IF($E$5=0,$E$4/$E$6,$E$4*$E$5*(1+$E$5)^$E$6/((1+$E$5)^$E$6-1))) -> 0 | G7: 0 | H7: 0 | I7: =IF(ABS(E7-H7)<0.01,"PASS","FAIL") -> PASS | J7: =IF(ABS(E7-G7)<0.01,"PASS","FAIL") -> PASS
A8: Mortgage term T (years) | B8: 30 | G8: Hand calculation | H8: Python engine | I8: Excel vs engine | J8: Excel vs hand
A9: Holding period H (years) | B9: 5 | D9: C_B(H) cost of buying (PV) | E9: =INDEX(J21:J50,$B$9) -> 38000 | G9: 38000 | H9: 38000 | I9: =IF(ABS(E9-H9)<0.01,"PASS","FAIL") -> PASS | J9: =IF(ABS(E9-G9)<0.01,"PASS","FAIL") -> PASS
A10: Property tax tau | B10: 0.01 | D10: C_R(H) cost of renting (PV) | E10: =INDEX(I21:I50,$B$9) -> 60000 | G10: 60000 | H10: 60000 | I10: =IF(ABS(E10-H10)<0.01,"PASS","FAIL") -> PASS | J10: =IF(ABS(E10-G10)<0.01,"PASS","FAIL") -> PASS
A11: Maintenance m | B11: 0.01 | D11: Delta(H) = C_R - C_B | E11: =INDEX(K21:K50,$B$9) -> 22000 | G11: 22000 | H11: 22000 | I11: =IF(ABS(E11-H11)<0.01,"PASS","FAIL") -> PASS | J11: =IF(ABS(E11-G11)<0.01,"PASS","FAIL") -> PASS
A12: Insurance h | B12: 0 | D12: Recommendation at H | E12: =IF(E11>=0,"buy","rent") -> buy | G12: buy | H12: buy | I12: =IF(E12=H12,"PASS","FAIL") -> PASS | J12: =IF(E12=G12,"PASS","FAIL") -> PASS
A13: Buying costs cb | B13: 0.03 | D13: Break-even year (search 1-30) | E13: =IF(COUNT(L21:L50)=0,"never",MIN(L21:L50)) -> 3 | G13: 3 | H13: 3 | I13: =IF(ABS(E13-H13)<0.01,"PASS","FAIL") -> PASS | J13: =IF(ABS(E13-G13)<0.01,"PASS","FAIL") -> PASS
A14: Selling costs cs | B14: 0.06 | D14: User cost UC = (k+tau+m+h-g)P | E14: =($B$15+$B$10+$B$11+$B$12-$B$16)*$B$4 -> 4000 | G14: 4000 | H14: 4000 | I14: =IF(ABS(E14-H14)<0.01,"PASS","FAIL") -> PASS | J14: =IF(ABS(E14-G14)<0.01,"PASS","FAIL") -> PASS
A15: Discount rate k | B15: 0 | D15: Annual rent 12R | E15: =12*$B$5 -> 12000 | H15: 12000 | I15: =IF(ABS(E15-H15)<0.01,"PASS","FAIL") -> PASS
A16: Appreciation g | B16: 0 | D16: Loan balance B_H | E16: =INDEX(C21:C50,$B$9) -> 0 | H16: 0 | I16: =IF(ABS(E16-H16)<0.01,"PASS","FAIL") -> PASS
A17: Rent growth q | B17: 0 | G17: Hand and Python values are pasted for the inputs above; if you edit an input, only the Excel column updates.
A19: Year-by-year (selling at the end of year t)
A20: Year t | B20: Home value V_t | C20: Loan balance B_t | D20: Owner cost O_t | E20: PV of O_t | F20: Sum PV O (1..t) | G20: Rent_t | H20: PV of Rent_t | I20: C_R(t) | J20: C_B(t) | K20: Delta(t) = C_R - C_B | L20: Break-even helper
A21: 1 | B21: =$B$4*(1+$B$16)^A21 -> 200000 | C21: =IF(OR($E$4=0,A21>=$B$8),0,IF($E$5=0,$E$4-12*A21*$E$7,$E$4*(1+$E$5)^(12*A21)-$E$7*((1+$E$5)^(12*A21)-1)/$E$5)) -> 0 | D21: =IF(A21<=$B$8,12*$E$7,0)+($B$10+$B$11+$B$12)*$B$4*(1+$B$16)^(A21-1) -> 4000 | E21: =D21/(1+$B$15)^A21 -> 4000 | F21: =SUM($E$21:E21) -> 4000 | G21: =12*$B$5*(1+$B$17)^(A21-1) -> 12000 | H21: =G21/(1+$B$15)^A21 -> 12000 | I21: =SUM($H$21:H21) -> 12000 | J21: =($B$6+$B$13)*$B$4+F21-(B21*(1-$B$14)-C21)/(1+$B$15)^A21 -> 22000 | K21: =I21-J21 -> -10000 | L21: =IF(K21>=0,A21,"")
A22: 2 | B22: =$B$4*(1+$B$16)^A22 -> 200000 | C22: =IF(OR($E$4=0,A22>=$B$8),0,IF($E$5=0,$E$4-12*A22*$E$7,$E$4*(1+$E$5)^(12*A22)-$E$7*((1+$E$5)^(12*A22)-1)/$E$5)) -> 0 | D22: =IF(A22<=$B$8,12*$E$7,0)+($B$10+$B$11+$B$12)*$B$4*(1+$B$16)^(A22-1) -> 4000 | E22: =D22/(1+$B$15)^A22 -> 4000 | F22: =SUM($E$21:E22) -> 8000 | G22: =12*$B$5*(1+$B$17)^(A22-1) -> 12000 | H22: =G22/(1+$B$15)^A22 -> 12000 | I22: =SUM($H$21:H22) -> 24000 | J22: =($B$6+$B$13)*$B$4+F22-(B22*(1-$B$14)-C22)/(1+$B$15)^A22 -> 26000 | K22: =I22-J22 -> -2000 | L22: =IF(K22>=0,A22,"")
A23: 3 | B23: =$B$4*(1+$B$16)^A23 -> 200000 | C23: =IF(OR($E$4=0,A23>=$B$8),0,IF($E$5=0,$E$4-12*A23*$E$7,$E$4*(1+$E$5)^(12*A23)-$E$7*((1+$E$5)^(12*A23)-1)/$E$5)) -> 0 | D23: =IF(A23<=$B$8,12*$E$7,0)+($B$10+$B$11+$B$12)*$B$4*(1+$B$16)^(A23-1) -> 4000 | E23: =D23/(1+$B$15)^A23 -> 4000 | F23: =SUM($E$21:E23) -> 12000 | G23: =12*$B$5*(1+$B$17)^(A23-1) -> 12000 | H23: =G23/(1+$B$15)^A23 -> 12000 | I23: =SUM($H$21:H23) -> 36000 | J23: =($B$6+$B$13)*$B$4+F23-(B23*(1-$B$14)-C23)/(1+$B$15)^A23 -> 30000 | K23: =I23-J23 -> 6000 | L23: =IF(K23>=0,A23,"") -> 3
A24: 4 | B24: =$B$4*(1+$B$16)^A24 -> 200000 | C24: =IF(OR($E$4=0,A24>=$B$8),0,IF($E$5=0,$E$4-12*A24*$E$7,$E$4*(1+$E$5)^(12*A24)-$E$7*((1+$E$5)^(12*A24)-1)/$E$5)) -> 0 | D24: =IF(A24<=$B$8,12*$E$7,0)+($B$10+$B$11+$B$12)*$B$4*(1+$B$16)^(A24-1) -> 4000 | E24: =D24/(1+$B$15)^A24 -> 4000 | F24: =SUM($E$21:E24) -> 16000 | G24: =12*$B$5*(1+$B$17)^(A24-1) -> 12000 | H24: =G24/(1+$B$15)^A24 -> 12000 | I24: =SUM($H$21:H24) -> 48000 | J24: =($B$6+$B$13)*$B$4+F24-(B24*(1-$B$14)-C24)/(1+$B$15)^A24 -> 34000 | K24: =I24-J24 -> 14000 | L24: =IF(K24>=0,A24,"") -> 4
A25: 5 | B25: =$B$4*(1+$B$16)^A25 -> 200000 | C25: =IF(OR($E$4=0,A25>=$B$8),0,IF($E$5=0,$E$4-12*A25*$E$7,$E$4*(1+$E$5)^(12*A25)-$E$7*((1+$E$5)^(12*A25)-1)/$E$5)) -> 0 | D25: =IF(A25<=$B$8,12*$E$7,0)+($B$10+$B$11+$B$12)*$B$4*(1+$B$16)^(A25-1) -> 4000 | E25: =D25/(1+$B$15)^A25 -> 4000 | F25: =SUM($E$21:E25) -> 20000 | G25: =12*$B$5*(1+$B$17)^(A25-1) -> 12000 | H25: =G25/(1+$B$15)^A25 -> 12000 | I25: =SUM($H$21:H25) -> 60000 | J25: =($B$6+$B$13)*$B$4+F25-(B25*(1-$B$14)-C25)/(1+$B$15)^A25 -> 38000 | K25: =I25-J25 -> 22000 | L25: =IF(K25>=0,A25,"") -> 5
A26: 6 | B26: =$B$4*(1+$B$16)^A26 -> 200000 | C26: =IF(OR($E$4=0,A26>=$B$8),0,IF($E$5=0,$E$4-12*A26*$E$7,$E$4*(1+$E$5)^(12*A26)-$E$7*((1+$E$5)^(12*A26)-1)/$E$5)) -> 0 | D26: =IF(A26<=$B$8,12*$E$7,0)+($B$10+$B$11+$B$12)*$B$4*(1+$B$16)^(A26-1) -> 4000 | E26: =D26/(1+$B$15)^A26 -> 4000 | F26: =SUM($E$21:E26) -> 24000 | G26: =12*$B$5*(1+$B$17)^(A26-1) -> 12000 | H26: =G26/(1+$B$15)^A26 -> 12000 | I26: =SUM($H$21:H26) -> 72000 | J26: =($B$6+$B$13)*$B$4+F26-(B26*(1-$B$14)-C26)/(1+$B$15)^A26 -> 42000 | K26: =I26-J26 -> 30000 | L26: =IF(K26>=0,A26,"") -> 6
A27: 7 | B27: =$B$4*(1+$B$16)^A27 -> 200000 | C27: =IF(OR($E$4=0,A27>=$B$8),0,IF($E$5=0,$E$4-12*A27*$E$7,$E$4*(1+$E$5)^(12*A27)-$E$7*((1+$E$5)^(12*A27)-1)/$E$5)) -> 0 | D27: =IF(A27<=$B$8,12*$E$7,0)+($B$10+$B$11+$B$12)*$B$4*(1+$B$16)^(A27-1) -> 4000 | E27: =D27/(1+$B$15)^A27 -> 4000 | F27: =SUM($E$21:E27) -> 28000 | G27: =12*$B$5*(1+$B$17)^(A27-1) -> 12000 | H27: =G27/(1+$B$15)^A27 -> 12000 | I27: =SUM($H$21:H27) -> 84000 | J27: =($B$6+$B$13)*$B$4+F27-(B27*(1-$B$14)-C27)/(1+$B$15)^A27 -> 46000 | K27: =I27-J27 -> 38000 | L27: =IF(K27>=0,A27,"") -> 7
A28: 8 | B28: =$B$4*(1+$B$16)^A28 -> 200000 | C28: =IF(OR($E$4=0,A28>=$B$8),0,IF($E$5=0,$E$4-12*A28*$E$7,$E$4*(1+$E$5)^(12*A28)-$E$7*((1+$E$5)^(12*A28)-1)/$E$5)) -> 0 | D28: =IF(A28<=$B$8,12*$E$7,0)+($B$10+$B$11+$B$12)*$B$4*(1+$B$16)^(A28-1) -> 4000 | E28: =D28/(1+$B$15)^A28 -> 4000 | F28: =SUM($E$21:E28) -> 32000 | G28: =12*$B$5*(1+$B$17)^(A28-1) -> 12000 | H28: =G28/(1+$B$15)^A28 -> 12000 | I28: =SUM($H$21:H28) -> 96000 | J28: =($B$6+$B$13)*$B$4+F28-(B28*(1-$B$14)-C28)/(1+$B$15)^A28 -> 50000 | K28: =I28-J28 -> 46000 | L28: =IF(K28>=0,A28,"") -> 8
A29: 9 | B29: =$B$4*(1+$B$16)^A29 -> 200000 | C29: =IF(OR($E$4=0,A29>=$B$8),0,IF($E$5=0,$E$4-12*A29*$E$7,$E$4*(1+$E$5)^(12*A29)-$E$7*((1+$E$5)^(12*A29)-1)/$E$5)) -> 0 | D29: =IF(A29<=$B$8,12*$E$7,0)+($B$10+$B$11+$B$12)*$B$4*(1+$B$16)^(A29-1) -> 4000 | E29: =D29/(1+$B$15)^A29 -> 4000 | F29: =SUM($E$21:E29) -> 36000 | G29: =12*$B$5*(1+$B$17)^(A29-1) -> 12000 | H29: =G29/(1+$B$15)^A29 -> 12000 | I29: =SUM($H$21:H29) -> 108000 | J29: =($B$6+$B$13)*$B$4+F29-(B29*(1-$B$14)-C29)/(1+$B$15)^A29 -> 54000 | K29: =I29-J29 -> 54000 | L29: =IF(K29>=0,A29,"") -> 9
A30: 10 | B30: =$B$4*(1+$B$16)^A30 -> 200000 | C30: =IF(OR($E$4=0,A30>=$B$8),0,IF($E$5=0,$E$4-12*A30*$E$7,$E$4*(1+$E$5)^(12*A30)-$E$7*((1+$E$5)^(12*A30)-1)/$E$5)) -> 0 | D30: =IF(A30<=$B$8,12*$E$7,0)+($B$10+$B$11+$B$12)*$B$4*(1+$B$16)^(A30-1) -> 4000 | E30: =D30/(1+$B$15)^A30 -> 4000 | F30: =SUM($E$21:E30) -> 40000 | G30: =12*$B$5*(1+$B$17)^(A30-1) -> 12000 | H30: =G30/(1+$B$15)^A30 -> 12000 | I30: =SUM($H$21:H30) -> 120000 | J30: =($B$6+$B$13)*$B$4+F30-(B30*(1-$B$14)-C30)/(1+$B$15)^A30 -> 58000 | K30: =I30-J30 -> 62000 | L30: =IF(K30>=0,A30,"") -> 10
A31: 11 | B31: =$B$4*(1+$B$16)^A31 -> 200000 | C31: =IF(OR($E$4=0,A31>=$B$8),0,IF($E$5=0,$E$4-12*A31*$E$7,$E$4*(1+$E$5)^(12*A31)-$E$7*((1+$E$5)^(12*A31)-1)/$E$5)) -> 0 | D31: =IF(A31<=$B$8,12*$E$7,0)+($B$10+$B$11+$B$12)*$B$4*(1+$B$16)^(A31-1) -> 4000 | E31: =D31/(1+$B$15)^A31 -> 4000 | F31: =SUM($E$21:E31) -> 44000 | G31: =12*$B$5*(1+$B$17)^(A31-1) -> 12000 | H31: =G31/(1+$B$15)^A31 -> 12000 | I31: =SUM($H$21:H31) -> 132000 | J31: =($B$6+$B$13)*$B$4+F31-(B31*(1-$B$14)-C31)/(1+$B$15)^A31 -> 62000 | K31: =I31-J31 -> 70000 | L31: =IF(K31>=0,A31,"") -> 11
A32: 12 | B32: =$B$4*(1+$B$16)^A32 -> 200000 | C32: =IF(OR($E$4=0,A32>=$B$8),0,IF($E$5=0,$E$4-12*A32*$E$7,$E$4*(1+$E$5)^(12*A32)-$E$7*((1+$E$5)^(12*A32)-1)/$E$5)) -> 0 | D32: =IF(A32<=$B$8,12*$E$7,0)+($B$10+$B$11+$B$12)*$B$4*(1+$B$16)^(A32-1) -> 4000 | E32: =D32/(1+$B$15)^A32 -> 4000 | F32: =SUM($E$21:E32) -> 48000 | G32: =12*$B$5*(1+$B$17)^(A32-1) -> 12000 | H32: =G32/(1+$B$15)^A32 -> 12000 | I32: =SUM($H$21:H32) -> 144000 | J32: =($B$6+$B$13)*$B$4+F32-(B32*(1-$B$14)-C32)/(1+$B$15)^A32 -> 66000 | K32: =I32-J32 -> 78000 | L32: =IF(K32>=0,A32,"") -> 12
... A50: 30 | B50: =$B$4*(1+$B$16)^A50 -> 200000 | C50: =IF(OR($E$4=0,A50>=$B$8),0,IF($E$5=0,$E$4-12*A50*$E$7,$E$4*(1+$E$5)^(12*A50)-$E$7*((1+$E$5)^(12*A50)-1)/$E$5)) -> 0 | D50: =IF(A50<=$B$8,12*$E$7,0)+($B$10+$B$11+$B$12)*$B$4*(1+$B$16)^(A50-1) -> 4000 | E50: =D50/(1+$B$15)^A50 -> 4000 | F50: =SUM($E$21:E50) -> 120000 | G50: =12*$B$5*(1+$B$17)^(A50-1) -> 12000 | H50: =G50/(1+$B$15)^A50 -> 12000 | I50: =SUM($H$21:H50) -> 360000 | J50: =($B$6+$B$13)*$B$4+F50-(B50*(1-$B$14)-C50)/(1+$B$15)^A50 -> 138000 | K50: =I50-J50 -> 222000 | L50: =IF(K50>=0,A50,"") -> 30

Sheet S03
A1: S03: Interest-free mortgage, holding period shorter than term
A2: Hand calculation: L = 0.75 x 120,000 = 90,000; r = 0 so M = 90,000 / 180 = 500. B_5 = 90,000 - 60 x 500 = 60,000. O_t = 6,000. C_B(5) = 30,000 + 30,000 - (120,000 - 60,000) = 0. C_R(5) = 5 x 8,400 = 42,000.
A3: Inputs (blue: edit to explore) | D3: Results (Excel formulas)
A4: Price P ($) | B4: 120000 | D4: Loan L = (1-d)P | E4: =(1-$B$6)*$B$4 -> 90000
A5: Monthly rent R ($) | B5: 700 | D5: Monthly rate i = r/12 | E5: =$B$7/12 -> 0
A6: Down payment d | B6: 0.25 | D6: Number of payments n = 12T | E6: =12*$B$8 -> 180
A7: Mortgage rate r | B7: 0 | D7: Monthly payment M | E7: =IF($E$4=0,0,IF($E$5=0,$E$4/$E$6,$E$4*$E$5*(1+$E$5)^$E$6/((1+$E$5)^$E$6-1))) -> 500 | G7: 500 | H7: 500 | I7: =IF(ABS(E7-H7)<0.01,"PASS","FAIL") -> PASS | J7: =IF(ABS(E7-G7)<0.01,"PASS","FAIL") -> PASS
A8: Mortgage term T (years) | B8: 15 | G8: Hand calculation | H8: Python engine | I8: Excel vs engine | J8: Excel vs hand
A9: Holding period H (years) | B9: 5 | D9: C_B(H) cost of buying (PV) | E9: =INDEX(J21:J50,$B$9) -> 0 | G9: 0 | H9: 0 | I9: =IF(ABS(E9-H9)<0.01,"PASS","FAIL") -> PASS | J9: =IF(ABS(E9-G9)<0.01,"PASS","FAIL") -> PASS
A10: Property tax tau | B10: 0 | D10: C_R(H) cost of renting (PV) | E10: =INDEX(I21:I50,$B$9) -> 42000 | G10: 42000 | H10: 42000 | I10: =IF(ABS(E10-H10)<0.01,"PASS","FAIL") -> PASS | J10: =IF(ABS(E10-G10)<0.01,"PASS","FAIL") -> PASS
A11: Maintenance m | B11: 0 | D11: Delta(H) = C_R - C_B | E11: =INDEX(K21:K50,$B$9) -> 42000 | G11: 42000 | H11: 42000 | I11: =IF(ABS(E11-H11)<0.01,"PASS","FAIL") -> PASS | J11: =IF(ABS(E11-G11)<0.01,"PASS","FAIL") -> PASS
A12: Insurance h | B12: 0 | D12: Recommendation at H | E12: =IF(E11>=0,"buy","rent") -> buy | G12: buy | H12: buy | I12: =IF(E12=H12,"PASS","FAIL") -> PASS | J12: =IF(E12=G12,"PASS","FAIL") -> PASS
A13: Buying costs cb | B13: 0 | D13: Break-even year (search 1-30) | E13: =IF(COUNT(L21:L50)=0,"never",MIN(L21:L50)) -> 1 | G13: 1 | H13: 1 | I13: =IF(ABS(E13-H13)<0.01,"PASS","FAIL") -> PASS | J13: =IF(ABS(E13-G13)<0.01,"PASS","FAIL") -> PASS
A14: Selling costs cs | B14: 0 | D14: User cost UC = (k+tau+m+h-g)P | E14: =($B$15+$B$10+$B$11+$B$12-$B$16)*$B$4 -> 0 | G14: 0 | H14: 0 | I14: =IF(ABS(E14-H14)<0.01,"PASS","FAIL") -> PASS | J14: =IF(ABS(E14-G14)<0.01,"PASS","FAIL") -> PASS
A15: Discount rate k | B15: 0 | D15: Annual rent 12R | E15: =12*$B$5 -> 8400 | H15: 8400 | I15: =IF(ABS(E15-H15)<0.01,"PASS","FAIL") -> PASS
A16: Appreciation g | B16: 0 | D16: Loan balance B_H | E16: =INDEX(C21:C50,$B$9) -> 60000 | G16: 60000 | H16: 60000 | I16: =IF(ABS(E16-H16)<0.01,"PASS","FAIL") -> PASS | J16: =IF(ABS(E16-G16)<0.01,"PASS","FAIL") -> PASS
A17: Rent growth q | B17: 0 | G17: Hand and Python values are pasted for the inputs above; if you edit an input, only the Excel column updates.
A19: Year-by-year (selling at the end of year t)
A20: Year t | B20: Home value V_t | C20: Loan balance B_t | D20: Owner cost O_t | E20: PV of O_t | F20: Sum PV O (1..t) | G20: Rent_t | H20: PV of Rent_t | I20: C_R(t) | J20: C_B(t) | K20: Delta(t) = C_R - C_B | L20: Break-even helper
A21: 1 | B21: =$B$4*(1+$B$16)^A21 -> 120000 | C21: =IF(OR($E$4=0,A21>=$B$8),0,IF($E$5=0,$E$4-12*A21*$E$7,$E$4*(1+$E$5)^(12*A21)-$E$7*((1+$E$5)^(12*A21)-1)/$E$5)) -> 84000 | D21: =IF(A21<=$B$8,12*$E$7,0)+($B$10+$B$11+$B$12)*$B$4*(1+$B$16)^(A21-1) -> 6000 | E21: =D21/(1+$B$15)^A21 -> 6000 | F21: =SUM($E$21:E21) -> 6000 | G21: =12*$B$5*(1+$B$17)^(A21-1) -> 8400 | H21: =G21/(1+$B$15)^A21 -> 8400 | I21: =SUM($H$21:H21) -> 8400 | J21: =($B$6+$B$13)*$B$4+F21-(B21*(1-$B$14)-C21)/(1+$B$15)^A21 -> 0 | K21: =I21-J21 -> 8400 | L21: =IF(K21>=0,A21,"") -> 1
A22: 2 | B22: =$B$4*(1+$B$16)^A22 -> 120000 | C22: =IF(OR($E$4=0,A22>=$B$8),0,IF($E$5=0,$E$4-12*A22*$E$7,$E$4*(1+$E$5)^(12*A22)-$E$7*((1+$E$5)^(12*A22)-1)/$E$5)) -> 78000 | D22: =IF(A22<=$B$8,12*$E$7,0)+($B$10+$B$11+$B$12)*$B$4*(1+$B$16)^(A22-1) -> 6000 | E22: =D22/(1+$B$15)^A22 -> 6000 | F22: =SUM($E$21:E22) -> 12000 | G22: =12*$B$5*(1+$B$17)^(A22-1) -> 8400 | H22: =G22/(1+$B$15)^A22 -> 8400 | I22: =SUM($H$21:H22) -> 16800 | J22: =($B$6+$B$13)*$B$4+F22-(B22*(1-$B$14)-C22)/(1+$B$15)^A22 -> 0 | K22: =I22-J22 -> 16800 | L22: =IF(K22>=0,A22,"") -> 2
A23: 3 | B23: =$B$4*(1+$B$16)^A23 -> 120000 | C23: =IF(OR($E$4=0,A23>=$B$8),0,IF($E$5=0,$E$4-12*A23*$E$7,$E$4*(1+$E$5)^(12*A23)-$E$7*((1+$E$5)^(12*A23)-1)/$E$5)) -> 72000 | D23: =IF(A23<=$B$8,12*$E$7,0)+($B$10+$B$11+$B$12)*$B$4*(1+$B$16)^(A23-1) -> 6000 | E23: =D23/(1+$B$15)^A23 -> 6000 | F23: =SUM($E$21:E23) -> 18000 | G23: =12*$B$5*(1+$B$17)^(A23-1) -> 8400 | H23: =G23/(1+$B$15)^A23 -> 8400 | I23: =SUM($H$21:H23) -> 25200 | J23: =($B$6+$B$13)*$B$4+F23-(B23*(1-$B$14)-C23)/(1+$B$15)^A23 -> 0 | K23: =I23-J23 -> 25200 | L23: =IF(K23>=0,A23,"") -> 3
A24: 4 | B24: =$B$4*(1+$B$16)^A24 -> 120000 | C24: =IF(OR($E$4=0,A24>=$B$8),0,IF($E$5=0,$E$4-12*A24*$E$7,$E$4*(1+$E$5)^(12*A24)-$E$7*((1+$E$5)^(12*A24)-1)/$E$5)) -> 66000 | D24: =IF(A24<=$B$8,12*$E$7,0)+($B$10+$B$11+$B$12)*$B$4*(1+$B$16)^(A24-1) -> 6000 | E24: =D24/(1+$B$15)^A24 -> 6000 | F24: =SUM($E$21:E24) -> 24000 | G24: =12*$B$5*(1+$B$17)^(A24-1) -> 8400 | H24: =G24/(1+$B$15)^A24 -> 8400 | I24: =SUM($H$21:H24) -> 33600 | J24: =($B$6+$B$13)*$B$4+F24-(B24*(1-$B$14)-C24)/(1+$B$15)^A24 -> 0 | K24: =I24-J24 -> 33600 | L24: =IF(K24>=0,A24,"") -> 4
A25: 5 | B25: =$B$4*(1+$B$16)^A25 -> 120000 | C25: =IF(OR($E$4=0,A25>=$B$8),0,IF($E$5=0,$E$4-12*A25*$E$7,$E$4*(1+$E$5)^(12*A25)-$E$7*((1+$E$5)^(12*A25)-1)/$E$5)) -> 60000 | D25: =IF(A25<=$B$8,12*$E$7,0)+($B$10+$B$11+$B$12)*$B$4*(1+$B$16)^(A25-1) -> 6000 | E25: =D25/(1+$B$15)^A25 -> 6000 | F25: =SUM($E$21:E25) -> 30000 | G25: =12*$B$5*(1+$B$17)^(A25-1) -> 8400 | H25: =G25/(1+$B$15)^A25 -> 8400 | I25: =SUM($H$21:H25) -> 42000 | J25: =($B$6+$B$13)*$B$4+F25-(B25*(1-$B$14)-C25)/(1+$B$15)^A25 -> 0 | K25: =I25-J25 -> 42000 | L25: =IF(K25>=0,A25,"") -> 5
A26: 6 | B26: =$B$4*(1+$B$16)^A26 -> 120000 | C26: =IF(OR($E$4=0,A26>=$B$8),0,IF($E$5=0,$E$4-12*A26*$E$7,$E$4*(1+$E$5)^(12*A26)-$E$7*((1+$E$5)^(12*A26)-1)/$E$5)) -> 54000 | D26: =IF(A26<=$B$8,12*$E$7,0)+($B$10+$B$11+$B$12)*$B$4*(1+$B$16)^(A26-1) -> 6000 | E26: =D26/(1+$B$15)^A26 -> 6000 | F26: =SUM($E$21:E26) -> 36000 | G26: =12*$B$5*(1+$B$17)^(A26-1) -> 8400 | H26: =G26/(1+$B$15)^A26 -> 8400 | I26: =SUM($H$21:H26) -> 50400 | J26: =($B$6+$B$13)*$B$4+F26-(B26*(1-$B$14)-C26)/(1+$B$15)^A26 -> 0 | K26: =I26-J26 -> 50400 | L26: =IF(K26>=0,A26,"") -> 6
A27: 7 | B27: =$B$4*(1+$B$16)^A27 -> 120000 | C27: =IF(OR($E$4=0,A27>=$B$8),0,IF($E$5=0,$E$4-12*A27*$E$7,$E$4*(1+$E$5)^(12*A27)-$E$7*((1+$E$5)^(12*A27)-1)/$E$5)) -> 48000 | D27: =IF(A27<=$B$8,12*$E$7,0)+($B$10+$B$11+$B$12)*$B$4*(1+$B$16)^(A27-1) -> 6000 | E27: =D27/(1+$B$15)^A27 -> 6000 | F27: =SUM($E$21:E27) -> 42000 | G27: =12*$B$5*(1+$B$17)^(A27-1) -> 8400 | H27: =G27/(1+$B$15)^A27 -> 8400 | I27: =SUM($H$21:H27) -> 58800 | J27: =($B$6+$B$13)*$B$4+F27-(B27*(1-$B$14)-C27)/(1+$B$15)^A27 -> 0 | K27: =I27-J27 -> 58800 | L27: =IF(K27>=0,A27,"") -> 7
A28: 8 | B28: =$B$4*(1+$B$16)^A28 -> 120000 | C28: =IF(OR($E$4=0,A28>=$B$8),0,IF($E$5=0,$E$4-12*A28*$E$7,$E$4*(1+$E$5)^(12*A28)-$E$7*((1+$E$5)^(12*A28)-1)/$E$5)) -> 42000 | D28: =IF(A28<=$B$8,12*$E$7,0)+($B$10+$B$11+$B$12)*$B$4*(1+$B$16)^(A28-1) -> 6000 | E28: =D28/(1+$B$15)^A28 -> 6000 | F28: =SUM($E$21:E28) -> 48000 | G28: =12*$B$5*(1+$B$17)^(A28-1) -> 8400 | H28: =G28/(1+$B$15)^A28 -> 8400 | I28: =SUM($H$21:H28) -> 67200 | J28: =($B$6+$B$13)*$B$4+F28-(B28*(1-$B$14)-C28)/(1+$B$15)^A28 -> 0 | K28: =I28-J28 -> 67200 | L28: =IF(K28>=0,A28,"") -> 8
A29: 9 | B29: =$B$4*(1+$B$16)^A29 -> 120000 | C29: =IF(OR($E$4=0,A29>=$B$8),0,IF($E$5=0,$E$4-12*A29*$E$7,$E$4*(1+$E$5)^(12*A29)-$E$7*((1+$E$5)^(12*A29)-1)/$E$5)) -> 36000 | D29: =IF(A29<=$B$8,12*$E$7,0)+($B$10+$B$11+$B$12)*$B$4*(1+$B$16)^(A29-1) -> 6000 | E29: =D29/(1+$B$15)^A29 -> 6000 | F29: =SUM($E$21:E29) -> 54000 | G29: =12*$B$5*(1+$B$17)^(A29-1) -> 8400 | H29: =G29/(1+$B$15)^A29 -> 8400 | I29: =SUM($H$21:H29) -> 75600 | J29: =($B$6+$B$13)*$B$4+F29-(B29*(1-$B$14)-C29)/(1+$B$15)^A29 -> 0 | K29: =I29-J29 -> 75600 | L29: =IF(K29>=0,A29,"") -> 9
A30: 10 | B30: =$B$4*(1+$B$16)^A30 -> 120000 | C30: =IF(OR($E$4=0,A30>=$B$8),0,IF($E$5=0,$E$4-12*A30*$E$7,$E$4*(1+$E$5)^(12*A30)-$E$7*((1+$E$5)^(12*A30)-1)/$E$5)) -> 30000 | D30: =IF(A30<=$B$8,12*$E$7,0)+($B$10+$B$11+$B$12)*$B$4*(1+$B$16)^(A30-1) -> 6000 | E30: =D30/(1+$B$15)^A30 -> 6000 | F30: =SUM($E$21:E30) -> 60000 | G30: =12*$B$5*(1+$B$17)^(A30-1) -> 8400 | H30: =G30/(1+$B$15)^A30 -> 8400 | I30: =SUM($H$21:H30) -> 84000 | J30: =($B$6+$B$13)*$B$4+F30-(B30*(1-$B$14)-C30)/(1+$B$15)^A30 -> 0 | K30: =I30-J30 -> 84000 | L30: =IF(K30>=0,A30,"") -> 10
A31: 11 | B31: =$B$4*(1+$B$16)^A31 -> 120000 | C31: =IF(OR($E$4=0,A31>=$B$8),0,IF($E$5=0,$E$4-12*A31*$E$7,$E$4*(1+$E$5)^(12*A31)-$E$7*((1+$E$5)^(12*A31)-1)/$E$5)) -> 24000 | D31: =IF(A31<=$B$8,12*$E$7,0)+($B$10+$B$11+$B$12)*$B$4*(1+$B$16)^(A31-1) -> 6000 | E31: =D31/(1+$B$15)^A31 -> 6000 | F31: =SUM($E$21:E31) -> 66000 | G31: =12*$B$5*(1+$B$17)^(A31-1) -> 8400 | H31: =G31/(1+$B$15)^A31 -> 8400 | I31: =SUM($H$21:H31) -> 92400 | J31: =($B$6+$B$13)*$B$4+F31-(B31*(1-$B$14)-C31)/(1+$B$15)^A31 -> 0 | K31: =I31-J31 -> 92400 | L31: =IF(K31>=0,A31,"") -> 11
A32: 12 | B32: =$B$4*(1+$B$16)^A32 -> 120000 | C32: =IF(OR($E$4=0,A32>=$B$8),0,IF($E$5=0,$E$4-12*A32*$E$7,$E$4*(1+$E$5)^(12*A32)-$E$7*((1+$E$5)^(12*A32)-1)/$E$5)) -> 18000 | D32: =IF(A32<=$B$8,12*$E$7,0)+($B$10+$B$11+$B$12)*$B$4*(1+$B$16)^(A32-1) -> 6000 | E32: =D32/(1+$B$15)^A32 -> 6000 | F32: =SUM($E$21:E32) -> 72000 | G32: =12*$B$5*(1+$B$17)^(A32-1) -> 8400 | H32: =G32/(1+$B$15)^A32 -> 8400 | I32: =SUM($H$21:H32) -> 100800 | J32: =($B$6+$B$13)*$B$4+F32-(B32*(1-$B$14)-C32)/(1+$B$15)^A32 -> 0 | K32: =I32-J32 -> 100800 | L32: =IF(K32>=0,A32,"") -> 12
... A50: 30 | B50: =$B$4*(1+$B$16)^A50 -> 120000 | C50: =IF(OR($E$4=0,A50>=$B$8),0,IF($E$5=0,$E$4-12*A50*$E$7,$E$4*(1+$E$5)^(12*A50)-$E$7*((1+$E$5)^(12*A50)-1)/$E$5)) -> 0 | D50: =IF(A50<=$B$8,12*$E$7,0)+($B$10+$B$11+$B$12)*$B$4*(1+$B$16)^(A50-1) -> 0 | E50: =D50/(1+$B$15)^A50 -> 0 | F50: =SUM($E$21:E50) -> 90000 | G50: =12*$B$5*(1+$B$17)^(A50-1) -> 8400 | H50: =G50/(1+$B$15)^A50 -> 8400 | I50: =SUM($H$21:H50) -> 252000 | J50: =($B$6+$B$13)*$B$4+F50-(B50*(1-$B$14)-C50)/(1+$B$15)^A50 -> 0 | K50: =I50-J50 -> 252000 | L50: =IF(K50>=0,A50,"") -> 30

Sheet S04
A1: S04: Holding period longer than mortgage term (H > T)
A2: Hand calculation: M = 90,000 / 60 = 1,500; O_t = 18,000 for t = 1..5 and 0 for t = 6, 7 (loan repaid, no running costs). B_7 = 0. C_B(7) = 30,000 + 90,000 - 120,000 = 0. C_R(7) = 7 x 8,400 = 58,800.
A3: Inputs (blue: edit to explore) | D3: Results (Excel formulas)
A4: Price P ($) | B4: 120000 | D4: Loan L = (1-d)P | E4: =(1-$B$6)*$B$4 -> 90000
A5: Monthly rent R ($) | B5: 700 | D5: Monthly rate i = r/12 | E5: =$B$7/12 -> 0
A6: Down payment d | B6: 0.25 | D6: Number of payments n = 12T | E6: =12*$B$8 -> 60
A7: Mortgage rate r | B7: 0 | D7: Monthly payment M | E7: =IF($E$4=0,0,IF($E$5=0,$E$4/$E$6,$E$4*$E$5*(1+$E$5)^$E$6/((1+$E$5)^$E$6-1))) -> 1500 | G7: 1500 | H7: 1500 | I7: =IF(ABS(E7-H7)<0.01,"PASS","FAIL") -> PASS | J7: =IF(ABS(E7-G7)<0.01,"PASS","FAIL") -> PASS
A8: Mortgage term T (years) | B8: 5 | G8: Hand calculation | H8: Python engine | I8: Excel vs engine | J8: Excel vs hand
A9: Holding period H (years) | B9: 7 | D9: C_B(H) cost of buying (PV) | E9: =INDEX(J21:J50,$B$9) -> 0 | G9: 0 | H9: 0 | I9: =IF(ABS(E9-H9)<0.01,"PASS","FAIL") -> PASS | J9: =IF(ABS(E9-G9)<0.01,"PASS","FAIL") -> PASS
A10: Property tax tau | B10: 0 | D10: C_R(H) cost of renting (PV) | E10: =INDEX(I21:I50,$B$9) -> 58800 | G10: 58800 | H10: 58800 | I10: =IF(ABS(E10-H10)<0.01,"PASS","FAIL") -> PASS | J10: =IF(ABS(E10-G10)<0.01,"PASS","FAIL") -> PASS
A11: Maintenance m | B11: 0 | D11: Delta(H) = C_R - C_B | E11: =INDEX(K21:K50,$B$9) -> 58800 | G11: 58800 | H11: 58800 | I11: =IF(ABS(E11-H11)<0.01,"PASS","FAIL") -> PASS | J11: =IF(ABS(E11-G11)<0.01,"PASS","FAIL") -> PASS
A12: Insurance h | B12: 0 | D12: Recommendation at H | E12: =IF(E11>=0,"buy","rent") -> buy | G12: buy | H12: buy | I12: =IF(E12=H12,"PASS","FAIL") -> PASS | J12: =IF(E12=G12,"PASS","FAIL") -> PASS
A13: Buying costs cb | B13: 0 | D13: Break-even year (search 1-30) | E13: =IF(COUNT(L21:L50)=0,"never",MIN(L21:L50)) -> 1 | G13: 1 | H13: 1 | I13: =IF(ABS(E13-H13)<0.01,"PASS","FAIL") -> PASS | J13: =IF(ABS(E13-G13)<0.01,"PASS","FAIL") -> PASS
A14: Selling costs cs | B14: 0 | D14: User cost UC = (k+tau+m+h-g)P | E14: =($B$15+$B$10+$B$11+$B$12-$B$16)*$B$4 -> 0 | G14: 0 | H14: 0 | I14: =IF(ABS(E14-H14)<0.01,"PASS","FAIL") -> PASS | J14: =IF(ABS(E14-G14)<0.01,"PASS","FAIL") -> PASS
A15: Discount rate k | B15: 0 | D15: Annual rent 12R | E15: =12*$B$5 -> 8400 | H15: 8400 | I15: =IF(ABS(E15-H15)<0.01,"PASS","FAIL") -> PASS
A16: Appreciation g | B16: 0 | D16: Loan balance B_H | E16: =INDEX(C21:C50,$B$9) -> 0 | G16: 0 | H16: 0 | I16: =IF(ABS(E16-H16)<0.01,"PASS","FAIL") -> PASS | J16: =IF(ABS(E16-G16)<0.01,"PASS","FAIL") -> PASS
A17: Rent growth q | B17: 0 | G17: Hand and Python values are pasted for the inputs above; if you edit an input, only the Excel column updates.
A19: Year-by-year (selling at the end of year t)
A20: Year t | B20: Home value V_t | C20: Loan balance B_t | D20: Owner cost O_t | E20: PV of O_t | F20: Sum PV O (1..t) | G20: Rent_t | H20: PV of Rent_t | I20: C_R(t) | J20: C_B(t) | K20: Delta(t) = C_R - C_B | L20: Break-even helper
A21: 1 | B21: =$B$4*(1+$B$16)^A21 -> 120000 | C21: =IF(OR($E$4=0,A21>=$B$8),0,IF($E$5=0,$E$4-12*A21*$E$7,$E$4*(1+$E$5)^(12*A21)-$E$7*((1+$E$5)^(12*A21)-1)/$E$5)) -> 72000 | D21: =IF(A21<=$B$8,12*$E$7,0)+($B$10+$B$11+$B$12)*$B$4*(1+$B$16)^(A21-1) -> 18000 | E21: =D21/(1+$B$15)^A21 -> 18000 | F21: =SUM($E$21:E21) -> 18000 | G21: =12*$B$5*(1+$B$17)^(A21-1) -> 8400 | H21: =G21/(1+$B$15)^A21 -> 8400 | I21: =SUM($H$21:H21) -> 8400 | J21: =($B$6+$B$13)*$B$4+F21-(B21*(1-$B$14)-C21)/(1+$B$15)^A21 -> 0 | K21: =I21-J21 -> 8400 | L21: =IF(K21>=0,A21,"") -> 1
A22: 2 | B22: =$B$4*(1+$B$16)^A22 -> 120000 | C22: =IF(OR($E$4=0,A22>=$B$8),0,IF($E$5=0,$E$4-12*A22*$E$7,$E$4*(1+$E$5)^(12*A22)-$E$7*((1+$E$5)^(12*A22)-1)/$E$5)) -> 54000 | D22: =IF(A22<=$B$8,12*$E$7,0)+($B$10+$B$11+$B$12)*$B$4*(1+$B$16)^(A22-1) -> 18000 | E22: =D22/(1+$B$15)^A22 -> 18000 | F22: =SUM($E$21:E22) -> 36000 | G22: =12*$B$5*(1+$B$17)^(A22-1) -> 8400 | H22: =G22/(1+$B$15)^A22 -> 8400 | I22: =SUM($H$21:H22) -> 16800 | J22: =($B$6+$B$13)*$B$4+F22-(B22*(1-$B$14)-C22)/(1+$B$15)^A22 -> 0 | K22: =I22-J22 -> 16800 | L22: =IF(K22>=0,A22,"") -> 2
A23: 3 | B23: =$B$4*(1+$B$16)^A23 -> 120000 | C23: =IF(OR($E$4=0,A23>=$B$8),0,IF($E$5=0,$E$4-12*A23*$E$7,$E$4*(1+$E$5)^(12*A23)-$E$7*((1+$E$5)^(12*A23)-1)/$E$5)) -> 36000 | D23: =IF(A23<=$B$8,12*$E$7,0)+($B$10+$B$11+$B$12)*$B$4*(1+$B$16)^(A23-1) -> 18000 | E23: =D23/(1+$B$15)^A23 -> 18000 | F23: =SUM($E$21:E23) -> 54000 | G23: =12*$B$5*(1+$B$17)^(A23-1) -> 8400 | H23: =G23/(1+$B$15)^A23 -> 8400 | I23: =SUM($H$21:H23) -> 25200 | J23: =($B$6+$B$13)*$B$4+F23-(B23*(1-$B$14)-C23)/(1+$B$15)^A23 -> 0 | K23: =I23-J23 -> 25200 | L23: =IF(K23>=0,A23,"") -> 3
A24: 4 | B24: =$B$4*(1+$B$16)^A24 -> 120000 | C24: =IF(OR($E$4=0,A24>=$B$8),0,IF($E$5=0,$E$4-12*A24*$E$7,$E$4*(1+$E$5)^(12*A24)-$E$7*((1+$E$5)^(12*A24)-1)/$E$5)) -> 18000 | D24: =IF(A24<=$B$8,12*$E$7,0)+($B$10+$B$11+$B$12)*$B$4*(1+$B$16)^(A24-1) -> 18000 | E24: =D24/(1+$B$15)^A24 -> 18000 | F24: =SUM($E$21:E24) -> 72000 | G24: =12*$B$5*(1+$B$17)^(A24-1) -> 8400 | H24: =G24/(1+$B$15)^A24 -> 8400 | I24: =SUM($H$21:H24) -> 33600 | J24: =($B$6+$B$13)*$B$4+F24-(B24*(1-$B$14)-C24)/(1+$B$15)^A24 -> 0 | K24: =I24-J24 -> 33600 | L24: =IF(K24>=0,A24,"") -> 4
A25: 5 | B25: =$B$4*(1+$B$16)^A25 -> 120000 | C25: =IF(OR($E$4=0,A25>=$B$8),0,IF($E$5=0,$E$4-12*A25*$E$7,$E$4*(1+$E$5)^(12*A25)-$E$7*((1+$E$5)^(12*A25)-1)/$E$5)) -> 0 | D25: =IF(A25<=$B$8,12*$E$7,0)+($B$10+$B$11+$B$12)*$B$4*(1+$B$16)^(A25-1) -> 18000 | E25: =D25/(1+$B$15)^A25 -> 18000 | F25: =SUM($E$21:E25) -> 90000 | G25: =12*$B$5*(1+$B$17)^(A25-1) -> 8400 | H25: =G25/(1+$B$15)^A25 -> 8400 | I25: =SUM($H$21:H25) -> 42000 | J25: =($B$6+$B$13)*$B$4+F25-(B25*(1-$B$14)-C25)/(1+$B$15)^A25 -> 0 | K25: =I25-J25 -> 42000 | L25: =IF(K25>=0,A25,"") -> 5
A26: 6 | B26: =$B$4*(1+$B$16)^A26 -> 120000 | C26: =IF(OR($E$4=0,A26>=$B$8),0,IF($E$5=0,$E$4-12*A26*$E$7,$E$4*(1+$E$5)^(12*A26)-$E$7*((1+$E$5)^(12*A26)-1)/$E$5)) -> 0 | D26: =IF(A26<=$B$8,12*$E$7,0)+($B$10+$B$11+$B$12)*$B$4*(1+$B$16)^(A26-1) -> 0 | E26: =D26/(1+$B$15)^A26 -> 0 | F26: =SUM($E$21:E26) -> 90000 | G26: =12*$B$5*(1+$B$17)^(A26-1) -> 8400 | H26: =G26/(1+$B$15)^A26 -> 8400 | I26: =SUM($H$21:H26) -> 50400 | J26: =($B$6+$B$13)*$B$4+F26-(B26*(1-$B$14)-C26)/(1+$B$15)^A26 -> 0 | K26: =I26-J26 -> 50400 | L26: =IF(K26>=0,A26,"") -> 6
A27: 7 | B27: =$B$4*(1+$B$16)^A27 -> 120000 | C27: =IF(OR($E$4=0,A27>=$B$8),0,IF($E$5=0,$E$4-12*A27*$E$7,$E$4*(1+$E$5)^(12*A27)-$E$7*((1+$E$5)^(12*A27)-1)/$E$5)) -> 0 | D27: =IF(A27<=$B$8,12*$E$7,0)+($B$10+$B$11+$B$12)*$B$4*(1+$B$16)^(A27-1) -> 0 | E27: =D27/(1+$B$15)^A27 -> 0 | F27: =SUM($E$21:E27) -> 90000 | G27: =12*$B$5*(1+$B$17)^(A27-1) -> 8400 | H27: =G27/(1+$B$15)^A27 -> 8400 | I27: =SUM($H$21:H27) -> 58800 | J27: =($B$6+$B$13)*$B$4+F27-(B27*(1-$B$14)-C27)/(1+$B$15)^A27 -> 0 | K27: =I27-J27 -> 58800 | L27: =IF(K27>=0,A27,"") -> 7
A28: 8 | B28: =$B$4*(1+$B$16)^A28 -> 120000 | C28: =IF(OR($E$4=0,A28>=$B$8),0,IF($E$5=0,$E$4-12*A28*$E$7,$E$4*(1+$E$5)^(12*A28)-$E$7*((1+$E$5)^(12*A28)-1)/$E$5)) -> 0 | D28: =IF(A28<=$B$8,12*$E$7,0)+($B$10+$B$11+$B$12)*$B$4*(1+$B$16)^(A28-1) -> 0 | E28: =D28/(1+$B$15)^A28 -> 0 | F28: =SUM($E$21:E28) -> 90000 | G28: =12*$B$5*(1+$B$17)^(A28-1) -> 8400 | H28: =G28/(1+$B$15)^A28 -> 8400 | I28: =SUM($H$21:H28) -> 67200 | J28: =($B$6+$B$13)*$B$4+F28-(B28*(1-$B$14)-C28)/(1+$B$15)^A28 -> 0 | K28: =I28-J28 -> 67200 | L28: =IF(K28>=0,A28,"") -> 8
A29: 9 | B29: =$B$4*(1+$B$16)^A29 -> 120000 | C29: =IF(OR($E$4=0,A29>=$B$8),0,IF($E$5=0,$E$4-12*A29*$E$7,$E$4*(1+$E$5)^(12*A29)-$E$7*((1+$E$5)^(12*A29)-1)/$E$5)) -> 0 | D29: =IF(A29<=$B$8,12*$E$7,0)+($B$10+$B$11+$B$12)*$B$4*(1+$B$16)^(A29-1) -> 0 | E29: =D29/(1+$B$15)^A29 -> 0 | F29: =SUM($E$21:E29) -> 90000 | G29: =12*$B$5*(1+$B$17)^(A29-1) -> 8400 | H29: =G29/(1+$B$15)^A29 -> 8400 | I29: =SUM($H$21:H29) -> 75600 | J29: =($B$6+$B$13)*$B$4+F29-(B29*(1-$B$14)-C29)/(1+$B$15)^A29 -> 0 | K29: =I29-J29 -> 75600 | L29: =IF(K29>=0,A29,"") -> 9
A30: 10 | B30: =$B$4*(1+$B$16)^A30 -> 120000 | C30: =IF(OR($E$4=0,A30>=$B$8),0,IF($E$5=0,$E$4-12*A30*$E$7,$E$4*(1+$E$5)^(12*A30)-$E$7*((1+$E$5)^(12*A30)-1)/$E$5)) -> 0 | D30: =IF(A30<=$B$8,12*$E$7,0)+($B$10+$B$11+$B$12)*$B$4*(1+$B$16)^(A30-1) -> 0 | E30: =D30/(1+$B$15)^A30 -> 0 | F30: =SUM($E$21:E30) -> 90000 | G30: =12*$B$5*(1+$B$17)^(A30-1) -> 8400 | H30: =G30/(1+$B$15)^A30 -> 8400 | I30: =SUM($H$21:H30) -> 84000 | J30: =($B$6+$B$13)*$B$4+F30-(B30*(1-$B$14)-C30)/(1+$B$15)^A30 -> 0 | K30: =I30-J30 -> 84000 | L30: =IF(K30>=0,A30,"") -> 10
A31: 11 | B31: =$B$4*(1+$B$16)^A31 -> 120000 | C31: =IF(OR($E$4=0,A31>=$B$8),0,IF($E$5=0,$E$4-12*A31*$E$7,$E$4*(1+$E$5)^(12*A31)-$E$7*((1+$E$5)^(12*A31)-1)/$E$5)) -> 0 | D31: =IF(A31<=$B$8,12*$E$7,0)+($B$10+$B$11+$B$12)*$B$4*(1+$B$16)^(A31-1) -> 0 | E31: =D31/(1+$B$15)^A31 -> 0 | F31: =SUM($E$21:E31) -> 90000 | G31: =12*$B$5*(1+$B$17)^(A31-1) -> 8400 | H31: =G31/(1+$B$15)^A31 -> 8400 | I31: =SUM($H$21:H31) -> 92400 | J31: =($B$6+$B$13)*$B$4+F31-(B31*(1-$B$14)-C31)/(1+$B$15)^A31 -> 0 | K31: =I31-J31 -> 92400 | L31: =IF(K31>=0,A31,"") -> 11
A32: 12 | B32: =$B$4*(1+$B$16)^A32 -> 120000 | C32: =IF(OR($E$4=0,A32>=$B$8),0,IF($E$5=0,$E$4-12*A32*$E$7,$E$4*(1+$E$5)^(12*A32)-$E$7*((1+$E$5)^(12*A32)-1)/$E$5)) -> 0 | D32: =IF(A32<=$B$8,12*$E$7,0)+($B$10+$B$11+$B$12)*$B$4*(1+$B$16)^(A32-1) -> 0 | E32: =D32/(1+$B$15)^A32 -> 0 | F32: =SUM($E$21:E32) -> 90000 | G32: =12*$B$5*(1+$B$17)^(A32-1) -> 8400 | H32: =G32/(1+$B$15)^A32 -> 8400 | I32: =SUM($H$21:H32) -> 100800 | J32: =($B$6+$B$13)*$B$4+F32-(B32*(1-$B$14)-C32)/(1+$B$15)^A32 -> 0 | K32: =I32-J32 -> 100800 | L32: =IF(K32>=0,A32,"") -> 12
... A50: 30 | B50: =$B$4*(1+$B$16)^A50 -> 120000 | C50: =IF(OR($E$4=0,A50>=$B$8),0,IF($E$5=0,$E$4-12*A50*$E$7,$E$4*(1+$E$5)^(12*A50)-$E$7*((1+$E$5)^(12*A50)-1)/$E$5)) -> 0 | D50: =IF(A50<=$B$8,12*$E$7,0)+($B$10+$B$11+$B$12)*$B$4*(1+$B$16)^(A50-1) -> 0 | E50: =D50/(1+$B$15)^A50 -> 0 | F50: =SUM($E$21:E50) -> 90000 | G50: =12*$B$5*(1+$B$17)^(A50-1) -> 8400 | H50: =G50/(1+$B$15)^A50 -> 8400 | I50: =SUM($H$21:H50) -> 252000 | J50: =($B$6+$B$13)*$B$4+F50-(B50*(1-$B$14)-C50)/(1+$B$15)^A50 -> 0 | K50: =I50-J50 -> 252000 | L50: =IF(K50>=0,A50,"") -> 30

Sheet S05
A1: S05: 100% down payment with appreciation and discounting
A2: Hand calculation: V_2 = 100,000 x 1.1^2 = 121,000; C_B(2) = 100,000 - 121,000 / 1.21 = 0. C_R(2) = 12,000/1.1 + 12,000/1.21 = 10,909.09 + 9,917.36 = 20,826.45. UC = (0.10 - 0.10) x P = 0.
A3: Inputs (blue: edit to explore) | D3: Results (Excel formulas)
A4: Price P ($) | B4: 100000 | D4: Loan L = (1-d)P | E4: =(1-$B$6)*$B$4 -> 0
A5: Monthly rent R ($) | B5: 1000 | D5: Monthly rate i = r/12 | E5: =$B$7/12 -> 0.0054166667
A6: Down payment d | B6: 1 | D6: Number of payments n = 12T | E6: =12*$B$8 -> 360
A7: Mortgage rate r | B7: 0.065 | D7: Monthly payment M | E7: =IF($E$4=0,0,IF($E$5=0,$E$4/$E$6,$E$4*$E$5*(1+$E$5)^$E$6/((1+$E$5)^$E$6-1))) -> 0 | G7: 0 | H7: 0 | I7: =IF(ABS(E7-H7)<0.01,"PASS","FAIL") -> PASS | J7: =IF(ABS(E7-G7)<0.01,"PASS","FAIL") -> PASS
A8: Mortgage term T (years) | B8: 30 | G8: Hand calculation | H8: Python engine | I8: Excel vs engine | J8: Excel vs hand
A9: Holding period H (years) | B9: 2 | D9: C_B(H) cost of buying (PV) | E9: =INDEX(J21:J50,$B$9) -> 0 | G9: 0 | H9: 0 | I9: =IF(ABS(E9-H9)<0.01,"PASS","FAIL") -> PASS | J9: =IF(ABS(E9-G9)<0.01,"PASS","FAIL") -> PASS
A10: Property tax tau | B10: 0 | D10: C_R(H) cost of renting (PV) | E10: =INDEX(I21:I50,$B$9) -> 20826.446 | G10: 20826.45 | H10: 20826.446 | I10: =IF(ABS(E10-H10)<0.01,"PASS","FAIL") -> PASS | J10: =IF(ABS(E10-G10)<0.01,"PASS","FAIL") -> PASS
A11: Maintenance m | B11: 0 | D11: Delta(H) = C_R - C_B | E11: =INDEX(K21:K50,$B$9) -> 20826.446 | G11: 20826.45 | H11: 20826.446 | I11: =IF(ABS(E11-H11)<0.01,"PASS","FAIL") -> PASS | J11: =IF(ABS(E11-G11)<0.01,"PASS","FAIL") -> PASS
A12: Insurance h | B12: 0 | D12: Recommendation at H | E12: =IF(E11>=0,"buy","rent") -> buy | G12: buy | H12: buy | I12: =IF(E12=H12,"PASS","FAIL") -> PASS | J12: =IF(E12=G12,"PASS","FAIL") -> PASS
A13: Buying costs cb | B13: 0 | D13: Break-even year (search 1-30) | E13: =IF(COUNT(L21:L50)=0,"never",MIN(L21:L50)) -> 1 | G13: 1 | H13: 1 | I13: =IF(ABS(E13-H13)<0.01,"PASS","FAIL") -> PASS | J13: =IF(ABS(E13-G13)<0.01,"PASS","FAIL") -> PASS
A14: Selling costs cs | B14: 0 | D14: User cost UC = (k+tau+m+h-g)P | E14: =($B$15+$B$10+$B$11+$B$12-$B$16)*$B$4 -> 0 | G14: 0 | H14: 0 | I14: =IF(ABS(E14-H14)<0.01,"PASS","FAIL") -> PASS | J14: =IF(ABS(E14-G14)<0.01,"PASS","FAIL") -> PASS
A15: Discount rate k | B15: 0.1 | D15: Annual rent 12R | E15: =12*$B$5 -> 12000 | H15: 12000 | I15: =IF(ABS(E15-H15)<0.01,"PASS","FAIL") -> PASS
A16: Appreciation g | B16: 0.1 | D16: Loan balance B_H | E16: =INDEX(C21:C50,$B$9) -> 0 | H16: 0 | I16: =IF(ABS(E16-H16)<0.01,"PASS","FAIL") -> PASS
A17: Rent growth q | B17: 0 | G17: Hand and Python values are pasted for the inputs above; if you edit an input, only the Excel column updates.
A19: Year-by-year (selling at the end of year t)
A20: Year t | B20: Home value V_t | C20: Loan balance B_t | D20: Owner cost O_t | E20: PV of O_t | F20: Sum PV O (1..t) | G20: Rent_t | H20: PV of Rent_t | I20: C_R(t) | J20: C_B(t) | K20: Delta(t) = C_R - C_B | L20: Break-even helper
A21: 1 | B21: =$B$4*(1+$B$16)^A21 -> 110000 | C21: =IF(OR($E$4=0,A21>=$B$8),0,IF($E$5=0,$E$4-12*A21*$E$7,$E$4*(1+$E$5)^(12*A21)-$E$7*((1+$E$5)^(12*A21)-1)/$E$5)) -> 0 | D21: =IF(A21<=$B$8,12*$E$7,0)+($B$10+$B$11+$B$12)*$B$4*(1+$B$16)^(A21-1) -> 0 | E21: =D21/(1+$B$15)^A21 -> 0 | F21: =SUM($E$21:E21) -> 0 | G21: =12*$B$5*(1+$B$17)^(A21-1) -> 12000 | H21: =G21/(1+$B$15)^A21 -> 10909.091 | I21: =SUM($H$21:H21) -> 10909.091 | J21: =($B$6+$B$13)*$B$4+F21-(B21*(1-$B$14)-C21)/(1+$B$15)^A21 -> 0 | K21: =I21-J21 -> 10909.091 | L21: =IF(K21>=0,A21,"") -> 1
A22: 2 | B22: =$B$4*(1+$B$16)^A22 -> 121000 | C22: =IF(OR($E$4=0,A22>=$B$8),0,IF($E$5=0,$E$4-12*A22*$E$7,$E$4*(1+$E$5)^(12*A22)-$E$7*((1+$E$5)^(12*A22)-1)/$E$5)) -> 0 | D22: =IF(A22<=$B$8,12*$E$7,0)+($B$10+$B$11+$B$12)*$B$4*(1+$B$16)^(A22-1) -> 0 | E22: =D22/(1+$B$15)^A22 -> 0 | F22: =SUM($E$21:E22) -> 0 | G22: =12*$B$5*(1+$B$17)^(A22-1) -> 12000 | H22: =G22/(1+$B$15)^A22 -> 9917.3554 | I22: =SUM($H$21:H22) -> 20826.446 | J22: =($B$6+$B$13)*$B$4+F22-(B22*(1-$B$14)-C22)/(1+$B$15)^A22 -> 0 | K22: =I22-J22 -> 20826.446 | L22: =IF(K22>=0,A22,"") -> 2
A23: 3 | B23: =$B$4*(1+$B$16)^A23 -> 133100 | C23: =IF(OR($E$4=0,A23>=$B$8),0,IF($E$5=0,$E$4-12*A23*$E$7,$E$4*(1+$E$5)^(12*A23)-$E$7*((1+$E$5)^(12*A23)-1)/$E$5)) -> 0 | D23: =IF(A23<=$B$8,12*$E$7,0)+($B$10+$B$11+$B$12)*$B$4*(1+$B$16)^(A23-1) -> 0 | E23: =D23/(1+$B$15)^A23 -> 0 | F23: =SUM($E$21:E23) -> 0 | G23: =12*$B$5*(1+$B$17)^(A23-1) -> 12000 | H23: =G23/(1+$B$15)^A23 -> 9015.7776 | I23: =SUM($H$21:H23) -> 29842.224 | J23: =($B$6+$B$13)*$B$4+F23-(B23*(1-$B$14)-C23)/(1+$B$15)^A23 -> 0 | K23: =I23-J23 -> 29842.224 | L23: =IF(K23>=0,A23,"") -> 3
A24: 4 | B24: =$B$4*(1+$B$16)^A24 -> 146410 | C24: =IF(OR($E$4=0,A24>=$B$8),0,IF($E$5=0,$E$4-12*A24*$E$7,$E$4*(1+$E$5)^(12*A24)-$E$7*((1+$E$5)^(12*A24)-1)/$E$5)) -> 0 | D24: =IF(A24<=$B$8,12*$E$7,0)+($B$10+$B$11+$B$12)*$B$4*(1+$B$16)^(A24-1) -> 0 | E24: =D24/(1+$B$15)^A24 -> 0 | F24: =SUM($E$21:E24) -> 0 | G24: =12*$B$5*(1+$B$17)^(A24-1) -> 12000 | H24: =G24/(1+$B$15)^A24 -> 8196.1615 | I24: =SUM($H$21:H24) -> 38038.385 | J24: =($B$6+$B$13)*$B$4+F24-(B24*(1-$B$14)-C24)/(1+$B$15)^A24 -> 0 | K24: =I24-J24 -> 38038.385 | L24: =IF(K24>=0,A24,"") -> 4
A25: 5 | B25: =$B$4*(1+$B$16)^A25 -> 161051 | C25: =IF(OR($E$4=0,A25>=$B$8),0,IF($E$5=0,$E$4-12*A25*$E$7,$E$4*(1+$E$5)^(12*A25)-$E$7*((1+$E$5)^(12*A25)-1)/$E$5)) -> 0 | D25: =IF(A25<=$B$8,12*$E$7,0)+($B$10+$B$11+$B$12)*$B$4*(1+$B$16)^(A25-1) -> 0 | E25: =D25/(1+$B$15)^A25 -> 0 | F25: =SUM($E$21:E25) -> 0 | G25: =12*$B$5*(1+$B$17)^(A25-1) -> 12000 | H25: =G25/(1+$B$15)^A25 -> 7451.0559 | I25: =SUM($H$21:H25) -> 45489.441 | J25: =($B$6+$B$13)*$B$4+F25-(B25*(1-$B$14)-C25)/(1+$B$15)^A25 -> 0 | K25: =I25-J25 -> 45489.441 | L25: =IF(K25>=0,A25,"") -> 5
A26: 6 | B26: =$B$4*(1+$B$16)^A26 -> 177156.1 | C26: =IF(OR($E$4=0,A26>=$B$8),0,IF($E$5=0,$E$4-12*A26*$E$7,$E$4*(1+$E$5)^(12*A26)-$E$7*((1+$E$5)^(12*A26)-1)/$E$5)) -> 0 | D26: =IF(A26<=$B$8,12*$E$7,0)+($B$10+$B$11+$B$12)*$B$4*(1+$B$16)^(A26-1) -> 0 | E26: =D26/(1+$B$15)^A26 -> 0 | F26: =SUM($E$21:E26) -> 0 | G26: =12*$B$5*(1+$B$17)^(A26-1) -> 12000 | H26: =G26/(1+$B$15)^A26 -> 6773.6872 | I26: =SUM($H$21:H26) -> 52263.128 | J26: =($B$6+$B$13)*$B$4+F26-(B26*(1-$B$14)-C26)/(1+$B$15)^A26 -> 0 | K26: =I26-J26 -> 52263.128 | L26: =IF(K26>=0,A26,"") -> 6
A27: 7 | B27: =$B$4*(1+$B$16)^A27 -> 194871.71 | C27: =IF(OR($E$4=0,A27>=$B$8),0,IF($E$5=0,$E$4-12*A27*$E$7,$E$4*(1+$E$5)^(12*A27)-$E$7*((1+$E$5)^(12*A27)-1)/$E$5)) -> 0 | D27: =IF(A27<=$B$8,12*$E$7,0)+($B$10+$B$11+$B$12)*$B$4*(1+$B$16)^(A27-1) -> 0 | E27: =D27/(1+$B$15)^A27 -> 0 | F27: =SUM($E$21:E27) -> 0 | G27: =12*$B$5*(1+$B$17)^(A27-1) -> 12000 | H27: =G27/(1+$B$15)^A27 -> 6157.8974 | I27: =SUM($H$21:H27) -> 58421.026 | J27: =($B$6+$B$13)*$B$4+F27-(B27*(1-$B$14)-C27)/(1+$B$15)^A27 -> 0 | K27: =I27-J27 -> 58421.026 | L27: =IF(K27>=0,A27,"") -> 7
A28: 8 | B28: =$B$4*(1+$B$16)^A28 -> 214358.88 | C28: =IF(OR($E$4=0,A28>=$B$8),0,IF($E$5=0,$E$4-12*A28*$E$7,$E$4*(1+$E$5)^(12*A28)-$E$7*((1+$E$5)^(12*A28)-1)/$E$5)) -> 0 | D28: =IF(A28<=$B$8,12*$E$7,0)+($B$10+$B$11+$B$12)*$B$4*(1+$B$16)^(A28-1) -> 0 | E28: =D28/(1+$B$15)^A28 -> 0 | F28: =SUM($E$21:E28) -> 0 | G28: =12*$B$5*(1+$B$17)^(A28-1) -> 12000 | H28: =G28/(1+$B$15)^A28 -> 5598.0886 | I28: =SUM($H$21:H28) -> 64019.114 | J28: =($B$6+$B$13)*$B$4+F28-(B28*(1-$B$14)-C28)/(1+$B$15)^A28 -> 0 | K28: =I28-J28 -> 64019.114 | L28: =IF(K28>=0,A28,"") -> 8
A29: 9 | B29: =$B$4*(1+$B$16)^A29 -> 235794.77 | C29: =IF(OR($E$4=0,A29>=$B$8),0,IF($E$5=0,$E$4-12*A29*$E$7,$E$4*(1+$E$5)^(12*A29)-$E$7*((1+$E$5)^(12*A29)-1)/$E$5)) -> 0 | D29: =IF(A29<=$B$8,12*$E$7,0)+($B$10+$B$11+$B$12)*$B$4*(1+$B$16)^(A29-1) -> 0 | E29: =D29/(1+$B$15)^A29 -> 0 | F29: =SUM($E$21:E29) -> 0 | G29: =12*$B$5*(1+$B$17)^(A29-1) -> 12000 | H29: =G29/(1+$B$15)^A29 -> 5089.1714 | I29: =SUM($H$21:H29) -> 69108.286 | J29: =($B$6+$B$13)*$B$4+F29-(B29*(1-$B$14)-C29)/(1+$B$15)^A29 -> 0 | K29: =I29-J29 -> 69108.286 | L29: =IF(K29>=0,A29,"") -> 9
A30: 10 | B30: =$B$4*(1+$B$16)^A30 -> 259374.25 | C30: =IF(OR($E$4=0,A30>=$B$8),0,IF($E$5=0,$E$4-12*A30*$E$7,$E$4*(1+$E$5)^(12*A30)-$E$7*((1+$E$5)^(12*A30)-1)/$E$5)) -> 0 | D30: =IF(A30<=$B$8,12*$E$7,0)+($B$10+$B$11+$B$12)*$B$4*(1+$B$16)^(A30-1) -> 0 | E30: =D30/(1+$B$15)^A30 -> 0 | F30: =SUM($E$21:E30) -> 0 | G30: =12*$B$5*(1+$B$17)^(A30-1) -> 12000 | H30: =G30/(1+$B$15)^A30 -> 4626.5195 | I30: =SUM($H$21:H30) -> 73734.805 | J30: =($B$6+$B$13)*$B$4+F30-(B30*(1-$B$14)-C30)/(1+$B$15)^A30 -> 0 | K30: =I30-J30 -> 73734.805 | L30: =IF(K30>=0,A30,"") -> 10
A31: 11 | B31: =$B$4*(1+$B$16)^A31 -> 285311.67 | C31: =IF(OR($E$4=0,A31>=$B$8),0,IF($E$5=0,$E$4-12*A31*$E$7,$E$4*(1+$E$5)^(12*A31)-$E$7*((1+$E$5)^(12*A31)-1)/$E$5)) -> 0 | D31: =IF(A31<=$B$8,12*$E$7,0)+($B$10+$B$11+$B$12)*$B$4*(1+$B$16)^(A31-1) -> 0 | E31: =D31/(1+$B$15)^A31 -> 0 | F31: =SUM($E$21:E31) -> 0 | G31: =12*$B$5*(1+$B$17)^(A31-1) -> 12000 | H31: =G31/(1+$B$15)^A31 -> 4205.9268 | I31: =SUM($H$21:H31) -> 77940.732 | J31: =($B$6+$B$13)*$B$4+F31-(B31*(1-$B$14)-C31)/(1+$B$15)^A31 -> 0 | K31: =I31-J31 -> 77940.732 | L31: =IF(K31>=0,A31,"") -> 11
A32: 12 | B32: =$B$4*(1+$B$16)^A32 -> 313842.84 | C32: =IF(OR($E$4=0,A32>=$B$8),0,IF($E$5=0,$E$4-12*A32*$E$7,$E$4*(1+$E$5)^(12*A32)-$E$7*((1+$E$5)^(12*A32)-1)/$E$5)) -> 0 | D32: =IF(A32<=$B$8,12*$E$7,0)+($B$10+$B$11+$B$12)*$B$4*(1+$B$16)^(A32-1) -> 0 | E32: =D32/(1+$B$15)^A32 -> 0 | F32: =SUM($E$21:E32) -> 0 | G32: =12*$B$5*(1+$B$17)^(A32-1) -> 12000 | H32: =G32/(1+$B$15)^A32 -> 3823.5698 | I32: =SUM($H$21:H32) -> 81764.302 | J32: =($B$6+$B$13)*$B$4+F32-(B32*(1-$B$14)-C32)/(1+$B$15)^A32 -> 0 | K32: =I32-J32 -> 81764.302 | L32: =IF(K32>=0,A32,"") -> 12
... A50: 30 | B50: =$B$4*(1+$B$16)^A50 -> 1744940.2 | C50: =IF(OR($E$4=0,A50>=$B$8),0,IF($E$5=0,$E$4-12*A50*$E$7,$E$4*(1+$E$5)^(12*A50)-$E$7*((1+$E$5)^(12*A50)-1)/$E$5)) -> 0 | D50: =IF(A50<=$B$8,12*$E$7,0)+($B$10+$B$11+$B$12)*$B$4*(1+$B$16)^(A50-1) -> 0 | E50: =D50/(1+$B$15)^A50 -> 0 | F50: =SUM($E$21:E50) -> 0 | G50: =12*$B$5*(1+$B$17)^(A50-1) -> 12000 | H50: =G50/(1+$B$15)^A50 -> 687.70264 | I50: =SUM($H$21:H50) -> 113122.97 | J50: =($B$6+$B$13)*$B$4+F50-(B50*(1-$B$14)-C50)/(1+$B$15)^A50 -> 0 | K50: =I50-J50 -> 113122.97 | L50: =IF(K50>=0,A50,"") -> 30

Sheet S06
A1: S06: Rent growth compounding
A2: Hand calculation: Rent_1 = 12,000; Rent_2 = 12,000 x 1.05 = 12,600; Rent_3 = 12,000 x 1.05^2 = 13,230. C_R(3) = 37,830 (k = 0). C_B = 500,000 - 500,000 = 0.
A3: Inputs (blue: edit to explore) | D3: Results (Excel formulas)
A4: Price P ($) | B4: 500000 | D4: Loan L = (1-d)P | E4: =(1-$B$6)*$B$4 -> 0
A5: Monthly rent R ($) | B5: 1000 | D5: Monthly rate i = r/12 | E5: =$B$7/12 -> 0
A6: Down payment d | B6: 1 | D6: Number of payments n = 12T | E6: =12*$B$8 -> 360
A7: Mortgage rate r | B7: 0 | D7: Monthly payment M | E7: =IF($E$4=0,0,IF($E$5=0,$E$4/$E$6,$E$4*$E$5*(1+$E$5)^$E$6/((1+$E$5)^$E$6-1))) -> 0 | H7: 0 | I7: =IF(ABS(E7-H7)<0.01,"PASS","FAIL") -> PASS
A8: Mortgage term T (years) | B8: 30 | G8: Hand calculation | H8: Python engine | I8: Excel vs engine | J8: Excel vs hand
A9: Holding period H (years) | B9: 3 | D9: C_B(H) cost of buying (PV) | E9: =INDEX(J21:J50,$B$9) -> 0 | G9: 0 | H9: 0 | I9: =IF(ABS(E9-H9)<0.01,"PASS","FAIL") -> PASS | J9: =IF(ABS(E9-G9)<0.01,"PASS","FAIL") -> PASS
A10: Property tax tau | B10: 0 | D10: C_R(H) cost of renting (PV) | E10: =INDEX(I21:I50,$B$9) -> 37830 | G10: 37830 | H10: 37830 | I10: =IF(ABS(E10-H10)<0.01,"PASS","FAIL") -> PASS | J10: =IF(ABS(E10-G10)<0.01,"PASS","FAIL") -> PASS
A11: Maintenance m | B11: 0 | D11: Delta(H) = C_R - C_B | E11: =INDEX(K21:K50,$B$9) -> 37830 | G11: 37830 | H11: 37830 | I11: =IF(ABS(E11-H11)<0.01,"PASS","FAIL") -> PASS | J11: =IF(ABS(E11-G11)<0.01,"PASS","FAIL") -> PASS
A12: Insurance h | B12: 0 | D12: Recommendation at H | E12: =IF(E11>=0,"buy","rent") -> buy | G12: buy | H12: buy | I12: =IF(E12=H12,"PASS","FAIL") -> PASS | J12: =IF(E12=G12,"PASS","FAIL") -> PASS
A13: Buying costs cb | B13: 0 | D13: Break-even year (search 1-30) | E13: =IF(COUNT(L21:L50)=0,"never",MIN(L21:L50)) -> 1 | G13: 1 | H13: 1 | I13: =IF(ABS(E13-H13)<0.01,"PASS","FAIL") -> PASS | J13: =IF(ABS(E13-G13)<0.01,"PASS","FAIL") -> PASS
A14: Selling costs cs | B14: 0 | D14: User cost UC = (k+tau+m+h-g)P | E14: =($B$15+$B$10+$B$11+$B$12-$B$16)*$B$4 -> 0 | H14: 0 | I14: =IF(ABS(E14-H14)<0.01,"PASS","FAIL") -> PASS
A15: Discount rate k | B15: 0 | D15: Annual rent 12R | E15: =12*$B$5 -> 12000 | H15: 12000 | I15: =IF(ABS(E15-H15)<0.01,"PASS","FAIL") -> PASS
A16: Appreciation g | B16: 0 | D16: Loan balance B_H | E16: =INDEX(C21:C50,$B$9) -> 0 | H16: 0 | I16: =IF(ABS(E16-H16)<0.01,"PASS","FAIL") -> PASS
A17: Rent growth q | B17: 0.05 | G17: Hand and Python values are pasted for the inputs above; if you edit an input, only the Excel column updates.
A19: Year-by-year (selling at the end of year t)
A20: Year t | B20: Home value V_t | C20: Loan balance B_t | D20: Owner cost O_t | E20: PV of O_t | F20: Sum PV O (1..t) | G20: Rent_t | H20: PV of Rent_t | I20: C_R(t) | J20: C_B(t) | K20: Delta(t) = C_R - C_B | L20: Break-even helper
A21: 1 | B21: =$B$4*(1+$B$16)^A21 -> 500000 | C21: =IF(OR($E$4=0,A21>=$B$8),0,IF($E$5=0,$E$4-12*A21*$E$7,$E$4*(1+$E$5)^(12*A21)-$E$7*((1+$E$5)^(12*A21)-1)/$E$5)) -> 0 | D21: =IF(A21<=$B$8,12*$E$7,0)+($B$10+$B$11+$B$12)*$B$4*(1+$B$16)^(A21-1) -> 0 | E21: =D21/(1+$B$15)^A21 -> 0 | F21: =SUM($E$21:E21) -> 0 | G21: =12*$B$5*(1+$B$17)^(A21-1) -> 12000 | H21: =G21/(1+$B$15)^A21 -> 12000 | I21: =SUM($H$21:H21) -> 12000 | J21: =($B$6+$B$13)*$B$4+F21-(B21*(1-$B$14)-C21)/(1+$B$15)^A21 -> 0 | K21: =I21-J21 -> 12000 | L21: =IF(K21>=0,A21,"") -> 1
A22: 2 | B22: =$B$4*(1+$B$16)^A22 -> 500000 | C22: =IF(OR($E$4=0,A22>=$B$8),0,IF($E$5=0,$E$4-12*A22*$E$7,$E$4*(1+$E$5)^(12*A22)-$E$7*((1+$E$5)^(12*A22)-1)/$E$5)) -> 0 | D22: =IF(A22<=$B$8,12*$E$7,0)+($B$10+$B$11+$B$12)*$B$4*(1+$B$16)^(A22-1) -> 0 | E22: =D22/(1+$B$15)^A22 -> 0 | F22: =SUM($E$21:E22) -> 0 | G22: =12*$B$5*(1+$B$17)^(A22-1) -> 12600 | H22: =G22/(1+$B$15)^A22 -> 12600 | I22: =SUM($H$21:H22) -> 24600 | J22: =($B$6+$B$13)*$B$4+F22-(B22*(1-$B$14)-C22)/(1+$B$15)^A22 -> 0 | K22: =I22-J22 -> 24600 | L22: =IF(K22>=0,A22,"") -> 2
A23: 3 | B23: =$B$4*(1+$B$16)^A23 -> 500000 | C23: =IF(OR($E$4=0,A23>=$B$8),0,IF($E$5=0,$E$4-12*A23*$E$7,$E$4*(1+$E$5)^(12*A23)-$E$7*((1+$E$5)^(12*A23)-1)/$E$5)) -> 0 | D23: =IF(A23<=$B$8,12*$E$7,0)+($B$10+$B$11+$B$12)*$B$4*(1+$B$16)^(A23-1) -> 0 | E23: =D23/(1+$B$15)^A23 -> 0 | F23: =SUM($E$21:E23) -> 0 | G23: =12*$B$5*(1+$B$17)^(A23-1) -> 13230 | H23: =G23/(1+$B$15)^A23 -> 13230 | I23: =SUM($H$21:H23) -> 37830 | J23: =($B$6+$B$13)*$B$4+F23-(B23*(1-$B$14)-C23)/(1+$B$15)^A23 -> 0 | K23: =I23-J23 -> 37830 | L23: =IF(K23>=0,A23,"") -> 3
A24: 4 | B24: =$B$4*(1+$B$16)^A24 -> 500000 | C24: =IF(OR($E$4=0,A24>=$B$8),0,IF($E$5=0,$E$4-12*A24*$E$7,$E$4*(1+$E$5)^(12*A24)-$E$7*((1+$E$5)^(12*A24)-1)/$E$5)) -> 0 | D24: =IF(A24<=$B$8,12*$E$7,0)+($B$10+$B$11+$B$12)*$B$4*(1+$B$16)^(A24-1) -> 0 | E24: =D24/(1+$B$15)^A24 -> 0 | F24: =SUM($E$21:E24) -> 0 | G24: =12*$B$5*(1+$B$17)^(A24-1) -> 13891.5 | H24: =G24/(1+$B$15)^A24 -> 13891.5 | I24: =SUM($H$21:H24) -> 51721.5 | J24: =($B$6+$B$13)*$B$4+F24-(B24*(1-$B$14)-C24)/(1+$B$15)^A24 -> 0 | K24: =I24-J24 -> 51721.5 | L24: =IF(K24>=0,A24,"") -> 4
A25: 5 | B25: =$B$4*(1+$B$16)^A25 -> 500000 | C25: =IF(OR($E$4=0,A25>=$B$8),0,IF($E$5=0,$E$4-12*A25*$E$7,$E$4*(1+$E$5)^(12*A25)-$E$7*((1+$E$5)^(12*A25)-1)/$E$5)) -> 0 | D25: =IF(A25<=$B$8,12*$E$7,0)+($B$10+$B$11+$B$12)*$B$4*(1+$B$16)^(A25-1) -> 0 | E25: =D25/(1+$B$15)^A25 -> 0 | F25: =SUM($E$21:E25) -> 0 | G25: =12*$B$5*(1+$B$17)^(A25-1) -> 14586.075 | H25: =G25/(1+$B$15)^A25 -> 14586.075 | I25: =SUM($H$21:H25) -> 66307.575 | J25: =($B$6+$B$13)*$B$4+F25-(B25*(1-$B$14)-C25)/(1+$B$15)^A25 -> 0 | K25: =I25-J25 -> 66307.575 | L25: =IF(K25>=0,A25,"") -> 5
A26: 6 | B26: =$B$4*(1+$B$16)^A26 -> 500000 | C26: =IF(OR($E$4=0,A26>=$B$8),0,IF($E$5=0,$E$4-12*A26*$E$7,$E$4*(1+$E$5)^(12*A26)-$E$7*((1+$E$5)^(12*A26)-1)/$E$5)) -> 0 | D26: =IF(A26<=$B$8,12*$E$7,0)+($B$10+$B$11+$B$12)*$B$4*(1+$B$16)^(A26-1) -> 0 | E26: =D26/(1+$B$15)^A26 -> 0 | F26: =SUM($E$21:E26) -> 0 | G26: =12*$B$5*(1+$B$17)^(A26-1) -> 15315.379 | H26: =G26/(1+$B$15)^A26 -> 15315.379 | I26: =SUM($H$21:H26) -> 81622.954 | J26: =($B$6+$B$13)*$B$4+F26-(B26*(1-$B$14)-C26)/(1+$B$15)^A26 -> 0 | K26: =I26-J26 -> 81622.954 | L26: =IF(K26>=0,A26,"") -> 6
A27: 7 | B27: =$B$4*(1+$B$16)^A27 -> 500000 | C27: =IF(OR($E$4=0,A27>=$B$8),0,IF($E$5=0,$E$4-12*A27*$E$7,$E$4*(1+$E$5)^(12*A27)-$E$7*((1+$E$5)^(12*A27)-1)/$E$5)) -> 0 | D27: =IF(A27<=$B$8,12*$E$7,0)+($B$10+$B$11+$B$12)*$B$4*(1+$B$16)^(A27-1) -> 0 | E27: =D27/(1+$B$15)^A27 -> 0 | F27: =SUM($E$21:E27) -> 0 | G27: =12*$B$5*(1+$B$17)^(A27-1) -> 16081.148 | H27: =G27/(1+$B$15)^A27 -> 16081.148 | I27: =SUM($H$21:H27) -> 97704.101 | J27: =($B$6+$B$13)*$B$4+F27-(B27*(1-$B$14)-C27)/(1+$B$15)^A27 -> 0 | K27: =I27-J27 -> 97704.101 | L27: =IF(K27>=0,A27,"") -> 7
A28: 8 | B28: =$B$4*(1+$B$16)^A28 -> 500000 | C28: =IF(OR($E$4=0,A28>=$B$8),0,IF($E$5=0,$E$4-12*A28*$E$7,$E$4*(1+$E$5)^(12*A28)-$E$7*((1+$E$5)^(12*A28)-1)/$E$5)) -> 0 | D28: =IF(A28<=$B$8,12*$E$7,0)+($B$10+$B$11+$B$12)*$B$4*(1+$B$16)^(A28-1) -> 0 | E28: =D28/(1+$B$15)^A28 -> 0 | F28: =SUM($E$21:E28) -> 0 | G28: =12*$B$5*(1+$B$17)^(A28-1) -> 16885.205 | H28: =G28/(1+$B$15)^A28 -> 16885.205 | I28: =SUM($H$21:H28) -> 114589.31 | J28: =($B$6+$B$13)*$B$4+F28-(B28*(1-$B$14)-C28)/(1+$B$15)^A28 -> 0 | K28: =I28-J28 -> 114589.31 | L28: =IF(K28>=0,A28,"") -> 8
A29: 9 | B29: =$B$4*(1+$B$16)^A29 -> 500000 | C29: =IF(OR($E$4=0,A29>=$B$8),0,IF($E$5=0,$E$4-12*A29*$E$7,$E$4*(1+$E$5)^(12*A29)-$E$7*((1+$E$5)^(12*A29)-1)/$E$5)) -> 0 | D29: =IF(A29<=$B$8,12*$E$7,0)+($B$10+$B$11+$B$12)*$B$4*(1+$B$16)^(A29-1) -> 0 | E29: =D29/(1+$B$15)^A29 -> 0 | F29: =SUM($E$21:E29) -> 0 | G29: =12*$B$5*(1+$B$17)^(A29-1) -> 17729.465 | H29: =G29/(1+$B$15)^A29 -> 17729.465 | I29: =SUM($H$21:H29) -> 132318.77 | J29: =($B$6+$B$13)*$B$4+F29-(B29*(1-$B$14)-C29)/(1+$B$15)^A29 -> 0 | K29: =I29-J29 -> 132318.77 | L29: =IF(K29>=0,A29,"") -> 9
A30: 10 | B30: =$B$4*(1+$B$16)^A30 -> 500000 | C30: =IF(OR($E$4=0,A30>=$B$8),0,IF($E$5=0,$E$4-12*A30*$E$7,$E$4*(1+$E$5)^(12*A30)-$E$7*((1+$E$5)^(12*A30)-1)/$E$5)) -> 0 | D30: =IF(A30<=$B$8,12*$E$7,0)+($B$10+$B$11+$B$12)*$B$4*(1+$B$16)^(A30-1) -> 0 | E30: =D30/(1+$B$15)^A30 -> 0 | F30: =SUM($E$21:E30) -> 0 | G30: =12*$B$5*(1+$B$17)^(A30-1) -> 18615.939 | H30: =G30/(1+$B$15)^A30 -> 18615.939 | I30: =SUM($H$21:H30) -> 150934.71 | J30: =($B$6+$B$13)*$B$4+F30-(B30*(1-$B$14)-C30)/(1+$B$15)^A30 -> 0 | K30: =I30-J30 -> 150934.71 | L30: =IF(K30>=0,A30,"") -> 10
A31: 11 | B31: =$B$4*(1+$B$16)^A31 -> 500000 | C31: =IF(OR($E$4=0,A31>=$B$8),0,IF($E$5=0,$E$4-12*A31*$E$7,$E$4*(1+$E$5)^(12*A31)-$E$7*((1+$E$5)^(12*A31)-1)/$E$5)) -> 0 | D31: =IF(A31<=$B$8,12*$E$7,0)+($B$10+$B$11+$B$12)*$B$4*(1+$B$16)^(A31-1) -> 0 | E31: =D31/(1+$B$15)^A31 -> 0 | F31: =SUM($E$21:E31) -> 0 | G31: =12*$B$5*(1+$B$17)^(A31-1) -> 19546.736 | H31: =G31/(1+$B$15)^A31 -> 19546.736 | I31: =SUM($H$21:H31) -> 170481.45 | J31: =($B$6+$B$13)*$B$4+F31-(B31*(1-$B$14)-C31)/(1+$B$15)^A31 -> 0 | K31: =I31-J31 -> 170481.45 | L31: =IF(K31>=0,A31,"") -> 11
A32: 12 | B32: =$B$4*(1+$B$16)^A32 -> 500000 | C32: =IF(OR($E$4=0,A32>=$B$8),0,IF($E$5=0,$E$4-12*A32*$E$7,$E$4*(1+$E$5)^(12*A32)-$E$7*((1+$E$5)^(12*A32)-1)/$E$5)) -> 0 | D32: =IF(A32<=$B$8,12*$E$7,0)+($B$10+$B$11+$B$12)*$B$4*(1+$B$16)^(A32-1) -> 0 | E32: =D32/(1+$B$15)^A32 -> 0 | F32: =SUM($E$21:E32) -> 0 | G32: =12*$B$5*(1+$B$17)^(A32-1) -> 20524.072 | H32: =G32/(1+$B$15)^A32 -> 20524.072 | I32: =SUM($H$21:H32) -> 191005.52 | J32: =($B$6+$B$13)*$B$4+F32-(B32*(1-$B$14)-C32)/(1+$B$15)^A32 -> 0 | K32: =I32-J32 -> 191005.52 | L32: =IF(K32>=0,A32,"") -> 12
... A50: 30 | B50: =$B$4*(1+$B$16)^A50 -> 500000 | C50: =IF(OR($E$4=0,A50>=$B$8),0,IF($E$5=0,$E$4-12*A50*$E$7,$E$4*(1+$E$5)^(12*A50)-$E$7*((1+$E$5)^(12*A50)-1)/$E$5)) -> 0 | D50: =IF(A50<=$B$8,12*$E$7,0)+($B$10+$B$11+$B$12)*$B$4*(1+$B$16)^(A50-1) -> 0 | E50: =D50/(1+$B$15)^A50 -> 0 | F50: =SUM($E$21:E50) -> 0 | G50: =12*$B$5*(1+$B$17)^(A50-1) -> 49393.627 | H50: =G50/(1+$B$15)^A50 -> 49393.627 | I50: =SUM($H$21:H50) -> 797266.17 | J50: =($B$6+$B$13)*$B$4+F50-(B50*(1-$B$14)-C50)/(1+$B$15)^A50 -> 0 | K50: =I50-J50 -> 797266.17 | L50: =IF(K50>=0,A50,"") -> 30

Sheet S07
A1: S07: Standard 30-year mortgage (published payment check)
A2: Hand calculation: L = 240,000 at 6% over 30 years: M = 240,000 x 0.005 x 1.005^360 / (1.005^360 - 1) = 1,438.92, the standard published value. Costs and break-even are checked against the independent monthly calculation and Excel.
A3: Inputs (blue: edit to explore) | D3: Results (Excel formulas)
A4: Price P ($) | B4: 300000 | D4: Loan L = (1-d)P | E4: =(1-$B$6)*$B$4 -> 240000
A5: Monthly rent R ($) | B5: 1500 | D5: Monthly rate i = r/12 | E5: =$B$7/12 -> 0.005
A6: Down payment d | B6: 0.2 | D6: Number of payments n = 12T | E6: =12*$B$8 -> 360
A7: Mortgage rate r | B7: 0.06 | D7: Monthly payment M | E7: =IF($E$4=0,0,IF($E$5=0,$E$4/$E$6,$E$4*$E$5*(1+$E$5)^$E$6/((1+$E$5)^$E$6-1))) -> 1438.9213 | G7: 1438.92 | H7: 1438.9213 | I7: =IF(ABS(E7-H7)<0.01,"PASS","FAIL") -> PASS | J7: =IF(ABS(E7-G7)<0.01,"PASS","FAIL") -> PASS
A8: Mortgage term T (years) | B8: 30 | G8: Hand calculation | H8: Python engine | I8: Excel vs engine | J8: Excel vs hand
A9: Holding period H (years) | B9: 7 | D9: C_B(H) cost of buying (PV) | E9: =INDEX(J21:J50,$B$9) -> 119722.01 | H9: 119722.01 | I9: =IF(ABS(E9-H9)<0.01,"PASS","FAIL") -> PASS
A10: Property tax tau | B10: 0.01 | D10: C_R(H) cost of renting (PV) | E10: =INDEX(I21:I50,$B$9) -> 113356.44 | H10: 113356.44 | I10: =IF(ABS(E10-H10)<0.01,"PASS","FAIL") -> PASS
A11: Maintenance m | B11: 0.01 | D11: Delta(H) = C_R - C_B | E11: =INDEX(K21:K50,$B$9) -> -6365.5684 | H11: -6365.5684 | I11: =IF(ABS(E11-H11)<0.01,"PASS","FAIL") -> PASS
A12: Insurance h | B12: 0.0035 | D12: Recommendation at H | E12: =IF(E11>=0,"buy","rent") -> rent | H12: rent | I12: =IF(E12=H12,"PASS","FAIL") -> PASS
A13: Buying costs cb | B13: 0.03 | D13: Break-even year (search 1-30) | E13: =IF(COUNT(L21:L50)=0,"never",MIN(L21:L50)) -> 10 | H13: 10 | I13: =IF(ABS(E13-H13)<0.01,"PASS","FAIL") -> PASS
A14: Selling costs cs | B14: 0.06 | D14: User cost UC = (k+tau+m+h-g)P | E14: =($B$15+$B$10+$B$11+$B$12-$B$16)*$B$4 -> 13050 | H14: 13050 | I14: =IF(ABS(E14-H14)<0.01,"PASS","FAIL") -> PASS
A15: Discount rate k | B15: 0.05 | D15: Annual rent 12R | E15: =12*$B$5 -> 18000 | H15: 18000 | I15: =IF(ABS(E15-H15)<0.01,"PASS","FAIL") -> PASS
A16: Appreciation g | B16: 0.03 | D16: Loan balance B_H | E16: =INDEX(C21:C50,$B$9) -> 215134.53 | H16: 215134.53 | I16: =IF(ABS(E16-H16)<0.01,"PASS","FAIL") -> PASS
A17: Rent growth q | B17: 0.03 | G17: Hand and Python values are pasted for the inputs above; if you edit an input, only the Excel column updates.
A19: Year-by-year (selling at the end of year t)
A20: Year t | B20: Home value V_t | C20: Loan balance B_t | D20: Owner cost O_t | E20: PV of O_t | F20: Sum PV O (1..t) | G20: Rent_t | H20: PV of Rent_t | I20: C_R(t) | J20: C_B(t) | K20: Delta(t) = C_R - C_B | L20: Break-even helper
A21: 1 | B21: =$B$4*(1+$B$16)^A21 -> 309000 | C21: =IF(OR($E$4=0,A21>=$B$8),0,IF($E$5=0,$E$4-12*A21*$E$7,$E$4*(1+$E$5)^(12*A21)-$E$7*((1+$E$5)^(12*A21)-1)/$E$5)) -> 237052.77 | D21: =IF(A21<=$B$8,12*$E$7,0)+($B$10+$B$11+$B$12)*$B$4*(1+$B$16)^(A21-1) -> 24317.055 | E21: =D21/(1+$B$15)^A21 -> 23159.1 | F21: =SUM($E$21:E21) -> 23159.1 | G21: =12*$B$5*(1+$B$17)^(A21-1) -> 18000 | H21: =G21/(1+$B$15)^A21 -> 17142.857 | I21: =SUM($H$21:H21) -> 17142.857 | J21: =($B$6+$B$13)*$B$4+F21-(B21*(1-$B$14)-C21)/(1+$B$15)^A21 -> 41295.073 | K21: =I21-J21 -> -24152.216 | L21: =IF(K21>=0,A21,"")
A22: 2 | B22: =$B$4*(1+$B$16)^A22 -> 318270 | C22: =IF(OR($E$4=0,A22>=$B$8),0,IF($E$5=0,$E$4-12*A22*$E$7,$E$4*(1+$E$5)^(12*A22)-$E$7*((1+$E$5)^(12*A22)-1)/$E$5)) -> 233923.77 | D22: =IF(A22<=$B$8,12*$E$7,0)+($B$10+$B$11+$B$12)*$B$4*(1+$B$16)^(A22-1) -> 24528.555 | E22: =D22/(1+$B$15)^A22 -> 22248.123 | F22: =SUM($E$21:E22) -> 45407.223 | G22: =12*$B$5*(1+$B$17)^(A22-1) -> 18540 | H22: =G22/(1+$B$15)^A22 -> 16816.327 | I22: =SUM($H$21:H22) -> 33959.184 | J22: =($B$6+$B$13)*$B$4+F22-(B22*(1-$B$14)-C22)/(1+$B$15)^A22 -> 55223.518 | K22: =I22-J22 -> -21264.334 | L22: =IF(K22>=0,A22,"")
A23: 3 | B23: =$B$4*(1+$B$16)^A23 -> 327818.1 | C23: =IF(OR($E$4=0,A23>=$B$8),0,IF($E$5=0,$E$4-12*A23*$E$7,$E$4*(1+$E$5)^(12*A23)-$E$7*((1+$E$5)^(12*A23)-1)/$E$5)) -> 230601.77 | D23: =IF(A23<=$B$8,12*$E$7,0)+($B$10+$B$11+$B$12)*$B$4*(1+$B$16)^(A23-1) -> 24746.4 | E23: =D23/(1+$B$15)^A23 -> 21376.871 | F23: =SUM($E$21:E23) -> 66784.094 | G23: =12*$B$5*(1+$B$17)^(A23-1) -> 19096.2 | H23: =G23/(1+$B$15)^A23 -> 16496.016 | I23: =SUM($H$21:H23) -> 50455.199 | J23: =($B$6+$B$13)*$B$4+F23-(B23*(1-$B$14)-C23)/(1+$B$15)^A23 -> 68795.867 | K23: =I23-J23 -> -18340.668 | L23: =IF(K23>=0,A23,"")
A24: 4 | B24: =$B$4*(1+$B$16)^A24 -> 337652.64 | C24: =IF(OR($E$4=0,A24>=$B$8),0,IF($E$5=0,$E$4-12*A24*$E$7,$E$4*(1+$E$5)^(12*A24)-$E$7*((1+$E$5)^(12*A24)-1)/$E$5)) -> 227074.88 | D24: =IF(A24<=$B$8,12*$E$7,0)+($B$10+$B$11+$B$12)*$B$4*(1+$B$16)^(A24-1) -> 24970.78 | E24: =D24/(1+$B$15)^A24 -> 20543.523 | F24: =SUM($E$21:E24) -> 87327.616 | G24: =12*$B$5*(1+$B$17)^(A24-1) -> 19669.086 | H24: =G24/(1+$B$15)^A24 -> 16181.806 | I24: =SUM($H$21:H24) -> 66637.005 | J24: =($B$6+$B$13)*$B$4+F24-(B24*(1-$B$14)-C24)/(1+$B$15)^A24 -> 82022.275 | K24: =I24-J24 -> -15385.27 | L24: =IF(K24>=0,A24,"")
A25: 5 | B25: =$B$4*(1+$B$16)^A25 -> 347782.22 | C25: =IF(OR($E$4=0,A25>=$B$8),0,IF($E$5=0,$E$4-12*A25*$E$7,$E$4*(1+$E$5)^(12*A25)-$E$7*((1+$E$5)^(12*A25)-1)/$E$5)) -> 223330.46 | D25: =IF(A25<=$B$8,12*$E$7,0)+($B$10+$B$11+$B$12)*$B$4*(1+$B$16)^(A25-1) -> 25201.892 | E25: =D25/(1+$B$15)^A25 -> 19746.342 | F25: =SUM($E$21:E25) -> 107073.96 | G25: =12*$B$5*(1+$B$17)^(A25-1) -> 20259.159 | H25: =G25/(1+$B$15)^A25 -> 15873.581 | I25: =SUM($H$21:H25) -> 82510.586 | J25: =($B$6+$B$13)*$B$4+F25-(B25*(1-$B$14)-C25)/(1+$B$15)^A25 -> 94912.532 | K25: =I25-J25 -> -12401.946 | L25: =IF(K25>=0,A25,"")
A26: 6 | B26: =$B$4*(1+$B$16)^A26 -> 358215.69 | C26: =IF(OR($E$4=0,A26>=$B$8),0,IF($E$5=0,$E$4-12*A26*$E$7,$E$4*(1+$E$5)^(12*A26)-$E$7*((1+$E$5)^(12*A26)-1)/$E$5)) -> 219355.09 | D26: =IF(A26<=$B$8,12*$E$7,0)+($B$10+$B$11+$B$12)*$B$4*(1+$B$16)^(A26-1) -> 25439.937 | E26: =D26/(1+$B$15)^A26 -> 18983.673 | F26: =SUM($E$21:E26) -> 126057.63 | G26: =12*$B$5*(1+$B$17)^(A26-1) -> 20866.933 | H26: =G26/(1+$B$15)^A26 -> 15571.227 | I26: =SUM($H$21:H26) -> 98081.813 | J26: =($B$6+$B$13)*$B$4+F26-(B26*(1-$B$14)-C26)/(1+$B$15)^A26 -> 107476.08 | K26: =I26-J26 -> -9394.2634 | L26: =IF(K26>=0,A26,"")
A27: 7 | B27: =$B$4*(1+$B$16)^A27 -> 368962.16 | C27: =IF(OR($E$4=0,A27>=$B$8),0,IF($E$5=0,$E$4-12*A27*$E$7,$E$4*(1+$E$5)^(12*A27)-$E$7*((1+$E$5)^(12*A27)-1)/$E$5)) -> 215134.53 | D27: =IF(A27<=$B$8,12*$E$7,0)+($B$10+$B$11+$B$12)*$B$4*(1+$B$16)^(A27-1) -> 25685.124 | E27: =D27/(1+$B$15)^A27 -> 18253.938 | F27: =SUM($E$21:E27) -> 144311.57 | G27: =12*$B$5*(1+$B$17)^(A27-1) -> 21492.941 | H27: =G27/(1+$B$15)^A27 -> 15274.632 | I27: =SUM($H$21:H27) -> 113356.44 | J27: =($B$6+$B$13)*$B$4+F27-(B27*(1-$B$14)-C27)/(1+$B$15)^A27 -> 119722.01 | K27: =I27-J27 -> -6365.5684 | L27: =IF(K27>=0,A27,"")
A28: 8 | B28: =$B$4*(1+$B$16)^A28 -> 380031.02 | C28: =IF(OR($E$4=0,A28>=$B$8),0,IF($E$5=0,$E$4-12*A28*$E$7,$E$4*(1+$E$5)^(12*A28)-$E$7*((1+$E$5)^(12*A28)-1)/$E$5)) -> 210653.65 | D28: =IF(A28<=$B$8,12*$E$7,0)+($B$10+$B$11+$B$12)*$B$4*(1+$B$16)^(A28-1) -> 25937.666 | E28: =D28/(1+$B$15)^A28 -> 17555.633 | F28: =SUM($E$21:E28) -> 161867.2 | G28: =12*$B$5*(1+$B$17)^(A28-1) -> 22137.73 | H28: =G28/(1+$B$15)^A28 -> 14983.687 | I28: =SUM($H$21:H28) -> 128340.13 | J28: =($B$6+$B$13)*$B$4+F28-(B28*(1-$B$14)-C28)/(1+$B$15)^A28 -> 131659.13 | K28: =I28-J28 -> -3318.9942 | L28: =IF(K28>=0,A28,"")
A29: 9 | B29: =$B$4*(1+$B$16)^A29 -> 391431.96 | C29: =IF(OR($E$4=0,A29>=$B$8),0,IF($E$5=0,$E$4-12*A29*$E$7,$E$4*(1+$E$5)^(12*A29)-$E$7*((1+$E$5)^(12*A29)-1)/$E$5)) -> 205896.4 | D29: =IF(A29<=$B$8,12*$E$7,0)+($B$10+$B$11+$B$12)*$B$4*(1+$B$16)^(A29-1) -> 26197.784 | E29: =D29/(1+$B$15)^A29 -> 16887.325 | F29: =SUM($E$21:E29) -> 178754.53 | G29: =12*$B$5*(1+$B$17)^(A29-1) -> 22801.861 | H29: =G29/(1+$B$15)^A29 -> 14698.283 | I29: =SUM($H$21:H29) -> 143038.41 | J29: =($B$6+$B$13)*$B$4+F29-(B29*(1-$B$14)-C29)/(1+$B$15)^A29 -> 143295.89 | K29: =I29-J29 -> -257.47366 | L29: =IF(K29>=0,A29,"")
A30: 10 | B30: =$B$4*(1+$B$16)^A30 -> 403174.91 | C30: =IF(OR($E$4=0,A30>=$B$8),0,IF($E$5=0,$E$4-12*A30*$E$7,$E$4*(1+$E$5)^(12*A30)-$E$7*((1+$E$5)^(12*A30)-1)/$E$5)) -> 200845.74 | D30: =IF(A30<=$B$8,12*$E$7,0)+($B$10+$B$11+$B$12)*$B$4*(1+$B$16)^(A30-1) -> 26465.706 | E30: =D30/(1+$B$15)^A30 -> 16247.648 | F30: =SUM($E$21:E30) -> 195002.18 | G30: =12*$B$5*(1+$B$17)^(A30-1) -> 23485.917 | H30: =G30/(1+$B$15)^A30 -> 14418.316 | I30: =SUM($H$21:H30) -> 157456.73 | J30: =($B$6+$B$13)*$B$4+F30-(B30*(1-$B$14)-C30)/(1+$B$15)^A30 -> 154640.48 | K30: =I30-J30 -> 2816.2512 | L30: =IF(K30>=0,A30,"") -> 10
A31: 11 | B31: =$B$4*(1+$B$16)^A31 -> 415270.16 | C31: =IF(OR($E$4=0,A31>=$B$8),0,IF($E$5=0,$E$4-12*A31*$E$7,$E$4*(1+$E$5)^(12*A31)-$E$7*((1+$E$5)^(12*A31)-1)/$E$5)) -> 195483.56 | D31: =IF(A31<=$B$8,12*$E$7,0)+($B$10+$B$11+$B$12)*$B$4*(1+$B$16)^(A31-1) -> 26741.666 | E31: =D31/(1+$B$15)^A31 -> 15635.298 | F31: =SUM($E$21:E31) -> 210637.47 | G31: =12*$B$5*(1+$B$17)^(A31-1) -> 24190.495 | H31: =G31/(1+$B$15)^A31 -> 14143.681 | I31: =SUM($H$21:H31) -> 171600.41 | J31: =($B$6+$B$13)*$B$4+F31-(B31*(1-$B$14)-C31)/(1+$B$15)^A31 -> 165700.79 | K31: =I31-J31 -> 5899.6189 | L31: =IF(K31>=0,A31,"") -> 11
A32: 12 | B32: =$B$4*(1+$B$16)^A32 -> 427728.27 | C32: =IF(OR($E$4=0,A32>=$B$8),0,IF($E$5=0,$E$4-12*A32*$E$7,$E$4*(1+$E$5)^(12*A32)-$E$7*((1+$E$5)^(12*A32)-1)/$E$5)) -> 189790.66 | D32: =IF(A32<=$B$8,12*$E$7,0)+($B$10+$B$11+$B$12)*$B$4*(1+$B$16)^(A32-1) -> 27025.904 | E32: =D32/(1+$B$15)^A32 -> 15049.035 | F32: =SUM($E$21:E32) -> 225686.51 | G32: =12*$B$5*(1+$B$17)^(A32-1) -> 24916.21 | H32: =G32/(1+$B$15)^A32 -> 13874.278 | I32: =SUM($H$21:H32) -> 185474.69 | J32: =($B$6+$B$13)*$B$4+F32-(B32*(1-$B$14)-C32)/(1+$B$15)^A32 -> 176484.45 | K32: =I32-J32 -> 8990.2389 | L32: =IF(K32>=0,A32,"") -> 12
... A50: 30 | B50: =$B$4*(1+$B$16)^A50 -> 728178.74 | C50: =IF(OR($E$4=0,A50>=$B$8),0,IF($E$5=0,$E$4-12*A50*$E$7,$E$4*(1+$E$5)^(12*A50)-$E$7*((1+$E$5)^(12*A50)-1)/$E$5)) -> 0 | D50: =IF(A50<=$B$8,12*$E$7,0)+($B$10+$B$11+$B$12)*$B$4*(1+$B$16)^(A50-1) -> 33880.842 | E50: =D50/(1+$B$15)^A50 -> 7839.2628 | F50: =SUM($E$21:E50) -> 419968.1 | G50: =12*$B$5*(1+$B$17)^(A50-1) -> 42418.179 | H50: =G50/(1+$B$15)^A50 -> 9814.6101 | I50: =SUM($H$21:H50) -> 394547.58 | J50: =($B$6+$B$13)*$B$4+F50-(B50*(1-$B$14)-C50)/(1+$B$15)^A50 -> 330593 | K50: =I50-J50 -> 63954.577 | L50: =IF(K50>=0,A50,"") -> 30

Sheet S08
A1: S08: Buying never breaks even (price very high relative to rent)
A2: Hand calculation: C_R(30) = 12,000 x 15.372 (30-year annuity factor at 5%) = 184,469. C_B(30) is at least the upfront 230,000 minus the discounted sale proceeds 940,000 / 1.05^30 = 217,497, plus positive running costs, so C_B > 12,503 + PV(mortgage 57,552 a year) >> C_R for every H <= 30. UC = (0.05 + 0.0235 - 0) x 1,000,000 = 73,500 > 12,000.
A3: Inputs (blue: edit to explore) | D3: Results (Excel formulas)
A4: Price P ($) | B4: 1000000 | D4: Loan L = (1-d)P | E4: =(1-$B$6)*$B$4 -> 800000
A5: Monthly rent R ($) | B5: 1000 | D5: Monthly rate i = r/12 | E5: =$B$7/12 -> 0.005
A6: Down payment d | B6: 0.2 | D6: Number of payments n = 12T | E6: =12*$B$8 -> 360
A7: Mortgage rate r | B7: 0.06 | D7: Monthly payment M | E7: =IF($E$4=0,0,IF($E$5=0,$E$4/$E$6,$E$4*$E$5*(1+$E$5)^$E$6/((1+$E$5)^$E$6-1))) -> 4796.4042 | H7: 4796.4042 | I7: =IF(ABS(E7-H7)<0.01,"PASS","FAIL") -> PASS
A8: Mortgage term T (years) | B8: 30 | G8: Hand calculation | H8: Python engine | I8: Excel vs engine | J8: Excel vs hand
A9: Holding period H (years) | B9: 7 | D9: C_B(H) cost of buying (PV) | E9: =INDEX(J21:J50,$B$9) -> 540625.06 | H9: 540625.06 | I9: =IF(ABS(E9-H9)<0.01,"PASS","FAIL") -> PASS
A10: Property tax tau | B10: 0.01 | D10: C_R(H) cost of renting (PV) | E10: =INDEX(I21:I50,$B$9) -> 69436.481 | H10: 69436.481 | I10: =IF(ABS(E10-H10)<0.01,"PASS","FAIL") -> PASS
A11: Maintenance m | B11: 0.01 | D11: Delta(H) = C_R - C_B | E11: =INDEX(K21:K50,$B$9) -> -471188.58 | H11: -471188.58 | I11: =IF(ABS(E11-H11)<0.01,"PASS","FAIL") -> PASS
A12: Insurance h | B12: 0.0035 | D12: Recommendation at H | E12: =IF(E11>=0,"buy","rent") -> rent | G12: rent | H12: rent | I12: =IF(E12=H12,"PASS","FAIL") -> PASS | J12: =IF(E12=G12,"PASS","FAIL") -> PASS
A13: Buying costs cb | B13: 0.03 | D13: Break-even year (search 1-30) | E13: =IF(COUNT(L21:L50)=0,"never",MIN(L21:L50)) -> never | G13: never | H13: never | I13: =IF(E13=H13,"PASS","FAIL") -> PASS | J13: =IF(E13=G13,"PASS","FAIL") -> PASS
A14: Selling costs cs | B14: 0.06 | D14: User cost UC = (k+tau+m+h-g)P | E14: =($B$15+$B$10+$B$11+$B$12-$B$16)*$B$4 -> 73500 | G14: 73500 | H14: 73500 | I14: =IF(ABS(E14-H14)<0.01,"PASS","FAIL") -> PASS | J14: =IF(ABS(E14-G14)<0.01,"PASS","FAIL") -> PASS
A15: Discount rate k | B15: 0.05 | D15: Annual rent 12R | E15: =12*$B$5 -> 12000 | H15: 12000 | I15: =IF(ABS(E15-H15)<0.01,"PASS","FAIL") -> PASS
A16: Appreciation g | B16: 0 | D16: Loan balance B_H | E16: =INDEX(C21:C50,$B$9) -> 717115.09 | H16: 717115.09 | I16: =IF(ABS(E16-H16)<0.01,"PASS","FAIL") -> PASS
A17: Rent growth q | B17: 0 | G17: Hand and Python values are pasted for the inputs above; if you edit an input, only the Excel column updates.
A19: Year-by-year (selling at the end of year t)
A20: Year t | B20: Home value V_t | C20: Loan balance B_t | D20: Owner cost O_t | E20: PV of O_t | F20: Sum PV O (1..t) | G20: Rent_t | H20: PV of Rent_t | I20: C_R(t) | J20: C_B(t) | K20: Delta(t) = C_R - C_B | L20: Break-even helper
A21: 1 | B21: =$B$4*(1+$B$16)^A21 -> 1000000 | C21: =IF(OR($E$4=0,A21>=$B$8),0,IF($E$5=0,$E$4-12*A21*$E$7,$E$4*(1+$E$5)^(12*A21)-$E$7*((1+$E$5)^(12*A21)-1)/$E$5)) -> 790175.91 | D21: =IF(A21<=$B$8,12*$E$7,0)+($B$10+$B$11+$B$12)*$B$4*(1+$B$16)^(A21-1) -> 81056.85 | E21: =D21/(1+$B$15)^A21 -> 77197 | F21: =SUM($E$21:E21) -> 77197 | G21: =12*$B$5*(1+$B$17)^(A21-1) -> 12000 | H21: =G21/(1+$B$15)^A21 -> 11428.571 | I21: =SUM($H$21:H21) -> 11428.571 | J21: =($B$6+$B$13)*$B$4+F21-(B21*(1-$B$14)-C21)/(1+$B$15)^A21 -> 164507.39 | K21: =I21-J21 -> -153078.82 | L21: =IF(K21>=0,A21,"")
A22: 2 | B22: =$B$4*(1+$B$16)^A22 -> 1000000 | C22: =IF(OR($E$4=0,A22>=$B$8),0,IF($E$5=0,$E$4-12*A22*$E$7,$E$4*(1+$E$5)^(12*A22)-$E$7*((1+$E$5)^(12*A22)-1)/$E$5)) -> 779745.88 | D22: =IF(A22<=$B$8,12*$E$7,0)+($B$10+$B$11+$B$12)*$B$4*(1+$B$16)^(A22-1) -> 81056.85 | E22: =D22/(1+$B$15)^A22 -> 73520.953 | F22: =SUM($E$21:E22) -> 150717.95 | G22: =12*$B$5*(1+$B$17)^(A22-1) -> 12000 | H22: =G22/(1+$B$15)^A22 -> 10884.354 | I22: =SUM($H$21:H22) -> 22312.925 | J22: =($B$6+$B$13)*$B$4+F22-(B22*(1-$B$14)-C22)/(1+$B$15)^A22 -> 235362.75 | K22: =I22-J22 -> -213049.82 | L22: =IF(K22>=0,A22,"")
A23: 3 | B23: =$B$4*(1+$B$16)^A23 -> 1000000 | C23: =IF(OR($E$4=0,A23>=$B$8),0,IF($E$5=0,$E$4-12*A23*$E$7,$E$4*(1+$E$5)^(12*A23)-$E$7*((1+$E$5)^(12*A23)-1)/$E$5)) -> 768672.56 | D23: =IF(A23<=$B$8,12*$E$7,0)+($B$10+$B$11+$B$12)*$B$4*(1+$B$16)^(A23-1) -> 81056.85 | E23: =D23/(1+$B$15)^A23 -> 70019.955 | F23: =SUM($E$21:E23) -> 220737.91 | G23: =12*$B$5*(1+$B$17)^(A23-1) -> 12000 | H23: =G23/(1+$B$15)^A23 -> 10366.051 | I23: =SUM($H$21:H23) -> 32678.976 | J23: =($B$6+$B$13)*$B$4+F23-(B23*(1-$B$14)-C23)/(1+$B$15)^A23 -> 302738.82 | K23: =I23-J23 -> -270059.85 | L23: =IF(K23>=0,A23,"")
A24: 4 | B24: =$B$4*(1+$B$16)^A24 -> 1000000 | C24: =IF(OR($E$4=0,A24>=$B$8),0,IF($E$5=0,$E$4-12*A24*$E$7,$E$4*(1+$E$5)^(12*A24)-$E$7*((1+$E$5)^(12*A24)-1)/$E$5)) -> 756916.26 | D24: =IF(A24<=$B$8,12*$E$7,0)+($B$10+$B$11+$B$12)*$B$4*(1+$B$16)^(A24-1) -> 81056.85 | E24: =D24/(1+$B$15)^A24 -> 66685.671 | F24: =SUM($E$21:E24) -> 287423.58 | G24: =12*$B$5*(1+$B$17)^(A24-1) -> 12000 | H24: =G24/(1+$B$15)^A24 -> 9872.4297 | I24: =SUM($H$21:H24) -> 42551.406 | J24: =($B$6+$B$13)*$B$4+F24-(B24*(1-$B$14)-C24)/(1+$B$15)^A24 -> 366800.13 | K24: =I24-J24 -> -324248.73 | L24: =IF(K24>=0,A24,"")
A25: 5 | B25: =$B$4*(1+$B$16)^A25 -> 1000000 | C25: =IF(OR($E$4=0,A25>=$B$8),0,IF($E$5=0,$E$4-12*A25*$E$7,$E$4*(1+$E$5)^(12*A25)-$E$7*((1+$E$5)^(12*A25)-1)/$E$5)) -> 744434.85 | D25: =IF(A25<=$B$8,12*$E$7,0)+($B$10+$B$11+$B$12)*$B$4*(1+$B$16)^(A25-1) -> 81056.85 | E25: =D25/(1+$B$15)^A25 -> 63510.163 | F25: =SUM($E$21:E25) -> 350933.74 | G25: =12*$B$5*(1+$B$17)^(A25-1) -> 12000 | H25: =G25/(1+$B$15)^A25 -> 9402.314 | I25: =SUM($H$21:H25) -> 51953.72 | J25: =($B$6+$B$13)*$B$4+F25-(B25*(1-$B$14)-C25)/(1+$B$15)^A25 -> 427703.33 | K25: =I25-J25 -> -375749.61 | L25: =IF(K25>=0,A25,"")
A26: 6 | B26: =$B$4*(1+$B$16)^A26 -> 1000000 | C26: =IF(OR($E$4=0,A26>=$B$8),0,IF($E$5=0,$E$4-12*A26*$E$7,$E$4*(1+$E$5)^(12*A26)-$E$7*((1+$E$5)^(12*A26)-1)/$E$5)) -> 731183.62 | D26: =IF(A26<=$B$8,12*$E$7,0)+($B$10+$B$11+$B$12)*$B$4*(1+$B$16)^(A26-1) -> 81056.85 | E26: =D26/(1+$B$15)^A26 -> 60485.87 | F26: =SUM($E$21:E26) -> 411419.61 | G26: =12*$B$5*(1+$B$17)^(A26-1) -> 12000 | H26: =G26/(1+$B$15)^A26 -> 8954.5848 | I26: =SUM($H$21:H26) -> 60908.305 | J26: =($B$6+$B$13)*$B$4+F26-(B26*(1-$B$14)-C26)/(1+$B$15)^A26 -> 485597.62 | K26: =I26-J26 -> -424689.31 | L26: =IF(K26>=0,A26,"")
A27: 7 | B27: =$B$4*(1+$B$16)^A27 -> 1000000 | C27: =IF(OR($E$4=0,A27>=$B$8),0,IF($E$5=0,$E$4-12*A27*$E$7,$E$4*(1+$E$5)^(12*A27)-$E$7*((1+$E$5)^(12*A27)-1)/$E$5)) -> 717115.09 | D27: =IF(A27<=$B$8,12*$E$7,0)+($B$10+$B$11+$B$12)*$B$4*(1+$B$16)^(A27-1) -> 81056.85 | E27: =D27/(1+$B$15)^A27 -> 57605.59 | F27: =SUM($E$21:E27) -> 469025.2 | G27: =12*$B$5*(1+$B$17)^(A27-1) -> 12000 | H27: =G27/(1+$B$15)^A27 -> 8528.176 | I27: =SUM($H$21:H27) -> 69436.481 | J27: =($B$6+$B$13)*$B$4+F27-(B27*(1-$B$14)-C27)/(1+$B$15)^A27 -> 540625.06 | K27: =I27-J27 -> -471188.58 | L27: =IF(K27>=0,A27,"")
A28: 8 | B28: =$B$4*(1+$B$16)^A28 -> 1000000 | C28: =IF(OR($E$4=0,A28>=$B$8),0,IF($E$5=0,$E$4-12*A28*$E$7,$E$4*(1+$E$5)^(12*A28)-$E$7*((1+$E$5)^(12*A28)-1)/$E$5)) -> 702178.83 | D28: =IF(A28<=$B$8,12*$E$7,0)+($B$10+$B$11+$B$12)*$B$4*(1+$B$16)^(A28-1) -> 81056.85 | E28: =D28/(1+$B$15)^A28 -> 54862.467 | F28: =SUM($E$21:E28) -> 523887.67 | G28: =12*$B$5*(1+$B$17)^(A28-1) -> 12000 | H28: =G28/(1+$B$15)^A28 -> 8122.0723 | I28: =SUM($H$21:H28) -> 77558.553 | J28: =($B$6+$B$13)*$B$4+F28-(B28*(1-$B$14)-C28)/(1+$B$15)^A28 -> 592920.94 | K28: =I28-J28 -> -515362.39 | L28: =IF(K28>=0,A28,"")
A29: 9 | B29: =$B$4*(1+$B$16)^A29 -> 1000000 | C29: =IF(OR($E$4=0,A29>=$B$8),0,IF($E$5=0,$E$4-12*A29*$E$7,$E$4*(1+$E$5)^(12*A29)-$E$7*((1+$E$5)^(12*A29)-1)/$E$5)) -> 686321.34 | D29: =IF(A29<=$B$8,12*$E$7,0)+($B$10+$B$11+$B$12)*$B$4*(1+$B$16)^(A29-1) -> 81056.85 | E29: =D29/(1+$B$15)^A29 -> 52249.968 | F29: =SUM($E$21:E29) -> 576137.64 | G29: =12*$B$5*(1+$B$17)^(A29-1) -> 12000 | H29: =G29/(1+$B$15)^A29 -> 7735.307 | I29: =SUM($H$21:H29) -> 85293.86 | J29: =($B$6+$B$13)*$B$4+F29-(B29*(1-$B$14)-C29)/(1+$B$15)^A29 -> 642614.11 | K29: =I29-J29 -> -557320.25 | L29: =IF(K29>=0,A29,"")
A30: 10 | B30: =$B$4*(1+$B$16)^A30 -> 1000000 | C30: =IF(OR($E$4=0,A30>=$B$8),0,IF($E$5=0,$E$4-12*A30*$E$7,$E$4*(1+$E$5)^(12*A30)-$E$7*((1+$E$5)^(12*A30)-1)/$E$5)) -> 669485.8 | D30: =IF(A30<=$B$8,12*$E$7,0)+($B$10+$B$11+$B$12)*$B$4*(1+$B$16)^(A30-1) -> 81056.85 | E30: =D30/(1+$B$15)^A30 -> 49761.875 | F30: =SUM($E$21:E30) -> 625899.51 | G30: =12*$B$5*(1+$B$17)^(A30-1) -> 12000 | H30: =G30/(1+$B$15)^A30 -> 7366.959 | I30: =SUM($H$21:H30) -> 92660.819 | J30: =($B$6+$B$13)*$B$4+F30-(B30*(1-$B$14)-C30)/(1+$B$15)^A30 -> 689827.26 | K30: =I30-J30 -> -597166.44 | L30: =IF(K30>=0,A30,"")
A31: 11 | B31: =$B$4*(1+$B$16)^A31 -> 1000000 | C31: =IF(OR($E$4=0,A31>=$B$8),0,IF($E$5=0,$E$4-12*A31*$E$7,$E$4*(1+$E$5)^(12*A31)-$E$7*((1+$E$5)^(12*A31)-1)/$E$5)) -> 651611.88 | D31: =IF(A31<=$B$8,12*$E$7,0)+($B$10+$B$11+$B$12)*$B$4*(1+$B$16)^(A31-1) -> 81056.85 | E31: =D31/(1+$B$15)^A31 -> 47392.262 | F31: =SUM($E$21:E31) -> 673291.77 | G31: =12*$B$5*(1+$B$17)^(A31-1) -> 12000 | H31: =G31/(1+$B$15)^A31 -> 7016.1515 | I31: =SUM($H$21:H31) -> 99676.971 | J31: =($B$6+$B$13)*$B$4+F31-(B31*(1-$B$14)-C31)/(1+$B$15)^A31 -> 734677.21 | K31: =I31-J31 -> -635000.24 | L31: =IF(K31>=0,A31,"")
A32: 12 | B32: =$B$4*(1+$B$16)^A32 -> 1000000 | C32: =IF(OR($E$4=0,A32>=$B$8),0,IF($E$5=0,$E$4-12*A32*$E$7,$E$4*(1+$E$5)^(12*A32)-$E$7*((1+$E$5)^(12*A32)-1)/$E$5)) -> 632635.53 | D32: =IF(A32<=$B$8,12*$E$7,0)+($B$10+$B$11+$B$12)*$B$4*(1+$B$16)^(A32-1) -> 81056.85 | E32: =D32/(1+$B$15)^A32 -> 45135.487 | F32: =SUM($E$21:E32) -> 718427.26 | G32: =12*$B$5*(1+$B$17)^(A32-1) -> 12000 | H32: =G32/(1+$B$15)^A32 -> 6682.049 | I32: =SUM($H$21:H32) -> 106359.02 | J32: =($B$6+$B$13)*$B$4+F32-(B32*(1-$B$14)-C32)/(1+$B$15)^A32 -> 777275.22 | K32: =I32-J32 -> -670916.2 | L32: =IF(K32>=0,A32,"")
... A50: 30 | B50: =$B$4*(1+$B$16)^A50 -> 1000000 | C50: =IF(OR($E$4=0,A50>=$B$8),0,IF($E$5=0,$E$4-12*A50*$E$7,$E$4*(1+$E$5)^(12*A50)-$E$7*((1+$E$5)^(12*A50)-1)/$E$5)) -> 0 | D50: =IF(A50<=$B$8,12*$E$7,0)+($B$10+$B$11+$B$12)*$B$4*(1+$B$16)^(A50-1) -> 81056.85 | E50: =D50/(1+$B$15)^A50 -> 18754.727 | F50: =SUM($E$21:E50) -> 1246042.5 | G50: =12*$B$5*(1+$B$17)^(A50-1) -> 12000 | H50: =G50/(1+$B$15)^A50 -> 2776.5294 | I50: =SUM($H$21:H50) -> 184469.41 | J50: =($B$6+$B$13)*$B$4+F50-(B50*(1-$B$14)-C50)/(1+$B$15)^A50 -> 1258547.7 | K50: =I50-J50 -> -1074078.2 | L50: =IF(K50>=0,A50,"")

Sheet S09
A1: S09: User cost check with default assumptions
A2: Hand calculation: UC = (0.05 + 0.01 + 0.01 + 0.0035 - 0.03) x 300,000 = 0.0435 x 300,000 = 13,050 < 12 x 1,200 = 14,400, so the user-cost rule says buy.
A3: Inputs (blue: edit to explore) | D3: Results (Excel formulas)
A4: Price P ($) | B4: 300000 | D4: Loan L = (1-d)P | E4: =(1-$B$6)*$B$4 -> 240000
A5: Monthly rent R ($) | B5: 1200 | D5: Monthly rate i = r/12 | E5: =$B$7/12 -> 0.005
A6: Down payment d | B6: 0.2 | D6: Number of payments n = 12T | E6: =12*$B$8 -> 360
A7: Mortgage rate r | B7: 0.06 | D7: Monthly payment M | E7: =IF($E$4=0,0,IF($E$5=0,$E$4/$E$6,$E$4*$E$5*(1+$E$5)^$E$6/((1+$E$5)^$E$6-1))) -> 1438.9213 | H7: 1438.9213 | I7: =IF(ABS(E7-H7)<0.01,"PASS","FAIL") -> PASS
A8: Mortgage term T (years) | B8: 30 | G8: Hand calculation | H8: Python engine | I8: Excel vs engine | J8: Excel vs hand
A9: Holding period H (years) | B9: 7 | D9: C_B(H) cost of buying (PV) | E9: =INDEX(J21:J50,$B$9) -> 119722.01 | H9: 119722.01 | I9: =IF(ABS(E9-H9)<0.01,"PASS","FAIL") -> PASS
A10: Property tax tau | B10: 0.01 | D10: C_R(H) cost of renting (PV) | E10: =INDEX(I21:I50,$B$9) -> 90685.156 | H10: 90685.156 | I10: =IF(ABS(E10-H10)<0.01,"PASS","FAIL") -> PASS
A11: Maintenance m | B11: 0.01 | D11: Delta(H) = C_R - C_B | E11: =INDEX(K21:K50,$B$9) -> -29036.857 | H11: -29036.857 | I11: =IF(ABS(E11-H11)<0.01,"PASS","FAIL") -> PASS
A12: Insurance h | B12: 0.0035 | D12: Recommendation at H | E12: =IF(E11>=0,"buy","rent") -> rent | H12: rent | I12: =IF(E12=H12,"PASS","FAIL") -> PASS
A13: Buying costs cb | B13: 0.03 | D13: Break-even year (search 1-30) | E13: =IF(COUNT(L21:L50)=0,"never",MIN(L21:L50)) -> never | H13: never | I13: =IF(E13=H13,"PASS","FAIL") -> PASS
A14: Selling costs cs | B14: 0.06 | D14: User cost UC = (k+tau+m+h-g)P | E14: =($B$15+$B$10+$B$11+$B$12-$B$16)*$B$4 -> 13050 | G14: 13050 | H14: 13050 | I14: =IF(ABS(E14-H14)<0.01,"PASS","FAIL") -> PASS | J14: =IF(ABS(E14-G14)<0.01,"PASS","FAIL") -> PASS
A15: Discount rate k | B15: 0.05 | D15: Annual rent 12R | E15: =12*$B$5 -> 14400 | H15: 14400 | I15: =IF(ABS(E15-H15)<0.01,"PASS","FAIL") -> PASS
A16: Appreciation g | B16: 0.03 | D16: Loan balance B_H | E16: =INDEX(C21:C50,$B$9) -> 215134.53 | H16: 215134.53 | I16: =IF(ABS(E16-H16)<0.01,"PASS","FAIL") -> PASS
A17: Rent growth q | B17: 0.03 | G17: Hand and Python values are pasted for the inputs above; if you edit an input, only the Excel column updates.
A19: Year-by-year (selling at the end of year t)
A20: Year t | B20: Home value V_t | C20: Loan balance B_t | D20: Owner cost O_t | E20: PV of O_t | F20: Sum PV O (1..t) | G20: Rent_t | H20: PV of Rent_t | I20: C_R(t) | J20: C_B(t) | K20: Delta(t) = C_R - C_B | L20: Break-even helper
A21: 1 | B21: =$B$4*(1+$B$16)^A21 -> 309000 | C21: =IF(OR($E$4=0,A21>=$B$8),0,IF($E$5=0,$E$4-12*A21*$E$7,$E$4*(1+$E$5)^(12*A21)-$E$7*((1+$E$5)^(12*A21)-1)/$E$5)) -> 237052.77 | D21: =IF(A21<=$B$8,12*$E$7,0)+($B$10+$B$11+$B$12)*$B$4*(1+$B$16)^(A21-1) -> 24317.055 | E21: =D21/(1+$B$15)^A21 -> 23159.1 | F21: =SUM($E$21:E21) -> 23159.1 | G21: =12*$B$5*(1+$B$17)^(A21-1) -> 14400 | H21: =G21/(1+$B$15)^A21 -> 13714.286 | I21: =SUM($H$21:H21) -> 13714.286 | J21: =($B$6+$B$13)*$B$4+F21-(B21*(1-$B$14)-C21)/(1+$B$15)^A21 -> 41295.073 | K21: =I21-J21 -> -27580.788 | L21: =IF(K21>=0,A21,"")
A22: 2 | B22: =$B$4*(1+$B$16)^A22 -> 318270 | C22: =IF(OR($E$4=0,A22>=$B$8),0,IF($E$5=0,$E$4-12*A22*$E$7,$E$4*(1+$E$5)^(12*A22)-$E$7*((1+$E$5)^(12*A22)-1)/$E$5)) -> 233923.77 | D22: =IF(A22<=$B$8,12*$E$7,0)+($B$10+$B$11+$B$12)*$B$4*(1+$B$16)^(A22-1) -> 24528.555 | E22: =D22/(1+$B$15)^A22 -> 22248.123 | F22: =SUM($E$21:E22) -> 45407.223 | G22: =12*$B$5*(1+$B$17)^(A22-1) -> 14832 | H22: =G22/(1+$B$15)^A22 -> 13453.061 | I22: =SUM($H$21:H22) -> 27167.347 | J22: =($B$6+$B$13)*$B$4+F22-(B22*(1-$B$14)-C22)/(1+$B$15)^A22 -> 55223.518 | K22: =I22-J22 -> -28056.171 | L22: =IF(K22>=0,A22,"")
A23: 3 | B23: =$B$4*(1+$B$16)^A23 -> 327818.1 | C23: =IF(OR($E$4=0,A23>=$B$8),0,IF($E$5=0,$E$4-12*A23*$E$7,$E$4*(1+$E$5)^(12*A23)-$E$7*((1+$E$5)^(12*A23)-1)/$E$5)) -> 230601.77 | D23: =IF(A23<=$B$8,12*$E$7,0)+($B$10+$B$11+$B$12)*$B$4*(1+$B$16)^(A23-1) -> 24746.4 | E23: =D23/(1+$B$15)^A23 -> 21376.871 | F23: =SUM($E$21:E23) -> 66784.094 | G23: =12*$B$5*(1+$B$17)^(A23-1) -> 15276.96 | H23: =G23/(1+$B$15)^A23 -> 13196.812 | I23: =SUM($H$21:H23) -> 40364.159 | J23: =($B$6+$B$13)*$B$4+F23-(B23*(1-$B$14)-C23)/(1+$B$15)^A23 -> 68795.867 | K23: =I23-J23 -> -28431.708 | L23: =IF(K23>=0,A23,"")
A24: 4 | B24: =$B$4*(1+$B$16)^A24 -> 337652.64 | C24: =IF(OR($E$4=0,A24>=$B$8),0,IF($E$5=0,$E$4-12*A24*$E$7,$E$4*(1+$E$5)^(12*A24)-$E$7*((1+$E$5)^(12*A24)-1)/$E$5)) -> 227074.88 | D24: =IF(A24<=$B$8,12*$E$7,0)+($B$10+$B$11+$B$12)*$B$4*(1+$B$16)^(A24-1) -> 24970.78 | E24: =D24/(1+$B$15)^A24 -> 20543.523 | F24: =SUM($E$21:E24) -> 87327.616 | G24: =12*$B$5*(1+$B$17)^(A24-1) -> 15735.269 | H24: =G24/(1+$B$15)^A24 -> 12945.445 | I24: =SUM($H$21:H24) -> 53309.604 | J24: =($B$6+$B$13)*$B$4+F24-(B24*(1-$B$14)-C24)/(1+$B$15)^A24 -> 82022.275 | K24: =I24-J24 -> -28712.671 | L24: =IF(K24>=0,A24,"")
A25: 5 | B25: =$B$4*(1+$B$16)^A25 -> 347782.22 | C25: =IF(OR($E$4=0,A25>=$B$8),0,IF($E$5=0,$E$4-12*A25*$E$7,$E$4*(1+$E$5)^(12*A25)-$E$7*((1+$E$5)^(12*A25)-1)/$E$5)) -> 223330.46 | D25: =IF(A25<=$B$8,12*$E$7,0)+($B$10+$B$11+$B$12)*$B$4*(1+$B$16)^(A25-1) -> 25201.892 | E25: =D25/(1+$B$15)^A25 -> 19746.342 | F25: =SUM($E$21:E25) -> 107073.96 | G25: =12*$B$5*(1+$B$17)^(A25-1) -> 16207.327 | H25: =G25/(1+$B$15)^A25 -> 12698.865 | I25: =SUM($H$21:H25) -> 66008.469 | J25: =($B$6+$B$13)*$B$4+F25-(B25*(1-$B$14)-C25)/(1+$B$15)^A25 -> 94912.532 | K25: =I25-J25 -> -28904.063 | L25: =IF(K25>=0,A25,"")
A26: 6 | B26: =$B$4*(1+$B$16)^A26 -> 358215.69 | C26: =IF(OR($E$4=0,A26>=$B$8),0,IF($E$5=0,$E$4-12*A26*$E$7,$E$4*(1+$E$5)^(12*A26)-$E$7*((1+$E$5)^(12*A26)-1)/$E$5)) -> 219355.09 | D26: =IF(A26<=$B$8,12*$E$7,0)+($B$10+$B$11+$B$12)*$B$4*(1+$B$16)^(A26-1) -> 25439.937 | E26: =D26/(1+$B$15)^A26 -> 18983.673 | F26: =SUM($E$21:E26) -> 126057.63 | G26: =12*$B$5*(1+$B$17)^(A26-1) -> 16693.547 | H26: =G26/(1+$B$15)^A26 -> 12456.982 | I26: =SUM($H$21:H26) -> 78465.45 | J26: =($B$6+$B$13)*$B$4+F26-(B26*(1-$B$14)-C26)/(1+$B$15)^A26 -> 107476.08 | K26: =I26-J26 -> -29010.626 | L26: =IF(K26>=0,A26,"")
A27: 7 | B27: =$B$4*(1+$B$16)^A27 -> 368962.16 | C27: =IF(OR($E$4=0,A27>=$B$8),0,IF($E$5=0,$E$4-12*A27*$E$7,$E$4*(1+$E$5)^(12*A27)-$E$7*((1+$E$5)^(12*A27)-1)/$E$5)) -> 215134.53 | D27: =IF(A27<=$B$8,12*$E$7,0)+($B$10+$B$11+$B$12)*$B$4*(1+$B$16)^(A27-1) -> 25685.124 | E27: =D27/(1+$B$15)^A27 -> 18253.938 | F27: =SUM($E$21:E27) -> 144311.57 | G27: =12*$B$5*(1+$B$17)^(A27-1) -> 17194.353 | H27: =G27/(1+$B$15)^A27 -> 12219.706 | I27: =SUM($H$21:H27) -> 90685.156 | J27: =($B$6+$B$13)*$B$4+F27-(B27*(1-$B$14)-C27)/(1+$B$15)^A27 -> 119722.01 | K27: =I27-J27 -> -29036.857 | L27: =IF(K27>=0,A27,"")
A28: 8 | B28: =$B$4*(1+$B$16)^A28 -> 380031.02 | C28: =IF(OR($E$4=0,A28>=$B$8),0,IF($E$5=0,$E$4-12*A28*$E$7,$E$4*(1+$E$5)^(12*A28)-$E$7*((1+$E$5)^(12*A28)-1)/$E$5)) -> 210653.65 | D28: =IF(A28<=$B$8,12*$E$7,0)+($B$10+$B$11+$B$12)*$B$4*(1+$B$16)^(A28-1) -> 25937.666 | E28: =D28/(1+$B$15)^A28 -> 17555.633 | F28: =SUM($E$21:E28) -> 161867.2 | G28: =12*$B$5*(1+$B$17)^(A28-1) -> 17710.184 | H28: =G28/(1+$B$15)^A28 -> 11986.949 | I28: =SUM($H$21:H28) -> 102672.11 | J28: =($B$6+$B$13)*$B$4+F28-(B28*(1-$B$14)-C28)/(1+$B$15)^A28 -> 131659.13 | K28: =I28-J28 -> -28987.021 | L28: =IF(K28>=0,A28,"")
A29: 9 | B29: =$B$4*(1+$B$16)^A29 -> 391431.96 | C29: =IF(OR($E$4=0,A29>=$B$8),0,IF($E$5=0,$E$4-12*A29*$E$7,$E$4*(1+$E$5)^(12*A29)-$E$7*((1+$E$5)^(12*A29)-1)/$E$5)) -> 205896.4 | D29: =IF(A29<=$B$8,12*$E$7,0)+($B$10+$B$11+$B$12)*$B$4*(1+$B$16)^(A29-1) -> 26197.784 | E29: =D29/(1+$B$15)^A29 -> 16887.325 | F29: =SUM($E$21:E29) -> 178754.53 | G29: =12*$B$5*(1+$B$17)^(A29-1) -> 18241.489 | H29: =G29/(1+$B$15)^A29 -> 11758.627 | I29: =SUM($H$21:H29) -> 114430.73 | J29: =($B$6+$B$13)*$B$4+F29-(B29*(1-$B$14)-C29)/(1+$B$15)^A29 -> 143295.89 | K29: =I29-J29 -> -28865.157 | L29: =IF(K29>=0,A29,"")
A30: 10 | B30: =$B$4*(1+$B$16)^A30 -> 403174.91 | C30: =IF(OR($E$4=0,A30>=$B$8),0,IF($E$5=0,$E$4-12*A30*$E$7,$E$4*(1+$E$5)^(12*A30)-$E$7*((1+$E$5)^(12*A30)-1)/$E$5)) -> 200845.74 | D30: =IF(A30<=$B$8,12*$E$7,0)+($B$10+$B$11+$B$12)*$B$4*(1+$B$16)^(A30-1) -> 26465.706 | E30: =D30/(1+$B$15)^A30 -> 16247.648 | F30: =SUM($E$21:E30) -> 195002.18 | G30: =12*$B$5*(1+$B$17)^(A30-1) -> 18788.734 | H30: =G30/(1+$B$15)^A30 -> 11534.653 | I30: =SUM($H$21:H30) -> 125965.38 | J30: =($B$6+$B$13)*$B$4+F30-(B30*(1-$B$14)-C30)/(1+$B$15)^A30 -> 154640.48 | K30: =I30-J30 -> -28675.095 | L30: =IF(K30>=0,A30,"")
A31: 11 | B31: =$B$4*(1+$B$16)^A31 -> 415270.16 | C31: =IF(OR($E$4=0,A31>=$B$8),0,IF($E$5=0,$E$4-12*A31*$E$7,$E$4*(1+$E$5)^(12*A31)-$E$7*((1+$E$5)^(12*A31)-1)/$E$5)) -> 195483.56 | D31: =IF(A31<=$B$8,12*$E$7,0)+($B$10+$B$11+$B$12)*$B$4*(1+$B$16)^(A31-1) -> 26741.666 | E31: =D31/(1+$B$15)^A31 -> 15635.298 | F31: =SUM($E$21:E31) -> 210637.47 | G31: =12*$B$5*(1+$B$17)^(A31-1) -> 19352.396 | H31: =G31/(1+$B$15)^A31 -> 11314.945 | I31: =SUM($H$21:H31) -> 137280.33 | J31: =($B$6+$B$13)*$B$4+F31-(B31*(1-$B$14)-C31)/(1+$B$15)^A31 -> 165700.79 | K31: =I31-J31 -> -28420.464 | L31: =IF(K31>=0,A31,"")
A32: 12 | B32: =$B$4*(1+$B$16)^A32 -> 427728.27 | C32: =IF(OR($E$4=0,A32>=$B$8),0,IF($E$5=0,$E$4-12*A32*$E$7,$E$4*(1+$E$5)^(12*A32)-$E$7*((1+$E$5)^(12*A32)-1)/$E$5)) -> 189790.66 | D32: =IF(A32<=$B$8,12*$E$7,0)+($B$10+$B$11+$B$12)*$B$4*(1+$B$16)^(A32-1) -> 27025.904 | E32: =D32/(1+$B$15)^A32 -> 15049.035 | F32: =SUM($E$21:E32) -> 225686.51 | G32: =12*$B$5*(1+$B$17)^(A32-1) -> 19932.968 | H32: =G32/(1+$B$15)^A32 -> 11099.422 | I32: =SUM($H$21:H32) -> 148379.75 | J32: =($B$6+$B$13)*$B$4+F32-(B32*(1-$B$14)-C32)/(1+$B$15)^A32 -> 176484.45 | K32: =I32-J32 -> -28104.699 | L32: =IF(K32>=0,A32,"")
... A50: 30 | B50: =$B$4*(1+$B$16)^A50 -> 728178.74 | C50: =IF(OR($E$4=0,A50>=$B$8),0,IF($E$5=0,$E$4-12*A50*$E$7,$E$4*(1+$E$5)^(12*A50)-$E$7*((1+$E$5)^(12*A50)-1)/$E$5)) -> 0 | D50: =IF(A50<=$B$8,12*$E$7,0)+($B$10+$B$11+$B$12)*$B$4*(1+$B$16)^(A50-1) -> 33880.842 | E50: =D50/(1+$B$15)^A50 -> 7839.2628 | F50: =SUM($E$21:E50) -> 419968.1 | G50: =12*$B$5*(1+$B$17)^(A50-1) -> 33934.543 | H50: =G50/(1+$B$15)^A50 -> 7851.688 | I50: =SUM($H$21:H50) -> 315638.07 | J50: =($B$6+$B$13)*$B$4+F50-(B50*(1-$B$14)-C50)/(1+$B$15)^A50 -> 330593 | K50: =I50-J50 -> -14954.939 | L50: =IF(K50>=0,A50,"")

Sheet S10
A1: S10: Negative appreciation
A2: Hand calculation: V_2 = 200,000 x 0.95^2 = 180,500; C_B(2) = 200,000 - 180,500 = 19,500. C_R(2) = 24,000. Year 1: C_B = 10,000 < C_R = 12,000. UC = (0 - (-0.05)) x 200,000 = 10,000.
A3: Inputs (blue: edit to explore) | D3: Results (Excel formulas)
A4: Price P ($) | B4: 200000 | D4: Loan L = (1-d)P | E4: =(1-$B$6)*$B$4 -> 0
A5: Monthly rent R ($) | B5: 1000 | D5: Monthly rate i = r/12 | E5: =$B$7/12 -> 0
A6: Down payment d | B6: 1 | D6: Number of payments n = 12T | E6: =12*$B$8 -> 360
A7: Mortgage rate r | B7: 0 | D7: Monthly payment M | E7: =IF($E$4=0,0,IF($E$5=0,$E$4/$E$6,$E$4*$E$5*(1+$E$5)^$E$6/((1+$E$5)^$E$6-1))) -> 0 | H7: 0 | I7: =IF(ABS(E7-H7)<0.01,"PASS","FAIL") -> PASS
A8: Mortgage term T (years) | B8: 30 | G8: Hand calculation | H8: Python engine | I8: Excel vs engine | J8: Excel vs hand
A9: Holding period H (years) | B9: 2 | D9: C_B(H) cost of buying (PV) | E9: =INDEX(J21:J50,$B$9) -> 19500 | G9: 19500 | H9: 19500 | I9: =IF(ABS(E9-H9)<0.01,"PASS","FAIL") -> PASS | J9: =IF(ABS(E9-G9)<0.01,"PASS","FAIL") -> PASS
A10: Property tax tau | B10: 0 | D10: C_R(H) cost of renting (PV) | E10: =INDEX(I21:I50,$B$9) -> 24000 | G10: 24000 | H10: 24000 | I10: =IF(ABS(E10-H10)<0.01,"PASS","FAIL") -> PASS | J10: =IF(ABS(E10-G10)<0.01,"PASS","FAIL") -> PASS
A11: Maintenance m | B11: 0 | D11: Delta(H) = C_R - C_B | E11: =INDEX(K21:K50,$B$9) -> 4500 | G11: 4500 | H11: 4500 | I11: =IF(ABS(E11-H11)<0.01,"PASS","FAIL") -> PASS | J11: =IF(ABS(E11-G11)<0.01,"PASS","FAIL") -> PASS
A12: Insurance h | B12: 0 | D12: Recommendation at H | E12: =IF(E11>=0,"buy","rent") -> buy | G12: buy | H12: buy | I12: =IF(E12=H12,"PASS","FAIL") -> PASS | J12: =IF(E12=G12,"PASS","FAIL") -> PASS
A13: Buying costs cb | B13: 0 | D13: Break-even year (search 1-30) | E13: =IF(COUNT(L21:L50)=0,"never",MIN(L21:L50)) -> 1 | G13: 1 | H13: 1 | I13: =IF(ABS(E13-H13)<0.01,"PASS","FAIL") -> PASS | J13: =IF(ABS(E13-G13)<0.01,"PASS","FAIL") -> PASS
A14: Selling costs cs | B14: 0 | D14: User cost UC = (k+tau+m+h-g)P | E14: =($B$15+$B$10+$B$11+$B$12-$B$16)*$B$4 -> 10000 | G14: 10000 | H14: 10000 | I14: =IF(ABS(E14-H14)<0.01,"PASS","FAIL") -> PASS | J14: =IF(ABS(E14-G14)<0.01,"PASS","FAIL") -> PASS
A15: Discount rate k | B15: 0 | D15: Annual rent 12R | E15: =12*$B$5 -> 12000 | H15: 12000 | I15: =IF(ABS(E15-H15)<0.01,"PASS","FAIL") -> PASS
A16: Appreciation g | B16: -0.05 | D16: Loan balance B_H | E16: =INDEX(C21:C50,$B$9) -> 0 | H16: 0 | I16: =IF(ABS(E16-H16)<0.01,"PASS","FAIL") -> PASS
A17: Rent growth q | B17: 0 | G17: Hand and Python values are pasted for the inputs above; if you edit an input, only the Excel column updates.
A19: Year-by-year (selling at the end of year t)
A20: Year t | B20: Home value V_t | C20: Loan balance B_t | D20: Owner cost O_t | E20: PV of O_t | F20: Sum PV O (1..t) | G20: Rent_t | H20: PV of Rent_t | I20: C_R(t) | J20: C_B(t) | K20: Delta(t) = C_R - C_B | L20: Break-even helper
A21: 1 | B21: =$B$4*(1+$B$16)^A21 -> 190000 | C21: =IF(OR($E$4=0,A21>=$B$8),0,IF($E$5=0,$E$4-12*A21*$E$7,$E$4*(1+$E$5)^(12*A21)-$E$7*((1+$E$5)^(12*A21)-1)/$E$5)) -> 0 | D21: =IF(A21<=$B$8,12*$E$7,0)+($B$10+$B$11+$B$12)*$B$4*(1+$B$16)^(A21-1) -> 0 | E21: =D21/(1+$B$15)^A21 -> 0 | F21: =SUM($E$21:E21) -> 0 | G21: =12*$B$5*(1+$B$17)^(A21-1) -> 12000 | H21: =G21/(1+$B$15)^A21 -> 12000 | I21: =SUM($H$21:H21) -> 12000 | J21: =($B$6+$B$13)*$B$4+F21-(B21*(1-$B$14)-C21)/(1+$B$15)^A21 -> 10000 | K21: =I21-J21 -> 2000 | L21: =IF(K21>=0,A21,"") -> 1
A22: 2 | B22: =$B$4*(1+$B$16)^A22 -> 180500 | C22: =IF(OR($E$4=0,A22>=$B$8),0,IF($E$5=0,$E$4-12*A22*$E$7,$E$4*(1+$E$5)^(12*A22)-$E$7*((1+$E$5)^(12*A22)-1)/$E$5)) -> 0 | D22: =IF(A22<=$B$8,12*$E$7,0)+($B$10+$B$11+$B$12)*$B$4*(1+$B$16)^(A22-1) -> 0 | E22: =D22/(1+$B$15)^A22 -> 0 | F22: =SUM($E$21:E22) -> 0 | G22: =12*$B$5*(1+$B$17)^(A22-1) -> 12000 | H22: =G22/(1+$B$15)^A22 -> 12000 | I22: =SUM($H$21:H22) -> 24000 | J22: =($B$6+$B$13)*$B$4+F22-(B22*(1-$B$14)-C22)/(1+$B$15)^A22 -> 19500 | K22: =I22-J22 -> 4500 | L22: =IF(K22>=0,A22,"") -> 2
A23: 3 | B23: =$B$4*(1+$B$16)^A23 -> 171475 | C23: =IF(OR($E$4=0,A23>=$B$8),0,IF($E$5=0,$E$4-12*A23*$E$7,$E$4*(1+$E$5)^(12*A23)-$E$7*((1+$E$5)^(12*A23)-1)/$E$5)) -> 0 | D23: =IF(A23<=$B$8,12*$E$7,0)+($B$10+$B$11+$B$12)*$B$4*(1+$B$16)^(A23-1) -> 0 | E23: =D23/(1+$B$15)^A23 -> 0 | F23: =SUM($E$21:E23) -> 0 | G23: =12*$B$5*(1+$B$17)^(A23-1) -> 12000 | H23: =G23/(1+$B$15)^A23 -> 12000 | I23: =SUM($H$21:H23) -> 36000 | J23: =($B$6+$B$13)*$B$4+F23-(B23*(1-$B$14)-C23)/(1+$B$15)^A23 -> 28525 | K23: =I23-J23 -> 7475 | L23: =IF(K23>=0,A23,"") -> 3
A24: 4 | B24: =$B$4*(1+$B$16)^A24 -> 162901.25 | C24: =IF(OR($E$4=0,A24>=$B$8),0,IF($E$5=0,$E$4-12*A24*$E$7,$E$4*(1+$E$5)^(12*A24)-$E$7*((1+$E$5)^(12*A24)-1)/$E$5)) -> 0 | D24: =IF(A24<=$B$8,12*$E$7,0)+($B$10+$B$11+$B$12)*$B$4*(1+$B$16)^(A24-1) -> 0 | E24: =D24/(1+$B$15)^A24 -> 0 | F24: =SUM($E$21:E24) -> 0 | G24: =12*$B$5*(1+$B$17)^(A24-1) -> 12000 | H24: =G24/(1+$B$15)^A24 -> 12000 | I24: =SUM($H$21:H24) -> 48000 | J24: =($B$6+$B$13)*$B$4+F24-(B24*(1-$B$14)-C24)/(1+$B$15)^A24 -> 37098.75 | K24: =I24-J24 -> 10901.25 | L24: =IF(K24>=0,A24,"") -> 4
A25: 5 | B25: =$B$4*(1+$B$16)^A25 -> 154756.19 | C25: =IF(OR($E$4=0,A25>=$B$8),0,IF($E$5=0,$E$4-12*A25*$E$7,$E$4*(1+$E$5)^(12*A25)-$E$7*((1+$E$5)^(12*A25)-1)/$E$5)) -> 0 | D25: =IF(A25<=$B$8,12*$E$7,0)+($B$10+$B$11+$B$12)*$B$4*(1+$B$16)^(A25-1) -> 0 | E25: =D25/(1+$B$15)^A25 -> 0 | F25: =SUM($E$21:E25) -> 0 | G25: =12*$B$5*(1+$B$17)^(A25-1) -> 12000 | H25: =G25/(1+$B$15)^A25 -> 12000 | I25: =SUM($H$21:H25) -> 60000 | J25: =($B$6+$B$13)*$B$4+F25-(B25*(1-$B$14)-C25)/(1+$B$15)^A25 -> 45243.812 | K25: =I25-J25 -> 14756.188 | L25: =IF(K25>=0,A25,"") -> 5
A26: 6 | B26: =$B$4*(1+$B$16)^A26 -> 147018.38 | C26: =IF(OR($E$4=0,A26>=$B$8),0,IF($E$5=0,$E$4-12*A26*$E$7,$E$4*(1+$E$5)^(12*A26)-$E$7*((1+$E$5)^(12*A26)-1)/$E$5)) -> 0 | D26: =IF(A26<=$B$8,12*$E$7,0)+($B$10+$B$11+$B$12)*$B$4*(1+$B$16)^(A26-1) -> 0 | E26: =D26/(1+$B$15)^A26 -> 0 | F26: =SUM($E$21:E26) -> 0 | G26: =12*$B$5*(1+$B$17)^(A26-1) -> 12000 | H26: =G26/(1+$B$15)^A26 -> 12000 | I26: =SUM($H$21:H26) -> 72000 | J26: =($B$6+$B$13)*$B$4+F26-(B26*(1-$B$14)-C26)/(1+$B$15)^A26 -> 52981.622 | K26: =I26-J26 -> 19018.378 | L26: =IF(K26>=0,A26,"") -> 6
A27: 7 | B27: =$B$4*(1+$B$16)^A27 -> 139667.46 | C27: =IF(OR($E$4=0,A27>=$B$8),0,IF($E$5=0,$E$4-12*A27*$E$7,$E$4*(1+$E$5)^(12*A27)-$E$7*((1+$E$5)^(12*A27)-1)/$E$5)) -> 0 | D27: =IF(A27<=$B$8,12*$E$7,0)+($B$10+$B$11+$B$12)*$B$4*(1+$B$16)^(A27-1) -> 0 | E27: =D27/(1+$B$15)^A27 -> 0 | F27: =SUM($E$21:E27) -> 0 | G27: =12*$B$5*(1+$B$17)^(A27-1) -> 12000 | H27: =G27/(1+$B$15)^A27 -> 12000 | I27: =SUM($H$21:H27) -> 84000 | J27: =($B$6+$B$13)*$B$4+F27-(B27*(1-$B$14)-C27)/(1+$B$15)^A27 -> 60332.541 | K27: =I27-J27 -> 23667.459 | L27: =IF(K27>=0,A27,"") -> 7
A28: 8 | B28: =$B$4*(1+$B$16)^A28 -> 132684.09 | C28: =IF(OR($E$4=0,A28>=$B$8),0,IF($E$5=0,$E$4-12*A28*$E$7,$E$4*(1+$E$5)^(12*A28)-$E$7*((1+$E$5)^(12*A28)-1)/$E$5)) -> 0 | D28: =IF(A28<=$B$8,12*$E$7,0)+($B$10+$B$11+$B$12)*$B$4*(1+$B$16)^(A28-1) -> 0 | E28: =D28/(1+$B$15)^A28 -> 0 | F28: =SUM($E$21:E28) -> 0 | G28: =12*$B$5*(1+$B$17)^(A28-1) -> 12000 | H28: =G28/(1+$B$15)^A28 -> 12000 | I28: =SUM($H$21:H28) -> 96000 | J28: =($B$6+$B$13)*$B$4+F28-(B28*(1-$B$14)-C28)/(1+$B$15)^A28 -> 67315.914 | K28: =I28-J28 -> 28684.086 | L28: =IF(K28>=0,A28,"") -> 8
A29: 9 | B29: =$B$4*(1+$B$16)^A29 -> 126049.88 | C29: =IF(OR($E$4=0,A29>=$B$8),0,IF($E$5=0,$E$4-12*A29*$E$7,$E$4*(1+$E$5)^(12*A29)-$E$7*((1+$E$5)^(12*A29)-1)/$E$5)) -> 0 | D29: =IF(A29<=$B$8,12*$E$7,0)+($B$10+$B$11+$B$12)*$B$4*(1+$B$16)^(A29-1) -> 0 | E29: =D29/(1+$B$15)^A29 -> 0 | F29: =SUM($E$21:E29) -> 0 | G29: =12*$B$5*(1+$B$17)^(A29-1) -> 12000 | H29: =G29/(1+$B$15)^A29 -> 12000 | I29: =SUM($H$21:H29) -> 108000 | J29: =($B$6+$B$13)*$B$4+F29-(B29*(1-$B$14)-C29)/(1+$B$15)^A29 -> 73950.118 | K29: =I29-J29 -> 34049.882 | L29: =IF(K29>=0,A29,"") -> 9
A30: 10 | B30: =$B$4*(1+$B$16)^A30 -> 119747.39 | C30: =IF(OR($E$4=0,A30>=$B$8),0,IF($E$5=0,$E$4-12*A30*$E$7,$E$4*(1+$E$5)^(12*A30)-$E$7*((1+$E$5)^(12*A30)-1)/$E$5)) -> 0 | D30: =IF(A30<=$B$8,12*$E$7,0)+($B$10+$B$11+$B$12)*$B$4*(1+$B$16)^(A30-1) -> 0 | E30: =D30/(1+$B$15)^A30 -> 0 | F30: =SUM($E$21:E30) -> 0 | G30: =12*$B$5*(1+$B$17)^(A30-1) -> 12000 | H30: =G30/(1+$B$15)^A30 -> 12000 | I30: =SUM($H$21:H30) -> 120000 | J30: =($B$6+$B$13)*$B$4+F30-(B30*(1-$B$14)-C30)/(1+$B$15)^A30 -> 80252.612 | K30: =I30-J30 -> 39747.388 | L30: =IF(K30>=0,A30,"") -> 10
A31: 11 | B31: =$B$4*(1+$B$16)^A31 -> 113760.02 | C31: =IF(OR($E$4=0,A31>=$B$8),0,IF($E$5=0,$E$4-12*A31*$E$7,$E$4*(1+$E$5)^(12*A31)-$E$7*((1+$E$5)^(12*A31)-1)/$E$5)) -> 0 | D31: =IF(A31<=$B$8,12*$E$7,0)+($B$10+$B$11+$B$12)*$B$4*(1+$B$16)^(A31-1) -> 0 | E31: =D31/(1+$B$15)^A31 -> 0 | F31: =SUM($E$21:E31) -> 0 | G31: =12*$B$5*(1+$B$17)^(A31-1) -> 12000 | H31: =G31/(1+$B$15)^A31 -> 12000 | I31: =SUM($H$21:H31) -> 132000 | J31: =($B$6+$B$13)*$B$4+F31-(B31*(1-$B$14)-C31)/(1+$B$15)^A31 -> 86239.982 | K31: =I31-J31 -> 45760.018 | L31: =IF(K31>=0,A31,"") -> 11
A32: 12 | B32: =$B$4*(1+$B$16)^A32 -> 108072.02 | C32: =IF(OR($E$4=0,A32>=$B$8),0,IF($E$5=0,$E$4-12*A32*$E$7,$E$4*(1+$E$5)^(12*A32)-$E$7*((1+$E$5)^(12*A32)-1)/$E$5)) -> 0 | D32: =IF(A32<=$B$8,12*$E$7,0)+($B$10+$B$11+$B$12)*$B$4*(1+$B$16)^(A32-1) -> 0 | E32: =D32/(1+$B$15)^A32 -> 0 | F32: =SUM($E$21:E32) -> 0 | G32: =12*$B$5*(1+$B$17)^(A32-1) -> 12000 | H32: =G32/(1+$B$15)^A32 -> 12000 | I32: =SUM($H$21:H32) -> 144000 | J32: =($B$6+$B$13)*$B$4+F32-(B32*(1-$B$14)-C32)/(1+$B$15)^A32 -> 91927.982 | K32: =I32-J32 -> 52072.018 | L32: =IF(K32>=0,A32,"") -> 12
... A50: 30 | B50: =$B$4*(1+$B$16)^A50 -> 42927.753 | C50: =IF(OR($E$4=0,A50>=$B$8),0,IF($E$5=0,$E$4-12*A50*$E$7,$E$4*(1+$E$5)^(12*A50)-$E$7*((1+$E$5)^(12*A50)-1)/$E$5)) -> 0 | D50: =IF(A50<=$B$8,12*$E$7,0)+($B$10+$B$11+$B$12)*$B$4*(1+$B$16)^(A50-1) -> 0 | E50: =D50/(1+$B$15)^A50 -> 0 | F50: =SUM($E$21:E50) -> 0 | G50: =12*$B$5*(1+$B$17)^(A50-1) -> 12000 | H50: =G50/(1+$B$15)^A50 -> 12000 | I50: =SUM($H$21:H50) -> 360000 | J50: =($B$6+$B$13)*$B$4+F50-(B50*(1-$B$14)-C50)/(1+$B$15)^A50 -> 157072.25 | K50: =I50-J50 -> 202927.75 | L50: =IF(K50>=0,A50,"") -> 30

Sheet S11
A1: S11: Typical case: defaults, latest mortgage rate and forecasts
A2: Hand calculation: No closed form; checked against the independent monthly calculation and the Excel formulas (r = Sep 2025 mortgage rate, g and q = mean forecasts).
A3: Inputs (blue: edit to explore) | D3: Results (Excel formulas)
A4: Price P ($) | B4: 400000 | D4: Loan L = (1-d)P | E4: =(1-$B$6)*$B$4 -> 320000
A5: Monthly rent R ($) | B5: 2000 | D5: Monthly rate i = r/12 | E5: =$B$7/12 -> 0.00529375
A6: Down payment d | B6: 0.2 | D6: Number of payments n = 12T | E6: =12*$B$8 -> 360
A7: Mortgage rate r | B7: 0.063525 | D7: Monthly payment M | E7: =IF($E$4=0,0,IF($E$5=0,$E$4/$E$6,$E$4*$E$5*(1+$E$5)^$E$6/((1+$E$5)^$E$6-1))) -> 1991.6769 | H7: 1991.6769 | I7: =IF(ABS(E7-H7)<0.01,"PASS","FAIL") -> PASS
A8: Mortgage term T (years) | B8: 30 | G8: Hand calculation | H8: Python engine | I8: Excel vs engine | J8: Excel vs hand
A9: Holding period H (years) | B9: 7 | D9: C_B(H) cost of buying (PV) | E9: =INDEX(J21:J50,$B$9) -> 149467.46 | H9: 149467.46 | I9: =IF(ABS(E9-H9)<0.01,"PASS","FAIL") -> PASS
A10: Property tax tau | B10: 0.01 | D10: C_R(H) cost of renting (PV) | E10: =INDEX(I21:I50,$B$9) -> 153609.24 | H10: 153609.24 | I10: =IF(ABS(E10-H10)<0.01,"PASS","FAIL") -> PASS
A11: Maintenance m | B11: 0.01 | D11: Delta(H) = C_R - C_B | E11: =INDEX(K21:K50,$B$9) -> 4141.7716 | H11: 4141.7716 | I11: =IF(ABS(E11-H11)<0.01,"PASS","FAIL") -> PASS
A12: Insurance h | B12: 0.0035 | D12: Recommendation at H | E12: =IF(E11>=0,"buy","rent") -> buy | H12: buy | I12: =IF(E12=H12,"PASS","FAIL") -> PASS
A13: Buying costs cb | B13: 0.03 | D13: Break-even year (search 1-30) | E13: =IF(COUNT(L21:L50)=0,"never",MIN(L21:L50)) -> 7 | H13: 7 | I13: =IF(ABS(E13-H13)<0.01,"PASS","FAIL") -> PASS
A14: Selling costs cs | B14: 0.06 | D14: User cost UC = (k+tau+m+h-g)P | E14: =($B$15+$B$10+$B$11+$B$12-$B$16)*$B$4 -> 14280 | H14: 14280 | I14: =IF(ABS(E14-H14)<0.01,"PASS","FAIL") -> PASS
A15: Discount rate k | B15: 0.05 | D15: Annual rent 12R | E15: =12*$B$5 -> 24000 | H15: 24000 | I15: =IF(ABS(E15-H15)<0.01,"PASS","FAIL") -> PASS
A16: Appreciation g | B16: 0.0378 | D16: Loan balance B_H | E16: =INDEX(C21:C50,$B$9) -> 288613.98 | H16: 288613.98 | I16: =IF(ABS(E16-H16)<0.01,"PASS","FAIL") -> PASS
A17: Rent growth q | B17: 0.0357 | G17: Hand and Python values are pasted for the inputs above; if you edit an input, only the Excel column updates.
A19: Year-by-year (selling at the end of year t)
A20: Year t | B20: Home value V_t | C20: Loan balance B_t | D20: Owner cost O_t | E20: PV of O_t | F20: Sum PV O (1..t) | G20: Rent_t | H20: PV of Rent_t | I20: C_R(t) | J20: C_B(t) | K20: Delta(t) = C_R - C_B | L20: Break-even helper
A21: 1 | B21: =$B$4*(1+$B$16)^A21 -> 415120 | C21: =IF(OR($E$4=0,A21>=$B$8),0,IF($E$5=0,$E$4-12*A21*$E$7,$E$4*(1+$E$5)^(12*A21)-$E$7*((1+$E$5)^(12*A21)-1)/$E$5)) -> 316322.01 | D21: =IF(A21<=$B$8,12*$E$7,0)+($B$10+$B$11+$B$12)*$B$4*(1+$B$16)^(A21-1) -> 33300.123 | E21: =D21/(1+$B$15)^A21 -> 31714.403 | F21: =SUM($E$21:E21) -> 31714.403 | G21: =12*$B$5*(1+$B$17)^(A21-1) -> 24000 | H21: =G21/(1+$B$15)^A21 -> 22857.143 | I21: =SUM($H$21:H21) -> 22857.143 | J21: =($B$6+$B$13)*$B$4+F21-(B21*(1-$B$14)-C21)/(1+$B$15)^A21 -> 53342.227 | K21: =I21-J21 -> -30485.084 | L21: =IF(K21>=0,A21,"")
A22: 2 | B22: =$B$4*(1+$B$16)^A22 -> 430811.54 | C22: =IF(OR($E$4=0,A22>=$B$8),0,IF($E$5=0,$E$4-12*A22*$E$7,$E$4*(1+$E$5)^(12*A22)-$E$7*((1+$E$5)^(12*A22)-1)/$E$5)) -> 312403.46 | D22: =IF(A22<=$B$8,12*$E$7,0)+($B$10+$B$11+$B$12)*$B$4*(1+$B$16)^(A22-1) -> 33655.443 | E22: =D22/(1+$B$15)^A22 -> 30526.479 | F22: =SUM($E$21:E22) -> 62240.882 | G22: =12*$B$5*(1+$B$17)^(A22-1) -> 24856.8 | H22: =G22/(1+$B$15)^A22 -> 22545.85 | I22: =SUM($H$21:H22) -> 45402.993 | J22: =($B$6+$B$13)*$B$4+F22-(B22*(1-$B$14)-C22)/(1+$B$15)^A22 -> 70286.794 | K22: =I22-J22 -> -24883.801 | L22: =IF(K22>=0,A22,"")
A23: 3 | B23: =$B$4*(1+$B$16)^A23 -> 447096.21 | C23: =IF(OR($E$4=0,A23>=$B$8),0,IF($E$5=0,$E$4-12*A23*$E$7,$E$4*(1+$E$5)^(12*A23)-$E$7*((1+$E$5)^(12*A23)-1)/$E$5)) -> 308228.61 | D23: =IF(A23<=$B$8,12*$E$7,0)+($B$10+$B$11+$B$12)*$B$4*(1+$B$16)^(A23-1) -> 34024.194 | E23: =D23/(1+$B$15)^A23 -> 29391.378 | F23: =SUM($E$21:E23) -> 91632.261 | G23: =12*$B$5*(1+$B$17)^(A23-1) -> 25744.188 | H23: =G23/(1+$B$15)^A23 -> 22238.797 | I23: =SUM($H$21:H23) -> 67641.791 | J23: =($B$6+$B$13)*$B$4+F23-(B23*(1-$B$14)-C23)/(1+$B$15)^A23 -> 86846.311 | K23: =I23-J23 -> -19204.521 | L23: =IF(K23>=0,A23,"")
A24: 4 | B24: =$B$4*(1+$B$16)^A24 -> 463996.45 | C24: =IF(OR($E$4=0,A24>=$B$8),0,IF($E$5=0,$E$4-12*A24*$E$7,$E$4*(1+$E$5)^(12*A24)-$E$7*((1+$E$5)^(12*A24)-1)/$E$5)) -> 303780.68 | D24: =IF(A24<=$B$8,12*$E$7,0)+($B$10+$B$11+$B$12)*$B$4*(1+$B$16)^(A24-1) -> 34406.884 | E24: =D24/(1+$B$15)^A24 -> 28306.629 | F24: =SUM($E$21:E24) -> 119938.89 | G24: =12*$B$5*(1+$B$17)^(A24-1) -> 26663.255 | H24: =G24/(1+$B$15)^A24 -> 21935.926 | I24: =SUM($H$21:H24) -> 89577.717 | J24: =($B$6+$B$13)*$B$4+F24-(B24*(1-$B$14)-C24)/(1+$B$15)^A24 -> 103032.84 | K24: =I24-J24 -> -13455.126 | L24: =IF(K24>=0,A24,"")
A25: 5 | B25: =$B$4*(1+$B$16)^A25 -> 481535.51 | C25: =IF(OR($E$4=0,A25>=$B$8),0,IF($E$5=0,$E$4-12*A25*$E$7,$E$4*(1+$E$5)^(12*A25)-$E$7*((1+$E$5)^(12*A25)-1)/$E$5)) -> 299041.83 | D25: =IF(A25<=$B$8,12*$E$7,0)+($B$10+$B$11+$B$12)*$B$4*(1+$B$16)^(A25-1) -> 34804.04 | E25: =D25/(1+$B$15)^A25 -> 27269.876 | F25: =SUM($E$21:E25) -> 147208.77 | G25: =12*$B$5*(1+$B$17)^(A25-1) -> 27615.133 | H25: =G25/(1+$B$15)^A25 -> 21637.18 | I25: =SUM($H$21:H25) -> 111214.9 | J25: =($B$6+$B$13)*$B$4+F25-(B25*(1-$B$14)-C25)/(1+$B$15)^A25 -> 118857.93 | K25: =I25-J25 -> -7643.0319 | L25: =IF(K25>=0,A25,"")
A26: 6 | B26: =$B$4*(1+$B$16)^A26 -> 499737.56 | C26: =IF(OR($E$4=0,A26>=$B$8),0,IF($E$5=0,$E$4-12*A26*$E$7,$E$4*(1+$E$5)^(12*A26)-$E$7*((1+$E$5)^(12*A26)-1)/$E$5)) -> 293993.02 | D26: =IF(A26<=$B$8,12*$E$7,0)+($B$10+$B$11+$B$12)*$B$4*(1+$B$16)^(A26-1) -> 35216.208 | E26: =D26/(1+$B$15)^A26 -> 26278.877 | F26: =SUM($E$21:E26) -> 173487.64 | G26: =12*$B$5*(1+$B$17)^(A26-1) -> 28600.994 | H26: =G26/(1+$B$15)^A26 -> 21342.502 | I26: =SUM($H$21:H26) -> 132557.4 | J26: =($B$6+$B$13)*$B$4+F26-(B26*(1-$B$14)-C26)/(1+$B$15)^A26 -> 134332.61 | K26: =I26-J26 -> -1775.2142 | L26: =IF(K26>=0,A26,"")
A27: 7 | B27: =$B$4*(1+$B$16)^A27 -> 518627.64 | C27: =IF(OR($E$4=0,A27>=$B$8),0,IF($E$5=0,$E$4-12*A27*$E$7,$E$4*(1+$E$5)^(12*A27)-$E$7*((1+$E$5)^(12*A27)-1)/$E$5)) -> 288613.98 | D27: =IF(A27<=$B$8,12*$E$7,0)+($B$10+$B$11+$B$12)*$B$4*(1+$B$16)^(A27-1) -> 35643.956 | E27: =D27/(1+$B$15)^A27 -> 25331.494 | F27: =SUM($E$21:E27) -> 198819.14 | G27: =12*$B$5*(1+$B$17)^(A27-1) -> 29622.049 | H27: =G27/(1+$B$15)^A27 -> 21051.837 | I27: =SUM($H$21:H27) -> 153609.24 | J27: =($B$6+$B$13)*$B$4+F27-(B27*(1-$B$14)-C27)/(1+$B$15)^A27 -> 149467.46 | K27: =I27-J27 -> 4141.7716 | L27: =IF(K27>=0,A27,"") -> 7
A28: 8 | B28: =$B$4*(1+$B$16)^A28 -> 538231.76 | C28: =IF(OR($E$4=0,A28>=$B$8),0,IF($E$5=0,$E$4-12*A28*$E$7,$E$4*(1+$E$5)^(12*A28)-$E$7*((1+$E$5)^(12*A28)-1)/$E$5)) -> 282883.11 | D28: =IF(A28<=$B$8,12*$E$7,0)+($B$10+$B$11+$B$12)*$B$4*(1+$B$16)^(A28-1) -> 36087.873 | E28: =D28/(1+$B$15)^A28 -> 24425.693 | F28: =SUM($E$21:E28) -> 223244.83 | G28: =12*$B$5*(1+$B$17)^(A28-1) -> 30679.556 | H28: =G28/(1+$B$15)^A28 -> 20765.131 | I28: =SUM($H$21:H28) -> 174374.37 | J28: =($B$6+$B$13)*$B$4+F28-(B28*(1-$B$14)-C28)/(1+$B$15)^A28 -> 164272.6 | K28: =I28-J28 -> 10101.769 | L28: =IF(K28>=0,A28,"") -> 8
A29: 9 | B29: =$B$4*(1+$B$16)^A29 -> 558576.92 | C29: =IF(OR($E$4=0,A29>=$B$8),0,IF($E$5=0,$E$4-12*A29*$E$7,$E$4*(1+$E$5)^(12*A29)-$E$7*((1+$E$5)^(12*A29)-1)/$E$5)) -> 276777.4 | D29: =IF(A29<=$B$8,12*$E$7,0)+($B$10+$B$11+$B$12)*$B$4*(1+$B$16)^(A29-1) -> 36548.57 | E29: =D29/(1+$B$15)^A29 -> 23559.534 | F29: =SUM($E$21:E29) -> 246804.36 | G29: =12*$B$5*(1+$B$17)^(A29-1) -> 31774.817 | H29: =G29/(1+$B$15)^A29 -> 20482.33 | I29: =SUM($H$21:H29) -> 194856.7 | J29: =($B$6+$B$13)*$B$4+F29-(B29*(1-$B$14)-C29)/(1+$B$15)^A29 -> 178757.7 | K29: =I29-J29 -> 16098.999 | L29: =IF(K29>=0,A29,"") -> 9
A30: 10 | B30: =$B$4*(1+$B$16)^A30 -> 579691.13 | C30: =IF(OR($E$4=0,A30>=$B$8),0,IF($E$5=0,$E$4-12*A30*$E$7,$E$4*(1+$E$5)^(12*A30)-$E$7*((1+$E$5)^(12*A30)-1)/$E$5)) -> 270272.33 | D30: =IF(A30<=$B$8,12*$E$7,0)+($B$10+$B$11+$B$12)*$B$4*(1+$B$16)^(A30-1) -> 37026.681 | E30: =D30/(1+$B$15)^A30 -> 22731.17 | F30: =SUM($E$21:E30) -> 269535.53 | G30: =12*$B$5*(1+$B$17)^(A30-1) -> 32909.177 | H30: =G30/(1+$B$15)^A30 -> 20203.38 | I30: =SUM($H$21:H30) -> 215060.08 | J30: =($B$6+$B$13)*$B$4+F30-(B30*(1-$B$14)-C30)/(1+$B$15)^A30 -> 192932.03 | K30: =I30-J30 -> 22128.043 | L30: =IF(K30>=0,A30,"") -> 10
A31: 11 | B31: =$B$4*(1+$B$16)^A31 -> 601603.45 | C31: =IF(OR($E$4=0,A31>=$B$8),0,IF($E$5=0,$E$4-12*A31*$E$7,$E$4*(1+$E$5)^(12*A31)-$E$7*((1+$E$5)^(12*A31)-1)/$E$5)) -> 263341.78 | D31: =IF(A31<=$B$8,12*$E$7,0)+($B$10+$B$11+$B$12)*$B$4*(1+$B$16)^(A31-1) -> 37522.865 | E31: =D31/(1+$B$15)^A31 -> 21938.842 | F31: =SUM($E$21:E31) -> 291474.37 | G31: =12*$B$5*(1+$B$17)^(A31-1) -> 34084.035 | H31: =G31/(1+$B$15)^A31 -> 19928.229 | I31: =SUM($H$21:H31) -> 234988.31 | J31: =($B$6+$B$13)*$B$4+F31-(B31*(1-$B$14)-C31)/(1+$B$15)^A31 -> 206804.48 | K31: =I31-J31 -> 28183.825 | L31: =IF(K31>=0,A31,"") -> 11
A32: 12 | B32: =$B$4*(1+$B$16)^A32 -> 624344.06 | C32: =IF(OR($E$4=0,A32>=$B$8),0,IF($E$5=0,$E$4-12*A32*$E$7,$E$4*(1+$E$5)^(12*A32)-$E$7*((1+$E$5)^(12*A32)-1)/$E$5)) -> 255957.91 | D32: =IF(A32<=$B$8,12*$E$7,0)+($B$10+$B$11+$B$12)*$B$4*(1+$B$16)^(A32-1) -> 38037.804 | E32: =D32/(1+$B$15)^A32 -> 21180.873 | F32: =SUM($E$21:E32) -> 312655.25 | G32: =12*$B$5*(1+$B$17)^(A32-1) -> 35300.835 | H32: =G32/(1+$B$15)^A32 -> 19656.826 | I32: =SUM($H$21:H32) -> 254645.13 | J32: =($B$6+$B$13)*$B$4+F32-(B32*(1-$B$14)-C32)/(1+$B$15)^A32 -> 220383.54 | K32: =I32-J32 -> 34261.591 | L32: =IF(K32>=0,A32,"") -> 12
... A50: 30 | B50: =$B$4*(1+$B$16)^A50 -> 1217502.8 | C50: =IF(OR($E$4=0,A50>=$B$8),0,IF($E$5=0,$E$4-12*A50*$E$7,$E$4*(1+$E$5)^(12*A50)-$E$7*((1+$E$5)^(12*A50)-1)/$E$5)) -> 0 | D50: =IF(A50<=$B$8,12*$E$7,0)+($B$10+$B$11+$B$12)*$B$4*(1+$B$16)^(A50-1) -> 51469.324 | E50: =D50/(1+$B$15)^A50 -> 11908.841 | F50: =SUM($E$21:E50) -> 595271.22 | G50: =12*$B$5*(1+$B$17)^(A50-1) -> 66373.78 | H50: =G50/(1+$B$15)^A50 -> 15357.396 | I50: =SUM($H$21:H50) -> 566038.11 | J50: =($B$6+$B$13)*$B$4+F50-(B50*(1-$B$14)-C50)/(1+$B$15)^A50 -> 422470.69 | K50: =I50-J50 -> 143567.43 | L50: =IF(K50>=0,A50,"") -> 30
